Workbook
Name UPDATE: 'Data Sheet'!$E$1

Sheet Cover
B2: Financial Statement Analysis & Valuation (FSAV)
B3: Term Project
B6: Hindustan Unilever Limited
B7: Fast Moving Consumer Goods | NSE: HINDUNILVR | BSE: 500696
B9: Project Details
B10: Submitted by | C10: Group 8
B11: Submitted to | C11: Dr. Kunal Saigal and Dr. Kriti Sharma
B12: Programme and Section | C12: PGDM - Sec A
B13: Date of submission | C13: 46249
B14: Period of analysis | C14: FY2017 to FY2026 (ten financial years)
B15: Projection period | C15: FY2027E to FY2031E (five years), with a terminal value thereafter
B16: Reporting currency and units | C16: Indian Rupees in crore, unless stated otherwise
B17: Sources of data | C17: Audited annual reports of Hindustan Unilever Ltd., Screener.in and NSE market data
B19: Contents
B20: Worksheet | C20: Purpose
B21: Assumptions Summary | C21: Consolidated list of every assumption used across the project, with its basis
B22: Profit & Loss | C22: Reported statement of profit and loss, FY2017 to FY2026
B23: Balance Sheet | C23: Reported balance sheet, FY2017 to FY2026
B24: Cash Flow | C24: Reported cash flow statement, FY2017 to FY2026
B25: Quarters | C25: Quarterly results used to assess recent operating momentum
B26: Data Sheet | C26: Underlying data extract on which the analysis worksheets are built
B27: Cash Flow Data | C27: Supporting workings for the cash flow analysis
B28: Common Size Statement | C28: Vertical analysis of the profit and loss account and balance sheet
B29: Comparative Statement | C29: Horizontal (year on year) analysis of the financial statements
B30: Ratio analysis | C30: Liquidity, profitability, efficiency, solvency and market ratios
B31: Altman Z Score | C31: Assessment of financial distress and bankruptcy risk
... B38: Customization | C38: Settings used by the source data template

Sheet Dashboard
A1: Hindustan Unilever Ltd. — Financial Dashboard
A2: Key Metrics & Trend Analysis | FY2017–FY2026 | Rs. crore unless stated otherwise
A4: KEY METRICS — FY2026
B5: REVENUE (RS. CR) | F5: NET PROFIT (RS. CR) | J5: NET PROFIT MARGIN | N5: RETURN ON EQUITY
B6: ='Profit & Loss'!K4 -> 64468 | F6: ='Profit & Loss'!K12 -> 15040 | J6: ='Ratio analysis'!L10 -> 0.23329404 | N6: ='Ratio analysis'!L12 -> 0.30649779
B8: EPS (RS.) | F8: P/E RATIO (X) | J8: CURRENT RATIO (X) | N8: DEBT-EQUITY (X)
B9: ='Profit & Loss'!K13 -> 64.010895 | F9: ='Ratio analysis'!L28 -> 32.107034 | J9: ='Ratio analysis'!L4 -> 0.57826632 | N9: ='Ratio analysis'!L22 -> 0.060239859
A11: CHARTS
A98: CHART SOURCE DATA — feeds the charts above, do not delete
A100: Year | B100: Revenue (Rs. cr) | C100: Net Profit (Rs. cr)
A101: {=INDEX('Ratio analysis'!$C$2:$L$2,ROW()-100)} -> FY17 | B101: {=INDEX('Profit & Loss'!$B$4:$K$4,ROW()-100)} -> 33162 | C101: {=INDEX('Profit & Loss'!$B$12:$K$12,ROW()-100)} -> 4476
A102: {=INDEX('Ratio analysis'!$C$2:$L$2,ROW()-100)} -> FY18 | B102: {=INDEX('Profit & Loss'!$B$4:$K$4,ROW()-100)} -> 35545 | C102: {=INDEX('Profit & Loss'!$B$12:$K$12,ROW()-100)} -> 5214
A103: {=INDEX('Ratio analysis'!$C$2:$L$2,ROW()-100)} -> FY19 | B103: {=INDEX('Profit & Loss'!$B$4:$K$4,ROW()-100)} -> 39310 | C103: {=INDEX('Profit & Loss'!$B$12:$K$12,ROW()-100)} -> 6054
A104: {=INDEX('Ratio analysis'!$C$2:$L$2,ROW()-100)} -> FY20 | B104: {=INDEX('Profit & Loss'!$B$4:$K$4,ROW()-100)} -> 39783 | C104: {=INDEX('Profit & Loss'!$B$12:$K$12,ROW()-100)} -> 6748
A105: {=INDEX('Ratio analysis'!$C$2:$L$2,ROW()-100)} -> FY21 | B105: {=INDEX('Profit & Loss'!$B$4:$K$4,ROW()-100)} -> 47028 | C105: {=INDEX('Profit & Loss'!$B$12:$K$12,ROW()-100)} -> 7995
A106: {=INDEX('Ratio analysis'!$C$2:$L$2,ROW()-100)} -> FY22 | B106: {=INDEX('Profit & Loss'!$B$4:$K$4,ROW()-100)} -> 52446 | C106: {=INDEX('Profit & Loss'!$B$12:$K$12,ROW()-100)} -> 8879
A107: {=INDEX('Ratio analysis'!$C$2:$L$2,ROW()-100)} -> FY23 | B107: {=INDEX('Profit & Loss'!$B$4:$K$4,ROW()-100)} -> 60580 | C107: {=INDEX('Profit & Loss'!$B$12:$K$12,ROW()-100)} -> 10120
A108: {=INDEX('Ratio analysis'!$C$2:$L$2,ROW()-100)} -> FY24 | B108: {=INDEX('Profit & Loss'!$B$4:$K$4,ROW()-100)} -> 61896 | C108: {=INDEX('Profit & Loss'!$B$12:$K$12,ROW()-100)} -> 10277
A109: {=INDEX('Ratio analysis'!$C$2:$L$2,ROW()-100)} -> FY25 | B109: {=INDEX('Profit & Loss'!$B$4:$K$4,ROW()-100)} -> 61328 | C109: {=INDEX('Profit & Loss'!$B$12:$K$12,ROW()-100)} -> 10649
A110: {=INDEX('Ratio analysis'!$C$2:$L$2,ROW()-100)} -> FY26 | B110: {=INDEX('Profit & Loss'!$B$4:$K$4,ROW()-100)} -> 64468 | C110: {=INDEX('Profit & Loss'!$B$12:$K$12,ROW()-100)} -> 15040
A112: Year | B112: Operating Profit Margin | C112: Net Profit Margin
A113: {=INDEX('Ratio analysis'!$C$2:$L$2,ROW()-112)} -> FY17 | B113: {=INDEX('Ratio analysis'!$C$9:$L$9,ROW()-112)} -> 0.19606779 | C113: {=INDEX('Ratio analysis'!$C$10:$L$10,ROW()-112)} -> 0.13497377
A114: {=INDEX('Ratio analysis'!$C$2:$L$2,ROW()-112)} -> FY18 | B114: {=INDEX('Ratio analysis'!$C$9:$L$9,ROW()-112)} -> 0.20627374 | C114: {=INDEX('Ratio analysis'!$C$10:$L$10,ROW()-112)} -> 0.1466873
A115: {=INDEX('Ratio analysis'!$C$2:$L$2,ROW()-112)} -> FY19 | B115: {=INDEX('Ratio analysis'!$C$9:$L$9,ROW()-112)} -> 0.21971509 | C115: {=INDEX('Ratio analysis'!$C$10:$L$10,ROW()-112)} -> 0.15400661
A116: {=INDEX('Ratio analysis'!$C$2:$L$2,ROW()-112)} -> FY20 | B116: {=INDEX('Ratio analysis'!$C$9:$L$9,ROW()-112)} -> 0.23334087 | C116: {=INDEX('Ratio analysis'!$C$10:$L$10,ROW()-112)} -> 0.16962019
A117: {=INDEX('Ratio analysis'!$C$2:$L$2,ROW()-112)} -> FY21 | B117: {=INDEX('Ratio analysis'!$C$9:$L$9,ROW()-112)} -> 0.22799183 | C117: {=INDEX('Ratio analysis'!$C$10:$L$10,ROW()-112)} -> 0.1700051
A118: {=INDEX('Ratio analysis'!$C$2:$L$2,ROW()-112)} -> FY22 | B118: {=INDEX('Ratio analysis'!$C$9:$L$9,ROW()-112)} -> 0.22852076 | C118: {=INDEX('Ratio analysis'!$C$10:$L$10,ROW()-112)} -> 0.16929794
A119: {=INDEX('Ratio analysis'!$C$2:$L$2,ROW()-112)} -> FY23 | B119: {=INDEX('Ratio analysis'!$C$9:$L$9,ROW()-112)} -> 0.22215253 | C119: {=INDEX('Ratio analysis'!$C$10:$L$10,ROW()-112)} -> 0.16705183
A120: {=INDEX('Ratio analysis'!$C$2:$L$2,ROW()-112)} -> FY24 | B120: {=INDEX('Ratio analysis'!$C$9:$L$9,ROW()-112)} -> 0.23038645 | C120: {=INDEX('Ratio analysis'!$C$10:$L$10,ROW()-112)} -> 0.16603658
A121: {=INDEX('Ratio analysis'!$C$2:$L$2,ROW()-112)} -> FY25 | B121: {=INDEX('Ratio analysis'!$C$9:$L$9,ROW()-112)} -> 0.24132533 | C121: {=INDEX('Ratio analysis'!$C$10:$L$10,ROW()-112)} -> 0.1736401
A122: {=INDEX('Ratio analysis'!$C$2:$L$2,ROW()-112)} -> FY26 | B122: {=INDEX('Ratio analysis'!$C$9:$L$9,ROW()-112)} -> 0.28896507 | C122: {=INDEX('Ratio analysis'!$C$10:$L$10,ROW()-112)} -> 0.23329404
A124: Year | B124: ROA | C124: ROE | D124: ROCE
A125: {=INDEX('Ratio analysis'!$C$2:$L$2,ROW()-124)} -> FY17 | B125: {=INDEX('Ratio analysis'!$C$11:$L$11,ROW()-124)} -> 0.28498663 | C125: {=INDEX('Ratio analysis'!$C$12:$L$12,ROW()-124)} -> 0.66370107 | D125: {=INDEX('Ratio analysis'!$C$13:$L$13,ROW()-124)} -> 0.96411625
A126: {=INDEX('Ratio analysis'!$C$2:$L$2,ROW()-124)} -> FY18 | B126: {=INDEX('Ratio analysis'!$C$11:$L$11,ROW()-124)} -> 0.310653 | C126: {=INDEX('Ratio analysis'!$C$12:$L$12,ROW()-124)} -> 0.74352941 | D126: {=INDEX('Ratio analysis'!$C$13:$L$13,ROW()-124)} -> 1.0455615
A127: {=INDEX('Ratio analysis'!$C$2:$L$2,ROW()-124)} -> FY19 | B127: {=INDEX('Ratio analysis'!$C$11:$L$11,ROW()-124)} -> 0.33180784 | C127: {=INDEX('Ratio analysis'!$C$12:$L$12,ROW()-124)} -> 0.79931344 | D127: {=INDEX('Ratio analysis'!$C$13:$L$13,ROW()-124)} -> 1.1403486
A128: {=INDEX('Ratio analysis'!$C$2:$L$2,ROW()-124)} -> FY20 | B128: {=INDEX('Ratio analysis'!$C$11:$L$11,ROW()-124)} -> 0.34799649 | C128: {=INDEX('Ratio analysis'!$C$12:$L$12,ROW()-124)} -> 0.83846918 | D128: {=INDEX('Ratio analysis'!$C$13:$L$13,ROW()-124)} -> 1.1534543
A129: {=INDEX('Ratio analysis'!$C$2:$L$2,ROW()-124)} -> FY21 | B129: {=INDEX('Ratio analysis'!$C$11:$L$11,ROW()-124)} -> 0.17987918 | C129: {=INDEX('Ratio analysis'!$C$12:$L$12,ROW()-124)} -> 0.28603116 | D129: {=INDEX('Ratio analysis'!$C$13:$L$13,ROW()-124)} -> 0.38359301
A130: {=INDEX('Ratio analysis'!$C$2:$L$2,ROW()-124)} -> FY22 | B130: {=INDEX('Ratio analysis'!$C$11:$L$11,ROW()-124)} -> 0.1275297 | C130: {=INDEX('Ratio analysis'!$C$12:$L$12,ROW()-124)} -> 0.18357368 | D130: {=INDEX('Ratio analysis'!$C$13:$L$13,ROW()-124)} -> 0.24779036
A131: {=INDEX('Ratio analysis'!$C$2:$L$2,ROW()-124)} -> FY23 | B131: {=INDEX('Ratio analysis'!$C$11:$L$11,ROW()-124)} -> 0.14096376 | C131: {=INDEX('Ratio analysis'!$C$12:$L$12,ROW()-124)} -> 0.20369345 | D131: {=INDEX('Ratio analysis'!$C$13:$L$13,ROW()-124)} -> 0.27088009
A132: {=INDEX('Ratio analysis'!$C$2:$L$2,ROW()-124)} -> FY24 | B132: {=INDEX('Ratio analysis'!$C$11:$L$11,ROW()-124)} -> 0.13561089 | C132: {=INDEX('Ratio analysis'!$C$12:$L$12,ROW()-124)} -> 0.20245858 | D132: {=INDEX('Ratio analysis'!$C$13:$L$13,ROW()-124)} -> 0.28092433
A133: {=INDEX('Ratio analysis'!$C$2:$L$2,ROW()-124)} -> FY25 | B133: {=INDEX('Ratio analysis'!$C$11:$L$11,ROW()-124)} -> 0.13449783 | C133: {=INDEX('Ratio analysis'!$C$12:$L$12,ROW()-124)} -> 0.21166766 | D133: {=INDEX('Ratio analysis'!$C$13:$L$13,ROW()-124)} -> 0.29417611
A134: {=INDEX('Ratio analysis'!$C$2:$L$2,ROW()-124)} -> FY26 | B134: {=INDEX('Ratio analysis'!$C$11:$L$11,ROW()-124)} -> 0.18847 | C134: {=INDEX('Ratio analysis'!$C$12:$L$12,ROW()-124)} -> 0.30649779 | D134: {=INDEX('Ratio analysis'!$C$13:$L$13,ROW()-124)} -> 0.37963746
A136: Year | B136: Current Ratio | C136: Quick Ratio
A137: {=INDEX('Ratio analysis'!$C$2:$L$2,ROW()-136)} -> FY17 | B137: {=INDEX('Ratio analysis'!$C$4:$L$4,ROW()-136)} -> 0.83638457 | C137: {=INDEX('Ratio analysis'!$C$5:$L$5,ROW()-136)} -> 0.54381117
A138: {=INDEX('Ratio analysis'!$C$2:$L$2,ROW()-136)} -> FY18 | B138: {=INDEX('Ratio analysis'!$C$4:$L$4,ROW()-136)} -> 0.94509026 | C138: {=INDEX('Ratio analysis'!$C$5:$L$5,ROW()-136)} -> 0.70758907
A139: {=INDEX('Ratio analysis'!$C$2:$L$2,ROW()-136)} -> FY19 | B139: {=INDEX('Ratio analysis'!$C$4:$L$4,ROW()-136)} -> 1.0120979 | C139: {=INDEX('Ratio analysis'!$C$5:$L$5,ROW()-136)} -> 0.77070243
A140: {=INDEX('Ratio analysis'!$C$2:$L$2,ROW()-136)} -> FY20 | B140: {=INDEX('Ratio analysis'!$C$4:$L$4,ROW()-136)} -> 1.0753103 | C140: {=INDEX('Ratio analysis'!$C$5:$L$5,ROW()-136)} -> 0.8432573
A141: {=INDEX('Ratio analysis'!$C$2:$L$2,ROW()-136)} -> FY21 | B141: {=INDEX('Ratio analysis'!$C$4:$L$4,ROW()-136)} -> 0.65712523 | C141: {=INDEX('Ratio analysis'!$C$5:$L$5,ROW()-136)} -> 0.48723061
A142: {=INDEX('Ratio analysis'!$C$2:$L$2,ROW()-136)} -> FY22 | B142: {=INDEX('Ratio analysis'!$C$4:$L$4,ROW()-136)} -> 0.69596118 | C142: {=INDEX('Ratio analysis'!$C$5:$L$5,ROW()-136)} -> 0.49519655
A143: {=INDEX('Ratio analysis'!$C$2:$L$2,ROW()-136)} -> FY23 | B143: {=INDEX('Ratio analysis'!$C$4:$L$4,ROW()-136)} -> 0.76018372 | C143: {=INDEX('Ratio analysis'!$C$5:$L$5,ROW()-136)} -> 0.56295815
A144: {=INDEX('Ratio analysis'!$C$2:$L$2,ROW()-136)} -> FY24 | B144: {=INDEX('Ratio analysis'!$C$4:$L$4,ROW()-136)} -> 0.74048939 | C144: {=INDEX('Ratio analysis'!$C$5:$L$5,ROW()-136)} -> 0.58451933
A145: {=INDEX('Ratio analysis'!$C$2:$L$2,ROW()-136)} -> FY25 | B145: {=INDEX('Ratio analysis'!$C$4:$L$4,ROW()-136)} -> 0.71873807 | C145: {=INDEX('Ratio analysis'!$C$5:$L$5,ROW()-136)} -> 0.56550862
A146: {=INDEX('Ratio analysis'!$C$2:$L$2,ROW()-136)} -> FY26 | B146: {=INDEX('Ratio analysis'!$C$4:$L$4,ROW()-136)} -> 0.57826632 | C146: {=INDEX('Ratio analysis'!$C$5:$L$5,ROW()-136)} -> 0.41604282
A148: Year | B148: Debt-Equity Ratio
A149: {=INDEX('Ratio analysis'!$C$2:$L$2,ROW()-148)} -> FY17 | B149: {=INDEX('Ratio analysis'!$C$22:$L$22,ROW()-148)} -> 0.041073547
A150: {=INDEX('Ratio analysis'!$C$2:$L$2,ROW()-148)} -> FY18 | B150: {=INDEX('Ratio analysis'!$C$22:$L$22,ROW()-148)} -> 0
A151: {=INDEX('Ratio analysis'!$C$2:$L$2,ROW()-148)} -> FY19 | B151: {=INDEX('Ratio analysis'!$C$22:$L$22,ROW()-148)} -> 0.026142065
A152: {=INDEX('Ratio analysis'!$C$2:$L$2,ROW()-148)} -> FY20 | B152: {=INDEX('Ratio analysis'!$C$22:$L$22,ROW()-148)} -> 0
A153: {=INDEX('Ratio analysis'!$C$2:$L$2,ROW()-148)} -> FY21 | B153: {=INDEX('Ratio analysis'!$C$22:$L$22,ROW()-148)} -> 0
A154: {=INDEX('Ratio analysis'!$C$2:$L$2,ROW()-148)} -> FY22 | B154: {=INDEX('Ratio analysis'!$C$22:$L$22,ROW()-148)} -> 0.043128134
A155: {=INDEX('Ratio analysis'!$C$2:$L$2,ROW()-148)} -> FY23 | B155: {=INDEX('Ratio analysis'!$C$22:$L$22,ROW()-148)} -> 0.049071605
A156: {=INDEX('Ratio analysis'!$C$2:$L$2,ROW()-148)} -> FY24 | B156: {=INDEX('Ratio analysis'!$C$22:$L$22,ROW()-148)} -> 0.058470085
A157: {=INDEX('Ratio analysis'!$C$2:$L$2,ROW()-148)} -> FY25 | B157: {=INDEX('Ratio analysis'!$C$22:$L$22,ROW()-148)} -> 0.065513814
A158: {=INDEX('Ratio analysis'!$C$2:$L$2,ROW()-148)} -> FY26 | B158: {=INDEX('Ratio analysis'!$C$22:$L$22,ROW()-148)} -> 0.060239859
A160: Year | B160: EPS (Rs.) | C160: P/E Ratio (x)
A161: {=INDEX('Ratio analysis'!$C$2:$L$2,ROW()-160)} -> FY17 | B161: {=INDEX('Ratio analysis'!$C$27:$L$27,ROW()-160)} -> 20.681052 | C161: {=INDEX('Ratio analysis'!$C$28:$L$28,ROW()-160)} -> 42.193696
A162: {=INDEX('Ratio analysis'!$C$2:$L$2,ROW()-160)} -> FY18 | B162: {=INDEX('Ratio analysis'!$C$27:$L$27,ROW()-160)} -> 24.088704 | C162: {=INDEX('Ratio analysis'!$C$28:$L$28,ROW()-160)} -> 52.975453
A163: {=INDEX('Ratio analysis'!$C$2:$L$2,ROW()-160)} -> FY19 | B163: {=INDEX('Ratio analysis'!$C$27:$L$27,ROW()-160)} -> 27.966924 | C163: {=INDEX('Ratio analysis'!$C$28:$L$28,ROW()-160)} -> 58.409356
A164: {=INDEX('Ratio analysis'!$C$2:$L$2,ROW()-160)} -> FY20 | B164: {=INDEX('Ratio analysis'!$C$27:$L$27,ROW()-160)} -> 31.171471 | C164: {=INDEX('Ratio analysis'!$C$28:$L$28,ROW()-160)} -> 70.571903
A165: {=INDEX('Ratio analysis'!$C$2:$L$2,ROW()-160)} -> FY21 | B165: {=INDEX('Ratio analysis'!$C$27:$L$27,ROW()-160)} -> 34.027068 | C165: {=INDEX('Ratio analysis'!$C$28:$L$28,ROW()-160)} -> 68.390258
A166: {=INDEX('Ratio analysis'!$C$2:$L$2,ROW()-160)} -> FY22 | B166: {=INDEX('Ratio analysis'!$C$27:$L$27,ROW()-160)} -> 37.789411 | C166: {=INDEX('Ratio analysis'!$C$28:$L$28,ROW()-160)} -> 51.884905
A167: {=INDEX('Ratio analysis'!$C$2:$L$2,ROW()-160)} -> FY23 | B167: {=INDEX('Ratio analysis'!$C$27:$L$27,ROW()-160)} -> 43.071161 | C167: {=INDEX('Ratio analysis'!$C$28:$L$28,ROW()-160)} -> 56.892824
A168: {=INDEX('Ratio analysis'!$C$2:$L$2,ROW()-160)} -> FY24 | B168: {=INDEX('Ratio analysis'!$C$27:$L$27,ROW()-160)} -> 43.73936 | C168: {=INDEX('Ratio analysis'!$C$28:$L$28,ROW()-160)} -> 49.546678
A169: {=INDEX('Ratio analysis'!$C$2:$L$2,ROW()-160)} -> FY25 | B169: {=INDEX('Ratio analysis'!$C$27:$L$27,ROW()-160)} -> 45.322608 | C169: {=INDEX('Ratio analysis'!$C$28:$L$28,ROW()-160)} -> 47.699815
A170: {=INDEX('Ratio analysis'!$C$2:$L$2,ROW()-160)} -> FY26 | B170: {=INDEX('Ratio analysis'!$C$27:$L$27,ROW()-160)} -> 64.010895 | C170: {=INDEX('Ratio analysis'!$C$28:$L$28,ROW()-160)} -> 32.107034
A172: Year | B172: Shareholders' Equity | C172: Borrowings | D172: Other Liabilities
A173: {=INDEX('Ratio analysis'!$C$2:$L$2,ROW()-172)} -> FY17 | B173: {=INDEX('Balance Sheet'!$B$4:$K$4,ROW()-172)+INDEX('Balance Sheet'!$B$5:$K$5,ROW()-172)} -> 6744 | C173: {=INDEX('Balance Sheet'!$B$6:$K$6,ROW()-172)} -> 277 | D173: {=INDEX('Balance Sheet'!$B$7:$K$7,ROW()-172)} -> 8685
A174: {=INDEX('Ratio analysis'!$C$2:$L$2,ROW()-172)} -> FY18 | B174: {=INDEX('Balance Sheet'!$B$4:$K$4,ROW()-172)+INDEX('Balance Sheet'!$B$5:$K$5,ROW()-172)} -> 7281 | C174: {=INDEX('Balance Sheet'!$B$6:$K$6,ROW()-172)} -> 0 | D174: {=INDEX('Balance Sheet'!$B$7:$K$7,ROW()-172)} -> 10581
A175: {=INDEX('Ratio analysis'!$C$2:$L$2,ROW()-172)} -> FY19 | B175: {=INDEX('Balance Sheet'!$B$4:$K$4,ROW()-172)+INDEX('Balance Sheet'!$B$5:$K$5,ROW()-172)} -> 7867 | C175: {=INDEX('Balance Sheet'!$B$6:$K$6,ROW()-172)} -> 99 | D175: {=INDEX('Balance Sheet'!$B$7:$K$7,ROW()-172)} -> 10663
A176: {=INDEX('Ratio analysis'!$C$2:$L$2,ROW()-172)} -> FY20 | B176: {=INDEX('Balance Sheet'!$B$4:$K$4,ROW()-172)+INDEX('Balance Sheet'!$B$5:$K$5,ROW()-172)} -> 8229 | C176: {=INDEX('Balance Sheet'!$B$6:$K$6,ROW()-172)} -> 0 | D176: {=INDEX('Balance Sheet'!$B$7:$K$7,ROW()-172)} -> 11924
A177: {=INDEX('Ratio analysis'!$C$2:$L$2,ROW()-172)} -> FY21 | B177: {=INDEX('Balance Sheet'!$B$4:$K$4,ROW()-172)+INDEX('Balance Sheet'!$B$5:$K$5,ROW()-172)} -> 47674 | C177: {=INDEX('Balance Sheet'!$B$6:$K$6,ROW()-172)} -> 0 | D177: {=INDEX('Balance Sheet'!$B$7:$K$7,ROW()-172)} -> 21066
A178: {=INDEX('Ratio analysis'!$C$2:$L$2,ROW()-172)} -> FY22 | B178: {=INDEX('Balance Sheet'!$B$4:$K$4,ROW()-172)+INDEX('Balance Sheet'!$B$5:$K$5,ROW()-172)} -> 49061 | C178: {=INDEX('Balance Sheet'!$B$6:$K$6,ROW()-172)} -> 1043 | D178: {=INDEX('Balance Sheet'!$B$7:$K$7,ROW()-172)} -> 20402
A179: {=INDEX('Ratio analysis'!$C$2:$L$2,ROW()-172)} -> FY23 | B179: {=INDEX('Balance Sheet'!$B$4:$K$4,ROW()-172)+INDEX('Balance Sheet'!$B$5:$K$5,ROW()-172)} -> 50304 | C179: {=INDEX('Balance Sheet'!$B$6:$K$6,ROW()-172)} -> 1219 | D179: {=INDEX('Balance Sheet'!$B$7:$K$7,ROW()-172)} -> 21554
A180: {=INDEX('Ratio analysis'!$C$2:$L$2,ROW()-172)} -> FY24 | B180: {=INDEX('Balance Sheet'!$B$4:$K$4,ROW()-172)+INDEX('Balance Sheet'!$B$5:$K$5,ROW()-172)} -> 51218 | C180: {=INDEX('Balance Sheet'!$B$6:$K$6,ROW()-172)} -> 1484 | D180: {=INDEX('Balance Sheet'!$B$7:$K$7,ROW()-172)} -> 25787
A181: {=INDEX('Ratio analysis'!$C$2:$L$2,ROW()-172)} -> FY25 | B181: {=INDEX('Balance Sheet'!$B$4:$K$4,ROW()-172)+INDEX('Balance Sheet'!$B$5:$K$5,ROW()-172)} -> 49402 | C181: {=INDEX('Balance Sheet'!$B$6:$K$6,ROW()-172)} -> 1648 | D181: {=INDEX('Balance Sheet'!$B$7:$K$7,ROW()-172)} -> 28813
A182: {=INDEX('Ratio analysis'!$C$2:$L$2,ROW()-172)} -> FY26 | B182: {=INDEX('Balance Sheet'!$B$4:$K$4,ROW()-172)+INDEX('Balance Sheet'!$B$5:$K$5,ROW()-172)} -> 48739 | C182: {=INDEX('Balance Sheet'!$B$6:$K$6,ROW()-172)} -> 1478 | D182: {=INDEX('Balance Sheet'!$B$7:$K$7,ROW()-172)} -> 29521
A184: Year | B184: Revenue (Rs. cr) | C184: FCFF (Rs. cr)
A185: {=INDEX('DCF Valuation'!$C$38:$G$38,ROW()-184)} -> FY2027E | B185: {=INDEX('DCF Valuation'!$C$39:$G$39,ROW()-184)} -> 69625.44 | C185: {=INDEX('DCF Valuation'!$C$59:$G$59,ROW()-184)} -> 11680.839
A186: {=INDEX('DCF Valuation'!$C$38:$G$38,ROW()-184)} -> FY2028E | B186: {=INDEX('DCF Valuation'!$C$39:$G$39,ROW()-184)} -> 74499.221 | C186: {=INDEX('DCF Valuation'!$C$59:$G$59,ROW()-184)} -> 12543.232
A187: {=INDEX('DCF Valuation'!$C$38:$G$38,ROW()-184)} -> FY2029E | B187: {=INDEX('DCF Valuation'!$C$39:$G$39,ROW()-184)} -> 79714.166 | C187: {=INDEX('DCF Valuation'!$C$59:$G$59,ROW()-184)} -> 13421.258
A188: {=INDEX('DCF Valuation'!$C$38:$G$38,ROW()-184)} -> FY2030E | B188: {=INDEX('DCF Valuation'!$C$39:$G$39,ROW()-184)} -> 84497.016 | C188: {=INDEX('DCF Valuation'!$C$59:$G$59,ROW()-184)} -> 14266.763
A189: {=INDEX('DCF Valuation'!$C$38:$G$38,ROW()-184)} -> FY2031E | B189: {=INDEX('DCF Valuation'!$C$39:$G$39,ROW()-184)} -> 89566.837 | C189: {=INDEX('DCF Valuation'!$C$59:$G$59,ROW()-184)} -> 15122.769
A191: Company | B191: EV/EBITDA (FY26A)
A192: {=INDEX('Relative Valuation'!$B$7:$B$11,ROW()-191)} -> Hind. Unilever | B192: {=INDEX('Relative Valuation'!$H$7:$H$11,ROW()-191)/INDEX('Relative Valuation'!$L$7:$L$11,ROW()-191)} -> 31.148446
A193: {=INDEX('Relative Valuation'!$B$7:$B$11,ROW()-191)} -> ITC | B193: {=INDEX('Relative Valuation'!$H$7:$H$11,ROW()-191)/INDEX('Relative Valuation'!$L$7:$L$11,ROW()-191)} -> 11.671167
A194: {=INDEX('Relative Valuation'!$B$7:$B$11,ROW()-191)} -> Nestle India | B194: {=INDEX('Relative Valuation'!$H$7:$H$11,ROW()-191)/INDEX('Relative Valuation'!$L$7:$L$11,ROW()-191)} -> 54.319851
A195: {=INDEX('Relative Valuation'!$B$7:$B$11,ROW()-191)} -> Godrej Consumer | B195: {=INDEX('Relative Valuation'!$H$7:$H$11,ROW()-191)/INDEX('Relative Valuation'!$L$7:$L$11,ROW()-191)} -> 33.526313
A196: {=INDEX('Relative Valuation'!$B$7:$B$11,ROW()-191)} -> Marico | B196: {=INDEX('Relative Valuation'!$H$7:$H$11,ROW()-191)/INDEX('Relative Valuation'!$L$7:$L$11,ROW()-191)} -> 44.813469

Sheet Key Findings
B2: Key Findings
B3: All figures in this worksheet are linked to the analysis worksheets. Amounts are in Rs. crore unless stated otherwise.
B5: 1. Operating Performance and Profitability
B6: Parameter | C6: FY2025 | D6: FY2026 | E6: Observation
B7: Net sales (Rs. crore) | C7: ='Beneish M-Score'!K5 -> 61328 | D7: ='Beneish M-Score'!L5 -> 64468 | E7: ="Revenue grew by "&TEXT(D7/C7-1,"0.0%")&" in FY2026 after a flat FY2025, indicating a recovery in volume led growth." -> Revenue grew by 5.1% in FY2026 after a flat FY2025, indicating a recovery in volume led growth.
B8: Net profit (Rs. crore) | C8: ='Beneish M-Score'!K16 -> 10649 | D8: ='Beneish M-Score'!L16 -> 15040 | E8: The sharp rise in FY2026 is largely attributable to a one-off divestment gain and a correspondingly low effective tax rate, and is therefore not representative of the underlying business.
B9: Operating profit margin | C9: ='Ratio analysis'!K9 -> 0.24132533 | D9: ='Ratio analysis'!L9 -> 0.28896507 | E9: Margins have improved steadily from 19.6 per cent in FY2017, reflecting premiumisation, cost savings and favourable input prices.
B10: Net profit margin | C10: ='Ratio analysis'!K10 -> 0.1736401 | D10: ='Ratio analysis'!L10 -> 0.23329404 | E10: The reported margin for FY2026 is inflated by the one-off gain; the underlying margin is closer to 17 to 18 per cent.
B11: Return on equity | C11: ='Ratio analysis'!K12 -> 0.21166766 | D11: ='Ratio analysis'!L12 -> 0.30649779 | E11: Return on equity fell sharply after FY2020 because the merger with GSK Consumer Healthcare added a large goodwill and equity base; it has since been rebuilt from 18.4 per cent in FY2022.
B12: Return on capital employed | C12: ='Ratio analysis'!K13 -> 0.29417611 | D12: ='Ratio analysis'!L13 -> 0.37963746 | E12: Returns remain well above the cost of capital of about 9.9 per cent, confirming that the company continues to create economic value.
B14: 2. Liquidity, Efficiency and Solvency
B15: Parameter | C15: FY2025 | D15: FY2026 | E15: Observation
B16: Current ratio | C16: ='Ratio analysis'!K4 -> 0.71873807 | D16: ='Ratio analysis'!L4 -> 0.57826632 | E16: The current ratio is below one and has declined further. This is characteristic of an FMCG business that operates on negative working capital by drawing extended credit from suppliers while selling largely on cash terms.
B17: Quick ratio | C17: ='Ratio analysis'!K5 -> 0.56550862 | D17: ='Ratio analysis'!L5 -> 0.41604282 | E17: Low in absolute terms, but not a concern given the strong and predictable operating cash flows and the negligible level of debt.
B18: Inventory turnover (times) | C18: ='Ratio analysis'!K16 -> 7.3052033 | D18: ='Ratio analysis'!L16 -> 7.2396784 | E18: Stable at about seven times over the entire period, indicating consistent inventory management.
B19: Debtors turnover (times) | C19: ='Ratio analysis'!K17 -> 17.995305 | D19: ='Ratio analysis'!L17 -> 17.912754 | E19: Debtors turnover has fallen from about 30 times in FY2017 to 18 times, showing that receivables are being collected more slowly. This is the clearest area of deterioration in working capital management.
B20: Debt to equity ratio | C20: ='Ratio analysis'!K22 -> 0.065513814 | D20: ='Ratio analysis'!L22 -> 0.060239859 | E20: The company is virtually debt free, which leaves substantial headroom to raise funds should an acquisition opportunity arise.
B21: Interest coverage (times) | C21: ='Ratio analysis'!K23 -> 38.845144 | D21: ='Ratio analysis'!L23 -> 45.436585 | E21: Interest cover of more than forty times means that solvency risk is negligible.
B22: Dividend payout ratio | C22: ='Ratio analysis'!K29 -> 1.1695934 | D22: ='Ratio analysis'!L29 -> 0.640625 | E22: The company has consistently distributed the greater part of its earnings, which is consistent with a mature business that has limited reinvestment requirements.
B24: 3. Earnings Quality and Financial Distress
B25: Test | C25: Result | E25: Interpretation
B26: Beneish M-Score, FY2026 | C26: ='Beneish M-Score'!K32 -> -2.3354644 | E26: ="The score is below the threshold of -1.78, which places the company in the low risk category. There is no statistical indication of earnings manipulation in FY2026." -> The score is below the threshold of -1.78, which places the company in the low risk category. There is no statistical indication of earnings manipulation in FY2026.
B27: Beneish M-Score, FY2021 | C27: ='Beneish M-Score'!F32 -> -1.2381429 | E27: FY2021 is the only year flagged as high risk. This is explained by the merger with GSK Consumer Healthcare, which distorted the sales growth, depreciation and leverage indices, rather than by any evidence of manipulation.
B28: Altman Z-Score, FY2026 | C28: ='Altman Z Score'!I35 -> 6.0734393 | E28: The score is above the safe zone threshold of 3.00 in every year examined — comfortably so from FY2022 to FY2026, and only marginally in FY2020 and FY2021 — so the risk of financial distress is negligible throughout. The absolute value in the later years is inflated because the market capitalisation to long term liabilities component becomes very large when borrowings are near zero; the conclusion, however, is unaffected.
B30: 4. Valuation
B31: Method | C31: Implied value (Rs.) | E31: Comment
B32: Discounted cash flow (base case) | C32: ='DCF Valuation'!C74 -> 1384.4125 | E32: Based on a WACC of 9.9 per cent and a terminal growth rate of 6.0 per cent. The value is highly sensitive to both inputs, as shown in the sensitivity table on the DCF worksheet.
B33: Relative valuation, median EV/EBITDA | C33: ='Relative Valuation'!U26 -> 2639.8646 | E33: Applying the median peer multiple indicates a material undervaluation against the market price.
B34: Relative valuation, median P/E | C34: ='Relative Valuation'!Y26 -> 2810.773 | E34: The peer set trades at a median price to earnings multiple higher than that of the company, which indicates undervaluation on this measure.
B35: Current market price | C35: ='DCF Valuation'!C75 -> 2108 | E35: Closing price on 30 July 2026.
B36: Deviation of the DCF value from the market price | C36: ='DCF Valuation'!C76 -> -0.34325782 | E36: The discounted cash flow model and the market price differ materially. The difference narrows substantially at a lower beta and a higher terminal growth rate, and the balance reflects the premium the market assigns to the brand portfolio and distribution network of the company.
B38: 5. Overall Assessment
B39: Hindustan Unilever remains a financially sound business. Profitability and returns on capital employed are comfortably above the cost of capital, the balance sheet carries almost no debt, and both the Altman Z-Score and the Beneish M-Score indicate that the risk of financial distress and of earnings manipulation is low. The principal areas of weakness are the slower collection of receivables, the persistently negative working capital position and the moderation in revenue growth compared with the earlier part of the period under review. On valuation, the comparable company analysis indicates the share is undervalued against its peers on both an EV/EBITDA and a price-to-earnings basis, while the discounted cash flow model indicates a value materially below the prevailing market price; the blended average across all three methods nevertheless sits close to the current market price. The difference across methods is driven mainly by the beta and terminal growth assumptions used in the DCF and by the premium that the market assigns to the brand portfolio and distribution reach of the company.

Sheet Recommendations
B2: Recommendations
B3: Based on the analysis carried out in the preceding worksheets. Figures are linked to their source worksheets.
B5: 1. Valuation Summary and Investment View
B6: Method | C6: Implied value per share (Rs.) | D6: Premium / (discount) to market price | E6: Signal
B7: Discounted cash flow, base case | C7: ='Key Findings'!C32 -> 1384.4125 | D7: =C7/$C$11-1 -> -0.34325782 | E7: =IF(D7>0.1,"Undervalued",IF(D7<-0.1,"Overvalued","Fairly valued")) -> Overvalued
B8: Relative valuation, median EV/EBITDA | C8: ='Key Findings'!C33 -> 2639.8646 | D8: =C8/$C$11-1 -> 0.25230767 | E8: =IF(D8>0.1,"Undervalued",IF(D8<-0.1,"Overvalued","Fairly valued")) -> Undervalued
B9: Relative valuation, median P/E | C9: ='Key Findings'!C34 -> 2810.773 | D9: =C9/$C$11-1 -> 0.33338378 | E9: =IF(D9>0.1,"Undervalued",IF(D9<-0.1,"Overvalued","Fairly valued")) -> Undervalued
B10: Average of the three methods | C10: =AVERAGE(C7:C9) -> 2278.35 | D10: =C10/$C$11-1 -> 0.080811207 | E10: =IF(D10>0.1,"Undervalued",IF(D10<-0.1,"Overvalued","Fairly valued")) -> Fairly valued
B11: Current market price | C11: ='DCF Valuation'!C75 -> 2108
B13: Recommendation | C13: HOLD
B14: Rationale | C14: The three valuation methods bracket the market price rather than pointing consistently in one direction, and their average is close to the price at which the share currently trades. The business is of high quality, generates returns well above its cost of capital and carries almost no debt, but the price already reflects much of that quality. Existing investors are therefore advised to hold, while fresh purchases are better made on a decline towards the discounted cash flow range, or once volume growth reaccelerates.
B16: 2. Recommendations to Management
B17: Area | C17: Recommendation
B18: Receivables management | C18: Debtors turnover has fallen from about thirty times in FY2017 to eighteen times in FY2026. Tighter credit terms for distributors and closer monitoring of overdue balances would release working capital and improve the cash conversion cycle.
B19: Revenue growth | C19: Growth of about five per cent is close to inflation and implies limited volume expansion. Continued investment in premium and health oriented categories, in rural distribution and in digital channels is necessary to restore mid to high single digit volume growth.
B20: Margin management | C20: Operating margins are at the upper end of their historical range. Further gains should be sought through mix improvement and cost efficiency rather than through price increases, which could weaken volumes in a competitive market.
B21: Capital allocation | C21: With negligible debt and a payout ratio of about sixty four per cent, the company has ample headroom to fund acquisitions in premium and wellness categories, which would support growth beyond the rate assumed in the terminal value.
B22: Disclosure | C22: The one-off divestment gain in FY2026 materially distorts the reported profit and the effective tax rate. Presenting a clear reconciliation of underlying and reported earnings would improve comparability for users of the financial statements.
B24: 3. Key Risks to the Recommendation
B25: Risk | C25: Description
B26: Input cost inflation | C26: A rise in palm oil, crude derivative or tea prices would compress the operating margin of 23.5 per cent assumed throughout the projection period.
B27: Competitive intensity | C27: Regional and direct to consumer brands continue to gain share in several categories, which may limit both volume growth and pricing power.
B28: Rural demand | C28: A weak monsoon or slower rural income growth would directly affect volumes, as rural markets contribute a substantial share of revenue.
B29: Valuation risk | C29: The share trades at a price to earnings multiple well above the peer median. Any disappointment in earnings could lead to a de-rating of the multiple in addition to a fall in earnings.
B30: Assumption risk | C30: The discounted cash flow value moves from roughly Rs. 950 to Rs. 2,740 per share across the range of WACC and terminal growth rates tested, so the conclusion drawn from that model is sensitive to the inputs selected.
B32: 4. Limitations of the Analysis
B33: The analysis is based entirely on published financial statements and market data, and no management guidance or segment level internal data has been used.
B34: Figures from FY2021 onward include the effect of the merger with GSK Consumer Healthcare, which limits comparability with earlier years.
B35: The Asset Quality Index within the Beneish model is held at the neutral value of 1.00 owing to the absence of a separate other non-current asset disclosure.
B36: The Altman Z-Score is inflated by the market capitalisation to long term liabilities component because borrowings are negligible; the classification is nevertheless unaffected.
B37: The comparable company analysis uses four peers only, and no adjustment has been made for differences in size, growth or category mix.

Sheet Assumptions Summary
B2: Summary of Assumptions
B3: This worksheet consolidates every assumption used in the project. Values shown in this sheet are linked to the worksheets in which they are applied, so that any change made there is reflected here.
B5: 1. Projection Assumptions (Discounted Cash Flow Model)
B6: Assumption | C6: Value | D6: Basis
B7: Explicit forecast period | C7: Five years | D7: FY2027E to FY2031E, followed by a terminal value
B8: Revenue growth rate | C8: =TEXT('DCF Valuation'!C7,"0.0%")&" tapering to "&TEXT('DCF Valuation'!G7,"0.0%") -> 8.0% tapering to 6.0% | D8: Tapering from recent momentum of 8 to 10 per cent towards long run FMCG industry growth
B9: Operating profit margin (EBIT) | C9: ='DCF Valuation'!C8 -> 0.235 | D9: Five year historical average operating margin of 23.3 to 24.5 per cent, held constant
B10: Effective tax rate | C10: ='DCF Valuation'!C9 -> 0.26 | D10: Normalised rate; excludes the one-off rate of 17 per cent in FY2026 arising from the divestment
B11: Depreciation and amortisation, as a percentage of revenue | C11: ='DCF Valuation'!C10 -> 0.021 | D11: FY2026 actual: 1,333 / 64,468 = 2.07 per cent
B12: Capital expenditure, as a percentage of revenue | C12: ='DCF Valuation'!C11 -> 0.023 | D12: Marginally above depreciation, to reflect premiumisation led capacity addition
B13: Net working capital, as a percentage of revenue | C13: ='DCF Valuation'!C12 -> 0.054 | D13: FY2026 actual: 3,472 / 64,468 = 5.4 per cent
B14: Terminal growth rate (g) | C14: ='DCF Valuation'!C13 -> 0.06 | D14: Long run growth assumption linked to nominal GDP growth in India
B16: 2. Cost of Capital Assumptions
B17: Assumption | C17: Value | D17: Basis
B18: Risk free rate | C18: ='DCF Valuation'!C20 -> 0.05 | D18: Yield on the 10 year Government of India security, July 2026
B19: Equity beta | C19: ='DCF Valuation'!C22 -> 0.66045291 | D19: Blended estimate; reported betas range from 0.3 to 0.9 depending on source and period
B20: Equity risk premium | C20: ='DCF Valuation'!C21 -> 0.0731 | D20: Equity risk premium for India, commonly taken at 6 to 7 per cent
B21: Cost of equity (Ke) | C21: ='DCF Valuation'!C23 -> 0.098279108 | D21: Capital asset pricing model: Ke = Rf + Beta * ERP
B22: Pre-tax cost of debt | C22: ='DCF Valuation'!C27 -> 0.27740189 | D22: Approximate yield on AAA rated corporate bonds; HUL is rated CRISIL AAA
B23: Post-tax cost of debt | C23: ='DCF Valuation'!C29 -> 0.19418133 | D23: Pre-tax cost of debt adjusted for the effective tax rate
B24: Weight of equity | C24: ='DCF Valuation'!C32 -> 0.995 | D24: Based on market capitalisation as at 30 July 2026 and book value of debt
B25: Weight of debt | C25: ='DCF Valuation'!C31 -> 0.005 | D25: Borrowings are negligible, hence the capital structure is almost entirely equity funded
B26: Weighted average cost of capital (WACC) | C26: ='DCF Valuation'!C35 -> 0.098758619 | D26: WACC = (We * Ke) + (Wd * Kd post-tax); tested from 8.0 to 13.0 per cent in the sensitivity analysis
B28: 3. Assumptions Underlying the Analytical Models
B29: Model | C29: Assumption applied
B30: Altman Z-Score | C30: The original 1968 model for listed manufacturing companies is used, with weights of 1.2, 1.4, 3.3, 0.6 and 1.0. Market value of equity is taken as market capitalisation. Interpretation: above 3.00 is safe, 1.81 to 3.00 is the grey zone and below 1.81 indicates distress.
B31: Beneish M-Score | C31: The eight variable model is used, with a threshold of -1.78. The Asset Quality Index is held at the neutral value of 1.00 because the balance sheet does not disclose a separate other non-current asset line, which makes the standard formula indeterminate. This is a conservative simplification rather than a computed result.
B32: Relative Valuation | C32: The peer set comprises ITC, Nestle India, Godrej Consumer Products and Marico, being listed Indian FMCG companies of comparable business profile. Trailing EV/Revenue, EV/EBITDA, EV/EBIT and P/E multiples are used, and the median peer multiple is applied to the corresponding financial of the company.
B33: Ratio Analysis | C33: Ratios are computed on reported year end figures rather than on averages. Figures from FY2021 onward reflect the merger of GSK Consumer Healthcare, so the balance sheet and the ratios derived from it are not strictly comparable with the earlier years.
B34: Common Size and Comparative Statements | C34: Common size figures are expressed as a percentage of net sales for the profit and loss account and of total assets for the balance sheet. Comparative figures are stated as year on year changes in absolute and percentage terms.
B36: 4. General Assumptions
B37: Assumption | C37: Value
B38: Financial year end | C38: 31 March
B39: Base year for the projections | C39: FY2026 (audited)
B40: Shares outstanding | C40: ='DCF Valuation'!C73&" crore shares of face value Re. 1 each" -> 234.96 crore shares of face value Re. 1 each
B41: Market price used | C41: ="Rs. "&TEXT('DCF Valuation'!C75,"#,##0")&" per share, being the closing price on 30 July 2026" -> Rs. 2,108 per share, being the closing price on 30 July 2026
B42: Units of presentation | C42: Rupees in crore, unless stated otherwise
B43: Treatment of one-off items | C43: The gain arising on divestment in FY2026 and the consequent low effective tax rate are treated as non-recurring and are excluded from the projections.

Sheet Data Sheet
A1: COMPANY NAME | B1: HINDUSTAN UNILEVER LTD | E1: =IF(B2<>B3, "A NEW VERSION OF THE WORKSHEET IS AVAILABLE", "")
A2: LATEST VERSION | B2: 2.1 | E2: PLEASE DO NOT MAKE ANY CHANGES TO THIS SHEET
A3: CURRENT VERSION | B3: 2.1
A5: META
A6: Number of shares | B6: =IF(B9>0, B9/B8, 0) -> 234.94241
A7: Face Value | B7: 1
A8: Current Price | B8: 2100.8
A9: Market Capitalization | B9: 493567.01
A15: PROFIT & LOSS
A16: Report Date | B16: 42825 | C16: 43190 | D16: 43555 | E16: 43921 | F16: 44286 | G16: 44651 | H16: 45016 | I16: 45382 | J16: 45747 | K16: 46112
A17: Sales | B17: 33162 | C17: 35545 | D17: 39310 | E17: 39783 | F17: 47028 | G17: 52446 | H17: 60580 | I17: 61896 | J17: 61328 | K17: 64468
A18: Raw Material Cost | B18: 13606 | C18: 14233 | D18: 15845 | E18: 15697 | F18: 20141 | G18: 22871 | H18: 28427 | I18: 26822 | J18: 26602 | K18: 29158
A19: Change in Inventory | B19: -144 | C19: 72 | D19: -12 | E19: 108 | F19: 405 | G19: 22 | H19: 75 | I19: 11 | J19: 125 | K19: 429
A20: Power and Fuel | B20: 295 | C20: 295 | D20: 308 | E20: 299 | F20: 339 | G20: 318 | H20: 384 | I20: 446 | J20: 403 | K20: 426
A21: Other Mfr. Exp | B21: 2887 | C21: 2998 | D21: 3041 | E21: 2906 | F21: 2868 | G21: 3354 | H21: 3791 | I21: 3385 | J21: 3687 | K21: 3304
A22: Employee Cost | B22: 1743 | C22: 1860 | D22: 1875 | E22: 1820 | F22: 2358 | G22: 2545 | H22: 2854 | I22: 3009 | J22: 2952 | K22: 3175
A23: Selling and admin | B23: 6689 | C23: 7252 | D23: 7796 | E23: 7620 | F23: 7906 | G23: 8164 | H23: 8785 | I23: 10780 | J23: 10145 | K23: 10744
A24: Other Expenses | B24: 1470 | C24: 1480 | D24: 1553 | E24: 1688 | F24: 2195 | G24: 2359 | H24: 2267 | I24: 2806 | J24: 2966 | K24: 3051
A25: Other Income | B25: 606 | C25: 353 | D25: 322 | E25: 424 | F25: 170 | G25: 219 | H25: 448 | I25: 817 | J25: 1355 | K25: 4923
A26: Depreciation | B26: 432 | C26: 520 | D26: 565 | E26: 1002 | F26: 1074 | G26: 1091 | H26: 1137 | I26: 1216 | J26: 1253 | K26: 1333
A27: Interest | B27: 35 | C27: 26 | D27: 33 | E27: 118 | F27: 117 | G27: 106 | H27: 114 | I27: 334 | J27: 381 | K27: 410
... A31: Dividend Amount | B31: 3672 | C31: 4320 | D31: 4752 | E31: 5400 | F31: 9517.5 | G31: 7990 | H31: 9165 | I31: 9870 | J31: 12455 | K31: 9635
A40: Quarters
A41: Report Date | B41: 45382 | C41: 45473 | D41: 45565 | E41: 45657 | F41: 45747 | G41: 45838 | H41: 45930 | I41: 46022 | J41: 46112 | K41: 46203
A42: Sales | B42: 15210 | C42: 15707 | D42: 15926 | E42: 15556 | F42: 15190 | G42: 15757 | H42: 15919 | I42: 16441 | J42: 16351 | K42: 17341
A43: Expenses | B43: 11675 | C43: 11965 | D43: 12139 | E43: 11867 | F43: 11572 | G43: 12118 | H43: 12137 | I43: 12660 | J43: 12514 | K43: 13394
A44: Other Income | B44: 309 | C44: 209 | D44: 203 | E44: 733 | F44: 149 | G44: 103 | H44: 269 | I44: 4048 | J44: 503 | K44: 113
A45: Depreciation | B45: 320 | C45: 329 | D45: 338 | E45: 318 | F45: 318 | G45: 326 | H45: 322 | I45: 337 | J45: 348 | K45: 353
A46: Interest | B46: 105 | C46: 93 | D46: 110 | E46: 109 | F46: 77 | G46: 122 | H46: 124 | I46: 88 | J46: 76 | K46: 75
A47: Profit before tax | B47: 3419 | C47: 3529 | D47: 3542 | E47: 3995 | F47: 3372 | G47: 3294 | H47: 3605 | I47: 7404 | J47: 3916 | K47: 3632
A48: Tax | B48: 858 | C48: 917 | D48: 947 | E48: 1006 | F48: 897 | G48: 526 | H48: 911 | I48: 801 | J48: 922 | K48: 952
A49: Net profit | B49: 2558 | C49: 2610 | D49: 2591 | E49: 2984 | F49: 2464 | G49: 2756 | H49: 2685 | I49: 6607 | J49: 2992 | K49: 2673
A50: Operating Profit | B50: 3535 | C50: 3742 | D50: 3787 | E50: 3689 | F50: 3618 | G50: 3639 | H50: 3782 | I50: 3781 | J50: 3837 | K50: 3947
A55: BALANCE SHEET
A56: Report Date | B56: 42825 | C56: 43190 | D56: 43555 | E56: 43921 | F56: 44286 | G56: 44651 | H56: 45016 | I56: 45382 | J56: 45747 | K56: 46112
A57: Equity Share Capital | B57: 216 | C57: 216 | D57: 216 | E57: 216 | F57: 235 | G57: 235 | H57: 235 | I57: 235 | J57: 235 | K57: 235
A58: Reserves | B58: 6528 | C58: 7065 | D58: 7651 | E58: 8013 | F58: 47439 | G58: 48826 | H58: 50069 | I58: 50983 | J58: 49167 | K58: 48504
A59: Borrowings | B59: 277 | D59: 99 | G59: 1043 | H59: 1219 | I59: 1484 | J59: 1648 | K59: 1478
A60: Other Liabilities | B60: 8685 | C60: 10581 | D60: 10663 | E60: 11924 | F60: 21066 | G60: 20402 | H60: 21554 | I60: 25787 | J60: 28813 | K60: 29521
A61: Total | B61: 15706 | C61: 17862 | D61: 18629 | E61: 20153 | F61: 68740 | G61: 70506 | H61: 73077 | I61: 78489 | J61: 79863 | K61: 79738
A62: Net Block | B62: 4419 | C62: 4528 | D62: 4715 | E62: 5479 | F62: 51443 | G62: 51473 | H62: 52678 | I62: 53744 | J62: 54335 | K62: 57428
A63: Capital Work in Progress | B63: 229 | C63: 461 | D63: 406 | E63: 597 | F63: 745 | G63: 1313 | H63: 1132 | I63: 1025 | J63: 1009 | K63: 880
A64: Investments | B64: 3794 | C64: 2873 | D64: 2716 | E64: 1255 | F64: 2709 | G64: 3521 | H64: 2882 | I64: 4625 | J64: 3810 | K64: 4359
A65: Other Assets | B65: 7264 | C65: 10000 | D65: 10792 | E65: 12822 | F65: 13843 | G65: 14199 | H65: 16385 | I65: 19095 | J65: 20709 | K65: 17071
A66: Total | B66: 15706 | C66: 17862 | D66: 18629 | E66: 20153 | F66: 68740 | G66: 70506 | H66: 73077 | I66: 78489 | J66: 79863 | K66: 79738
A67: Receivables | B67: 1085 | C67: 1310 | D67: 1816 | E67: 1149 | F67: 1758 | G67: 2236 | H67: 3079 | I67: 2997 | J67: 3819 | K67: 3379
A68: Inventory | B68: 2541 | C68: 2513 | D68: 2574 | E68: 2767 | F68: 3579 | G68: 4096 | H68: 4251 | I68: 4022 | J68: 4415 | K68: 4789
A69: Cash & Bank | B69: 1828 | C69: 3485 | D69: 3757 | E69: 5113 | F69: 4471 | G69: 3846 | H69: 4678 | I69: 7559 | J69: 7554 | K69: 3248
A70: No. of Equity Shares | B70: 2164349639 | C70: 2164528777 | D70: 2164704405 | E70: 2164704405 | F70: 2349567819 | G70: 2349591262 | H70: 2349591262 | I70: 2349591262 | J70: 2349591262 | K70: 2349591262
A71: New Bonus Shares
A72: Face value | B72: 1 | C72: 1 | D72: 1 | E72: 1 | F72: 1 | G72: 1 | H72: 1 | I72: 1 | J72: 1 | K72: 1
A80: CASH FLOW:
A81: Report Date | B81: 42825 | C81: 43190 | D81: 43555 | E81: 43921 | F81: 44286 | G81: 44651 | H81: 45016 | I81: 45382 | J81: 45747 | K81: 46112
A82: Cash from Operating Activity | B82: 5185 | C82: 6059 | D82: 5800 | E82: 7623 | F82: 9163 | G82: 9048 | H82: 9991 | I82: 15469 | J82: 11886 | K82: 10999
A83: Cash from Investing Activity | B83: -1173 | C83: -1063 | D83: -438 | E83: 1791 | F83: -1228 | G83: -1728 | H83: -1484 | I83: -5324 | J83: 6473 | K83: -3676
A84: Cash from Financing Activity | B84: -4214 | C84: -4975 | D84: -5390 | E84: -6819 | F84: -9309 | G84: -8015 | H84: -8953 | I84: -10034 | J84: -13101 | K84: -10810
A85: Net Cash Flow | B85: -202 | C85: 21 | D85: -28 | E85: 2595 | F85: -1374 | G85: -695 | H85: -446 | I85: 111 | J85: 5258 | K85: -3487
A90: PRICE: | B90: 872.61 | C90: 1276.11 | D90: 1633.53 | E90: 2199.83 | F90: 2327.12 | G90: 1960.7 | H90: 2450.44 | I90: 2167.14 | J90: 2161.88 | K90: 2055.2
A92: DERIVED:
A93: Adjusted Equity Shares in Cr | B93: 216.43 | C93: 216.45 | D93: 216.47 | E93: 216.48 | F93: 234.96 | G93: 234.96 | H93: 234.96 | I93: 234.96 | J93: 234.96 | K93: 234.96

Sheet Profit & Loss
A1: ='Data Sheet'!B1 -> HINDUSTAN UNILEVER LTD | H1: =UPDATE | M1: SCREENER.IN
A3: Narration | B3: ='Data Sheet'!B16 -> 42825 | C3: ='Data Sheet'!C16 -> 43190 | D3: ='Data Sheet'!D16 -> 43555 | E3: ='Data Sheet'!E16 -> 43921 | F3: ='Data Sheet'!F16 -> 44286 | G3: ='Data Sheet'!G16 -> 44651 | H3: ='Data Sheet'!H16 -> 45016 | I3: ='Data Sheet'!I16 -> 45382 | ... K3: ='Data Sheet'!K16 -> 46112 | L3: Trailing | M3: Best Case | N3: Worst Case
A4: Sales | B4: ='Data Sheet'!B17 -> 33162 | C4: ='Data Sheet'!C17 -> 35545 | D4: ='Data Sheet'!D17 -> 39310 | E4: ='Data Sheet'!E17 -> 39783 | F4: ='Data Sheet'!F17 -> 47028 | G4: ='Data Sheet'!G17 -> 52446 | H4: ='Data Sheet'!H17 -> 60580 | I4: ='Data Sheet'!I17 -> 61896 | ... K4: ='Data Sheet'!K17 -> 64468 | L4: =SUM(Quarters!H4:K4) -> 66052 | M4: =$K4+M23*K4 -> 67768.768 | N4: =$K4+N23*L4 -> 65851.867
A5: Expenses | B5: =SUM('Data Sheet'!B18,'Data Sheet'!B20:B24, -1*'Data Sheet'!B19) -> 26834 | C5: =SUM('Data Sheet'!C18,'Data Sheet'!C20:C24, -1*'Data Sheet'!C19) -> 28046 | D5: =SUM('Data Sheet'!D18,'Data Sheet'!D20:D24, -1*'Data Sheet'!D19) -> 30430 | E5: =SUM('Data Sheet'!E18,'Data Sheet'!E20:E24, -1*'Data Sheet'!E19) -> 29922 | F5: =SUM('Data Sheet'!F18,'Data Sheet'!F20:F24, -1*'Data Sheet'!F19) -> 35402 | G5: =SUM('Data Sheet'!G18,'Data Sheet'!G20:G24, -1*'Data Sheet'!G19) -> 39589 | H5: =SUM('Data Sheet'!H18,'Data Sheet'!H20:H24, -1*'Data Sheet'!H19) -> 46433 | I5: =SUM('Data Sheet'!I18,'Data Sheet'!I20:I24, -1*'Data Sheet'!I19) -> 47237 | ... K5: =SUM('Data Sheet'!K18,'Data Sheet'!K20:K24, -1*'Data Sheet'!K19) -> 49429 | L5: =SUM(Quarters!H5:K5) -> 50705 | M5: =M4-M6 -> 51738.984 | N5: =N4-N6 -> 50551.368
A6: Operating Profit | B6: =B4-B5 -> 6328 | C6: =C4-C5 -> 7499 | D6: =D4-D5 -> 8880 | E6: =E4-E5 -> 9861 | F6: =F4-F5 -> 11626 | G6: =G4-G5 -> 12857 | H6: =H4-H5 -> 14147 | I6: =I4-I5 -> 14659 | ... K6: =K4-K5 -> 15039 | L6: =SUM(Quarters!H6:K6) -> 15347 | M6: =M4*M24 -> 16029.784 | N6: =N4*N24 -> 15300.5
A7: Other Income | B7: ='Data Sheet'!B25 -> 606 | C7: ='Data Sheet'!C25 -> 353 | D7: ='Data Sheet'!D25 -> 322 | E7: ='Data Sheet'!E25 -> 424 | F7: ='Data Sheet'!F25 -> 170 | G7: ='Data Sheet'!G25 -> 219 | H7: ='Data Sheet'!H25 -> 448 | I7: ='Data Sheet'!I25 -> 817 | ... K7: ='Data Sheet'!K25 -> 4923 | L7: =SUM(Quarters!H7:K7) -> 4933 | M7: 0 | N7: 0
A8: Depreciation | B8: ='Data Sheet'!B26 -> 432 | C8: ='Data Sheet'!C26 -> 520 | D8: ='Data Sheet'!D26 -> 565 | E8: ='Data Sheet'!E26 -> 1002 | F8: ='Data Sheet'!F26 -> 1074 | G8: ='Data Sheet'!G26 -> 1091 | H8: ='Data Sheet'!H26 -> 1137 | I8: ='Data Sheet'!I26 -> 1216 | ... K8: ='Data Sheet'!K26 -> 1333 | L8: =SUM(Quarters!H8:K8) -> 1360 | M8: =+$L8 -> 1360 | N8: =+$L8 -> 1360
A9: Interest | B9: ='Data Sheet'!B27 -> 35 | C9: ='Data Sheet'!C27 -> 26 | D9: ='Data Sheet'!D27 -> 33 | E9: ='Data Sheet'!E27 -> 118 | F9: ='Data Sheet'!F27 -> 117 | G9: ='Data Sheet'!G27 -> 106 | H9: ='Data Sheet'!H27 -> 114 | I9: ='Data Sheet'!I27 -> 334 | ... K9: ='Data Sheet'!K27 -> 410 | L9: =SUM(Quarters!H9:K9) -> 363 | M9: =+$L9 -> 363 | N9: =+$L9 -> 363
A10: Profit before tax | B10: ='Data Sheet'!B28 -> 6467 | C10: ='Data Sheet'!C28 -> 7306 | D10: ='Data Sheet'!D28 -> 8604 | E10: ='Data Sheet'!E28 -> 9165 | F10: ='Data Sheet'!F28 -> 10605 | G10: ='Data Sheet'!G28 -> 11879 | H10: ='Data Sheet'!H28 -> 13344 | I10: ='Data Sheet'!I28 -> 13926 | ... K10: ='Data Sheet'!K28 -> 18219 | L10: =SUM(Quarters!H10:K10) -> 18557 | M10: =M6+M7-SUM(M8:M9) -> 14306.784 | N10: =N6+N7-SUM(N8:N9) -> 13577.5
A11: Tax | B11: ='Data Sheet'!B29 -> 1977 | C11: ='Data Sheet'!C29 -> 2079 | D11: ='Data Sheet'!D29 -> 2544 | E11: ='Data Sheet'!E29 -> 2409 | F11: ='Data Sheet'!F29 -> 2606 | G11: ='Data Sheet'!G29 -> 2987 | H11: ='Data Sheet'!H29 -> 3201 | I11: ='Data Sheet'!I29 -> 3644 | ... K11: ='Data Sheet'!K29 -> 3160 | L11: =SUM(Quarters!H11:K11) -> 3586 | M11: =IF($L10>0,$L11/$L10,0) -> 0.19324244 | N11: =IF($L10>0,$L11/$L10,0) -> 0.19324244
A12: Net profit | B12: ='Data Sheet'!B30 -> 4476 | C12: ='Data Sheet'!C30 -> 5214 | D12: ='Data Sheet'!D30 -> 6054 | E12: ='Data Sheet'!E30 -> 6748 | F12: ='Data Sheet'!F30 -> 7995 | G12: ='Data Sheet'!G30 -> 8879 | H12: ='Data Sheet'!H30 -> 10120 | I12: ='Data Sheet'!I30 -> 10277 | ... K12: ='Data Sheet'!K30 -> 15040 | L12: =SUM(Quarters!H12:K12) -> 14957 | M12: =M10-M11*M10 -> 11542.106 | N12: =N10-N11*N10 -> 10953.751
A13: EPS | B13: =IF('Data Sheet'!B93>0,B12/'Data Sheet'!B93,0) -> 20.681052 | C13: =IF('Data Sheet'!C93>0,C12/'Data Sheet'!C93,0) -> 24.088704 | D13: =IF('Data Sheet'!D93>0,D12/'Data Sheet'!D93,0) -> 27.966924 | E13: =IF('Data Sheet'!E93>0,E12/'Data Sheet'!E93,0) -> 31.171471 | F13: =IF('Data Sheet'!F93>0,F12/'Data Sheet'!F93,0) -> 34.027068 | G13: =IF('Data Sheet'!G93>0,G12/'Data Sheet'!G93,0) -> 37.789411 | H13: =IF('Data Sheet'!H93>0,H12/'Data Sheet'!H93,0) -> 43.071161 | I13: =IF('Data Sheet'!I93>0,I12/'Data Sheet'!I93,0) -> 43.73936 | ... K13: =IF('Data Sheet'!K93>0,K12/'Data Sheet'!K93,0) -> 64.010895 | L13: =IF('Data Sheet'!$B6>0,'Profit & Loss'!L12/'Data Sheet'!$B6,0) -> 63.662411 | M13: =IF('Data Sheet'!$B6>0,'Profit & Loss'!M12/'Data Sheet'!$B6,0) -> 49.127385 | N13: =IF('Data Sheet'!$B6>0,'Profit & Loss'!N12/'Data Sheet'!$B6,0) -> 46.623131
A14: Price to earning | B14: =IF(B15>0,B15/B13,"") -> 42.193696 | C14: =IF(C15>0,C15/C13,"") -> 52.975453 | D14: =IF(D15>0,D15/D13,"") -> 58.409356 | E14: =IF(E15>0,E15/E13,"") -> 70.571903 | F14: =IF(F15>0,F15/F13,"") -> 68.390258 | G14: =IF(G15>0,G15/G13,"") -> 51.884905 | H14: =IF(H15>0,H15/H13,"") -> 56.892824 | I14: =IF(I15>0,I15/I13,"") -> 49.546678 | ... K14: =IF(K15>0,K15/K13,"") -> 32.107034 | L14: =IF(L13>0,L15/L13,0) -> 32.999065 | M14: =M25 -> 40.588148 | N14: =N25 -> 32.999065
A15: Price | B15: ='Data Sheet'!B90 -> 872.61 | C15: ='Data Sheet'!C90 -> 1276.11 | D15: ='Data Sheet'!D90 -> 1633.53 | E15: ='Data Sheet'!E90 -> 2199.83 | F15: ='Data Sheet'!F90 -> 2327.12 | G15: ='Data Sheet'!G90 -> 1960.7 | H15: ='Data Sheet'!H90 -> 2450.44 | I15: ='Data Sheet'!I90 -> 2167.14 | ... K15: ='Data Sheet'!K90 -> 2055.2 | L15: ='Data Sheet'!B8 -> 2100.8 | N15: =N13*N14 -> 1538.5197
A17: RATIOS:
A18: Dividend Payout | B18: =IF('Data Sheet'!B30>0, 'Data Sheet'!B31/'Data Sheet'!B30, 0) -> 0.82037534 | C18: =IF('Data Sheet'!C30>0, 'Data Sheet'!C31/'Data Sheet'!C30, 0) -> 0.82853855 | D18: =IF('Data Sheet'!D30>0, 'Data Sheet'!D31/'Data Sheet'!D30, 0) -> 0.78493558 | E18: =IF('Data Sheet'!E30>0, 'Data Sheet'!E31/'Data Sheet'!E30, 0) -> 0.80023711 | F18: =IF('Data Sheet'!F30>0, 'Data Sheet'!F31/'Data Sheet'!F30, 0) -> 1.1904315 | G18: =IF('Data Sheet'!G30>0, 'Data Sheet'!G31/'Data Sheet'!G30, 0) -> 0.89987611 | H18: =IF('Data Sheet'!H30>0, 'Data Sheet'!H31/'Data Sheet'!H30, 0) -> 0.90563241 | I18: =IF('Data Sheet'!I30>0, 'Data Sheet'!I31/'Data Sheet'!I30, 0) -> 0.960397 | ... K18: =IF('Data Sheet'!K30>0, 'Data Sheet'!K31/'Data Sheet'!K30, 0) -> 0.640625
A19: OPM | B19: =IF(B6>0,B6/B4,0) -> 0.19082082 | C19: =IF(C6>0,C6/C4,0) -> 0.21097201 | D19: =IF(D6>0,D6/D4,0) -> 0.22589672 | E19: =IF(E6>0,E6/E4,0) -> 0.24786969 | F19: =IF(F6>0,F6/F4,0) -> 0.24721443 | G19: =IF(G6>0,G6/G4,0) -> 0.24514739 | H19: =IF(H6>0,H6/H4,0) -> 0.23352592 | I19: =IF(I6>0,I6/I4,0) -> 0.23683275 | ... L19: =IF(L6>0,L6/L4,0) -> 0.23234724
G22: TRENDS: | H22: 10 YEARS | I22: 7 YEARS | J22: 5 YEARS | K22: 3 YEARS | L22: RECENT | M22: BEST | N22: WORST
G23: Sales Growth | H23: =IF(B4=0,"",POWER($K4/B4,1/9)-1) -> 0.076658974 | I23: =IF(D4=0,"",POWER($K4/D4,1/7)-1) -> 0.073227008 | J23: =IF(F4=0,"",POWER($K4/F4,1/5)-1) -> 0.065117542 | K23: =IF(H4=0,"",POWER($K4/H4, 1/3)-1) -> 0.020951182 | L23: =IF(ISERROR(MAX(IF(J4=0,"",(K4-J4)/J4),IF(K4=0,"",(L4-K4)/K4))),"",MAX(IF(J4=0,"",(K4-J4)/J4),IF(K4=0,"",(L4-K4)/K4))) -> 0.051200104 | M23: =MAX(K23:L23) -> 0.051200104 | N23: =MIN(H23:L23) -> 0.020951182
G24: OPM | H24: =IF(SUM(B4:$K$4)=0,"",SUMPRODUCT(B19:$K$19,B4:$K$4)/SUM(B4:$K$4)) -> 0.23326593 | I24: =IF(SUM(E4:$K$4)=0,"",SUMPRODUCT(E19:$K$19,E4:$K$4)/SUM(E4:$K$4)) -> 0.23969045 | J24: =IF(SUM(G4:$K$4)=0,"",SUMPRODUCT(G19:$K$19,G4:$K$4)/SUM(G4:$K$4)) -> 0.23743175 | K24: =IF(SUM(I4:$K$4)=0, "", SUMPRODUCT(I19:$K$19,I4:$K$4)/SUM(I4:$K$4)) -> 0.23653645 | L24: =L19 -> 0.23234724 | M24: =MAX(K24:L24) -> 0.23653645 | N24: =MIN(H24:L24) -> 0.23234724
G25: Price to Earning | H25: =IF(ISERROR(AVERAGEIF(B14:$L14,">0")),"",AVERAGEIF(B14:$L14,">0")) -> 51.242817 | I25: =IF(ISERROR(AVERAGEIF(E14:$L14,">0")),"",AVERAGEIF(E14:$L14,">0")) -> 51.26156 | J25: =IF(ISERROR(AVERAGEIF(G14:$L14,">0")),"",AVERAGEIF(G14:$L14,">0")) -> 45.188387 | K25: =IF(ISERROR(AVERAGEIF(I14:$L14,">0")),"",AVERAGEIF(I14:$L14,">0")) -> 40.588148 | L25: =L14 -> 32.999065 | M25: =MAX(K25:L25) -> 40.588148 | N25: =MIN(H25:L25) -> 32.999065

Sheet Balance Sheet
A1: ='Profit & Loss'!A1 -> HINDUSTAN UNILEVER LTD | E1: =UPDATE | J1: SCREENER.IN
A3: Narration | B3: ='Data Sheet'!B56 -> 42825 | C3: ='Data Sheet'!C56 -> 43190 | D3: ='Data Sheet'!D56 -> 43555 | E3: ='Data Sheet'!E56 -> 43921 | F3: ='Data Sheet'!F56 -> 44286 | G3: ='Data Sheet'!G56 -> 44651 | H3: ='Data Sheet'!H56 -> 45016 | I3: ='Data Sheet'!I56 -> 45382 | ... K3: ='Data Sheet'!K56 -> 46112
A4: Equity Share Capital | B4: ='Data Sheet'!B57 -> 216 | C4: ='Data Sheet'!C57 -> 216 | D4: ='Data Sheet'!D57 -> 216 | E4: ='Data Sheet'!E57 -> 216 | F4: ='Data Sheet'!F57 -> 235 | G4: ='Data Sheet'!G57 -> 235 | H4: ='Data Sheet'!H57 -> 235 | I4: ='Data Sheet'!I57 -> 235 | ... K4: ='Data Sheet'!K57 -> 235
A5: Reserves | B5: ='Data Sheet'!B58 -> 6528 | C5: ='Data Sheet'!C58 -> 7065 | D5: ='Data Sheet'!D58 -> 7651 | E5: ='Data Sheet'!E58 -> 8013 | F5: ='Data Sheet'!F58 -> 47439 | G5: ='Data Sheet'!G58 -> 48826 | H5: ='Data Sheet'!H58 -> 50069 | I5: ='Data Sheet'!I58 -> 50983 | ... K5: ='Data Sheet'!K58 -> 48504
A6: Borrowings | B6: ='Data Sheet'!B59 -> 277 | C6: ='Data Sheet'!C59 -> 0 | D6: ='Data Sheet'!D59 -> 99 | E6: ='Data Sheet'!E59 -> 0 | F6: ='Data Sheet'!F59 -> 0 | G6: ='Data Sheet'!G59 -> 1043 | H6: ='Data Sheet'!H59 -> 1219 | I6: ='Data Sheet'!I59 -> 1484 | ... K6: ='Data Sheet'!K59 -> 1478
A7: Other Liabilities | B7: ='Data Sheet'!B60 -> 8685 | C7: ='Data Sheet'!C60 -> 10581 | D7: ='Data Sheet'!D60 -> 10663 | E7: ='Data Sheet'!E60 -> 11924 | F7: ='Data Sheet'!F60 -> 21066 | G7: ='Data Sheet'!G60 -> 20402 | H7: ='Data Sheet'!H60 -> 21554 | I7: ='Data Sheet'!I60 -> 25787 | ... K7: ='Data Sheet'!K60 -> 29521
A8: Total | B8: ='Data Sheet'!B61 -> 15706 | C8: ='Data Sheet'!C61 -> 17862 | D8: ='Data Sheet'!D61 -> 18629 | E8: ='Data Sheet'!E61 -> 20153 | F8: ='Data Sheet'!F61 -> 68740 | G8: ='Data Sheet'!G61 -> 70506 | H8: ='Data Sheet'!H61 -> 73077 | I8: ='Data Sheet'!I61 -> 78489 | ... K8: ='Data Sheet'!K61 -> 79738
A10: Net Block | B10: ='Data Sheet'!B62 -> 4419 | C10: ='Data Sheet'!C62 -> 4528 | D10: ='Data Sheet'!D62 -> 4715 | E10: ='Data Sheet'!E62 -> 5479 | F10: ='Data Sheet'!F62 -> 51443 | G10: ='Data Sheet'!G62 -> 51473 | H10: ='Data Sheet'!H62 -> 52678 | I10: ='Data Sheet'!I62 -> 53744 | ... K10: ='Data Sheet'!K62 -> 57428
A11: Capital Work in Progress | B11: ='Data Sheet'!B63 -> 229 | C11: ='Data Sheet'!C63 -> 461 | D11: ='Data Sheet'!D63 -> 406 | E11: ='Data Sheet'!E63 -> 597 | F11: ='Data Sheet'!F63 -> 745 | G11: ='Data Sheet'!G63 -> 1313 | H11: ='Data Sheet'!H63 -> 1132 | I11: ='Data Sheet'!I63 -> 1025 | ... K11: ='Data Sheet'!K63 -> 880
A12: Investments | B12: ='Data Sheet'!B64 -> 3794 | C12: ='Data Sheet'!C64 -> 2873 | D12: ='Data Sheet'!D64 -> 2716 | E12: ='Data Sheet'!E64 -> 1255 | F12: ='Data Sheet'!F64 -> 2709 | G12: ='Data Sheet'!G64 -> 3521 | H12: ='Data Sheet'!H64 -> 2882 | I12: ='Data Sheet'!I64 -> 4625 | ... K12: ='Data Sheet'!K64 -> 4359
A13: Other Assets | B13: ='Data Sheet'!B65 -> 7264 | C13: ='Data Sheet'!C65 -> 10000 | D13: ='Data Sheet'!D65 -> 10792 | E13: ='Data Sheet'!E65 -> 12822 | F13: ='Data Sheet'!F65 -> 13843 | G13: ='Data Sheet'!G65 -> 14199 | H13: ='Data Sheet'!H65 -> 16385 | I13: ='Data Sheet'!I65 -> 19095 | ... K13: ='Data Sheet'!K65 -> 17071
A14: Total | B14: ='Data Sheet'!B66 -> 15706 | C14: ='Data Sheet'!C66 -> 17862 | D14: ='Data Sheet'!D66 -> 18629 | E14: ='Data Sheet'!E66 -> 20153 | F14: ='Data Sheet'!F66 -> 68740 | G14: ='Data Sheet'!G66 -> 70506 | H14: ='Data Sheet'!H66 -> 73077 | I14: ='Data Sheet'!I66 -> 78489 | ... K14: ='Data Sheet'!K66 -> 79738
A16: Working Capital | B16: =B13-B7 -> -1421 | C16: =C13-C7 -> -581 | D16: =D13-D7 -> 129 | E16: =E13-E7 -> 898 | F16: =F13-F7 -> -7223 | G16: =G13-G7 -> -6203 | H16: =H13-H7 -> -5169 | I16: =I13-I7 -> -6692 | ... K16: =K13-K7 -> -12450
A17: Debtors | B17: ='Data Sheet'!B67 -> 1085 | C17: ='Data Sheet'!C67 -> 1310 | D17: ='Data Sheet'!D67 -> 1816 | E17: ='Data Sheet'!E67 -> 1149 | F17: ='Data Sheet'!F67 -> 1758 | G17: ='Data Sheet'!G67 -> 2236 | H17: ='Data Sheet'!H67 -> 3079 | I17: ='Data Sheet'!I67 -> 2997 | ... K17: ='Data Sheet'!K67 -> 3379
A18: Inventory | B18: ='Data Sheet'!B68 -> 2541 | C18: ='Data Sheet'!C68 -> 2513 | D18: ='Data Sheet'!D68 -> 2574 | E18: ='Data Sheet'!E68 -> 2767 | F18: ='Data Sheet'!F68 -> 3579 | G18: ='Data Sheet'!G68 -> 4096 | H18: ='Data Sheet'!H68 -> 4251 | I18: ='Data Sheet'!I68 -> 4022 | ... K18: ='Data Sheet'!K68 -> 4789
A20: Debtor Days | B20: =IF('Profit & Loss'!B4>0,'Balance Sheet'!B17/('Profit & Loss'!B4/365),0) -> 11.942133 | C20: =IF('Profit & Loss'!C4>0,'Balance Sheet'!C17/('Profit & Loss'!C4/365),0) -> 13.451962 | D20: =IF('Profit & Loss'!D4>0,'Balance Sheet'!D17/('Profit & Loss'!D4/365),0) -> 16.861867 | E20: =IF('Profit & Loss'!E4>0,'Balance Sheet'!E17/('Profit & Loss'!E4/365),0) -> 10.541814 | F20: =IF('Profit & Loss'!F4>0,'Balance Sheet'!F17/('Profit & Loss'!F4/365),0) -> 13.644425 | G20: =IF('Profit & Loss'!G4>0,'Balance Sheet'!G17/('Profit & Loss'!G4/365),0) -> 15.56153 | H20: =IF('Profit & Loss'!H4>0,'Balance Sheet'!H17/('Profit & Loss'!H4/365),0) -> 18.551255 | I20: =IF('Profit & Loss'!I4>0,'Balance Sheet'!I17/('Profit & Loss'!I4/365),0) -> 17.673275 | ... K20: =IF('Profit & Loss'!K4>0,'Balance Sheet'!K17/('Profit & Loss'!K4/365),0) -> 19.130964
A21: Inventory Turnover | B21: =IF('Balance Sheet'!B18>0,'Profit & Loss'!B4/'Balance Sheet'!B18,0) -> 13.050767 | C21: =IF('Balance Sheet'!C18>0,'Profit & Loss'!C4/'Balance Sheet'!C18,0) -> 14.144449 | D21: =IF('Balance Sheet'!D18>0,'Profit & Loss'!D4/'Balance Sheet'!D18,0) -> 15.27195 | E21: =IF('Balance Sheet'!E18>0,'Profit & Loss'!E4/'Balance Sheet'!E18,0) -> 14.377665 | F21: =IF('Balance Sheet'!F18>0,'Profit & Loss'!F4/'Balance Sheet'!F18,0) -> 13.139983 | G21: =IF('Balance Sheet'!G18>0,'Profit & Loss'!G4/'Balance Sheet'!G18,0) -> 12.804199 | H21: =IF('Balance Sheet'!H18>0,'Profit & Loss'!H4/'Balance Sheet'!H18,0) -> 14.250765 | I21: =IF('Balance Sheet'!I18>0,'Profit & Loss'!I4/'Balance Sheet'!I18,0) -> 15.389359 | ... K21: =IF('Balance Sheet'!K18>0,'Profit & Loss'!K4/'Balance Sheet'!K18,0) -> 13.461683
A23: Return on Equity | B23: =IF(SUM('Balance Sheet'!B4:B5)>0,'Profit & Loss'!B12/SUM('Balance Sheet'!B4:B5),"") -> 0.66370107 | C23: =IF(SUM('Balance Sheet'!C4:C5)>0,'Profit & Loss'!C12/SUM('Balance Sheet'!C4:C5),"") -> 0.71611042 | D23: =IF(SUM('Balance Sheet'!D4:D5)>0,'Profit & Loss'!D12/SUM('Balance Sheet'!D4:D5),"") -> 0.76954366 | E23: =IF(SUM('Balance Sheet'!E4:E5)>0,'Profit & Loss'!E12/SUM('Balance Sheet'!E4:E5),"") -> 0.82002673 | F23: =IF(SUM('Balance Sheet'!F4:F5)>0,'Profit & Loss'!F12/SUM('Balance Sheet'!F4:F5),"") -> 0.16770147 | G23: =IF(SUM('Balance Sheet'!G4:G5)>0,'Profit & Loss'!G12/SUM('Balance Sheet'!G4:G5),"") -> 0.18097878 | H23: =IF(SUM('Balance Sheet'!H4:H5)>0,'Profit & Loss'!H12/SUM('Balance Sheet'!H4:H5),"") -> 0.20117684 | I23: =IF(SUM('Balance Sheet'!I4:I5)>0,'Profit & Loss'!I12/SUM('Balance Sheet'!I4:I5),"") -> 0.20065211 | ... K23: =IF(SUM('Balance Sheet'!K4:K5)>0,'Profit & Loss'!K12/SUM('Balance Sheet'!K4:K5),"") -> 0.30858245
A24: Return on Capital Emp | C24: =IF((B4+B5+B6+C4+C5+C6)>0,('Profit & Loss'!C10+'Profit & Loss'!C9)*2/(B4+B5+B6+C4+C5+C6),"") -> 1.0253111 | D24: =IF((C4+C5+C6+D4+D5+D6)>0,('Profit & Loss'!D10+'Profit & Loss'!D9)*2/(C4+C5+C6+D4+D5+D6),"") -> 1.1329442 | E24: =IF((D4+D5+D6+E4+E5+E6)>0,('Profit & Loss'!E10+'Profit & Loss'!E9)*2/(D4+D5+D6+E4+E5+E6),"") -> 1.1464032 | F24: =IF((E4+E5+E6+F4+F5+F6)>0,('Profit & Loss'!F10+'Profit & Loss'!F9)*2/(E4+E5+E6+F4+F5+F6),"") -> 0.38359301 | G24: =IF((F4+F5+F6+G4+G5+G6)>0,('Profit & Loss'!G10+'Profit & Loss'!G9)*2/(F4+F5+F6+G4+G5+G6),"") -> 0.24514717 | H24: =IF((G4+G5+G6+H4+H5+H6)>0,('Profit & Loss'!H10+'Profit & Loss'!H9)*2/(G4+G5+G6+H4+H5+H6),"") -> 0.26485088 | I24: =IF((H4+H5+H6+I4+I5+I6)>0,('Profit & Loss'!I10+'Profit & Loss'!I9)*2/(H4+H5+H6+I4+I5+I6),"") -> 0.27363876 | J24: =IF((I4+I5+I6+J4+J5+J6)>0,('Profit & Loss'!J10+'Profit & Loss'!J9)*2/(I4+I5+I6+J4+J5+J6),"") -> 0.28529571 | K24: =IF((J4+J5+J6+K4+K5+K6)>0,('Profit & Loss'!K10+'Profit & Loss'!K9)*2/(J4+J5+J6+K4+K5+K6),"") -> 0.36791847

Sheet Cash Flow
A1: ='Balance Sheet'!A1 -> HINDUSTAN UNILEVER LTD | E1: =UPDATE | J1: SCREENER.IN
A3: Narration | B3: ='Data Sheet'!B81 -> 42825 | C3: ='Data Sheet'!C81 -> 43190 | D3: ='Data Sheet'!D81 -> 43555 | E3: ='Data Sheet'!E81 -> 43921 | F3: ='Data Sheet'!F81 -> 44286 | G3: ='Data Sheet'!G81 -> 44651 | H3: ='Data Sheet'!H81 -> 45016 | I3: ='Data Sheet'!I81 -> 45382 | ... K3: ='Data Sheet'!K81 -> 46112
A4: Cash from Operating Activity | B4: ='Data Sheet'!B82 -> 5185 | C4: ='Data Sheet'!C82 -> 6059 | D4: ='Data Sheet'!D82 -> 5800 | E4: ='Data Sheet'!E82 -> 7623 | F4: ='Data Sheet'!F82 -> 9163 | G4: ='Data Sheet'!G82 -> 9048 | H4: ='Data Sheet'!H82 -> 9991 | I4: ='Data Sheet'!I82 -> 15469 | ... K4: ='Data Sheet'!K82 -> 10999
A5: Cash from Investing Activity | B5: ='Data Sheet'!B83 -> -1173 | C5: ='Data Sheet'!C83 -> -1063 | D5: ='Data Sheet'!D83 -> -438 | E5: ='Data Sheet'!E83 -> 1791 | F5: ='Data Sheet'!F83 -> -1228 | G5: ='Data Sheet'!G83 -> -1728 | H5: ='Data Sheet'!H83 -> -1484 | I5: ='Data Sheet'!I83 -> -5324 | ... K5: ='Data Sheet'!K83 -> -3676
A6: Cash from Financing Activity | B6: ='Data Sheet'!B84 -> -4214 | C6: ='Data Sheet'!C84 -> -4975 | D6: ='Data Sheet'!D84 -> -5390 | E6: ='Data Sheet'!E84 -> -6819 | F6: ='Data Sheet'!F84 -> -9309 | G6: ='Data Sheet'!G84 -> -8015 | H6: ='Data Sheet'!H84 -> -8953 | I6: ='Data Sheet'!I84 -> -10034 | ... K6: ='Data Sheet'!K84 -> -10810
A7: Net Cash Flow | B7: ='Data Sheet'!B85 -> -202 | C7: ='Data Sheet'!C85 -> 21 | D7: ='Data Sheet'!D85 -> -28 | E7: ='Data Sheet'!E85 -> 2595 | F7: ='Data Sheet'!F85 -> -1374 | G7: ='Data Sheet'!G85 -> -695 | H7: ='Data Sheet'!H85 -> -446 | I7: ='Data Sheet'!I85 -> 111 | ... K7: ='Data Sheet'!K85 -> -3487

Sheet Cash Flow Data
B3: Cash Flows
B4: Consolidated Figures in Rs. Crores / View Standalone
C5: 42064 | D5: 42430 | E5: 42795 | F5: 43160 | G5: 43525 | H5: 43891 | I5: 44256 | J5: 44621 | K5: 44986 | L5: 45352 | M5: 45717 | N5: 46082
B6: Cash from Operating Activity - | C6: 3292 | D6: 4171 | E6: 5185 | F6: 6059 | G6: 5800 | H6: 7623 | I6: 9163 | J6: 9048 | K6: 9991 | L6: 15469 | M6: 11886 | N6: 10999
B7: Profit from operations | C7: 5510 | D7: 6025 | E7: 6512 | F7: 7485 | G7: 8909 | H7: 9723 | I7: 11672 | J7: 12829 | K7: 14089 | L7: 14537 | M7: 14942 | N7: 15153
B8: Receivables | C8: 3 | D8: -257 | E8: 173 | F8: 0 | G8: 0 | H8: 0 | I8: 0 | J8: 0 | K8: 0 | L8: 0 | M8: 0 | N8: 0
B9: Inventory | C9: 91 | D9: 89 | E9: 37 | F9: -146 | G9: -195 | H9: -331 | I9: -543 | J9: -758 | K9: -339 | L9: 74 | M9: -584 | N9: -692
B10: Payables | C10: -327 | D10: 164 | E10: 501 | F10: 0 | G10: 0 | H10: 0 | I10: 0 | J10: 0 | K10: 0 | L10: 0 | M10: 0 | N10: 0
B11: Loans Advances | C11: -148 | D11: 0 | E11: 0 | F11: 0 | G11: 0 | H11: 0 | I11: 0 | J11: 0 | K11: 0 | L11: 0 | M11: 0 | N11: 0
B12: Operating Deposits | C12: 0 | D12: 0 | E12: -46 | F12: 0 | G12: 0 | H12: 0 | I12: 0 | J12: 0 | K12: 0 | L12: 0 | M12: 0 | N12: 0
B13: Other WC items | C13: 38 | D13: -77 | E13: -99 | F13: 982 | G13: -147 | H13: 742 | I13: 442 | J13: -242 | K13: -621 | L13: 1239 | M13: -204 | N13: 1378
B14: Working capital changes | C14: -342 | D14: -81 | E14: 566 | F14: 836 | G14: -342 | H14: 411 | I14: -101 | J14: -1000 | K14: -960 | L14: 1313 | M14: -788 | N14: 686
B15: Direct taxes | C15: -1862 | D15: -1765 | E15: -1859 | F15: -2264 | G15: -2767 | H15: -2505 | I15: -2407 | J15: -2784 | K15: -3138 | L15: -381 | M15: -2268 | N15: -4840
B16: Other operating items | C16: -14 | D16: -8 | E16: -21 | F16: 0 | G16: 0 | H16: 0 | I16: 0 | J16: 0 | K16: 0 | L16: 0 | M16: 0 | N16: 0
B17: Exceptional CF items | C17: 0 | D17: 0 | E17: -13 | F17: 2 | G17: 0 | H17: -6 | I17: -1 | J17: 3 | K17: 0 | L17: 0 | M17: 0 | N17: 0
... B38: CFO/OP | C38: 0.95 | D38: 1 | E38: 1.11 | F38: 1.11 | G38: 0.96 | H38: 1.03 | I38: 1 | J38: 0.92 | K38: 0.93 | L38: 1.08 | M38: 0.96 | N38: 1.05

Sheet Quarters
A1: ='Profit & Loss'!A1 -> HINDUSTAN UNILEVER LTD | E1: =UPDATE | J1: SCREENER.IN
A3: Narration | B3: ='Data Sheet'!B41 -> 45382 | C3: ='Data Sheet'!C41 -> 45473 | D3: ='Data Sheet'!D41 -> 45565 | E3: ='Data Sheet'!E41 -> 45657 | F3: ='Data Sheet'!F41 -> 45747 | G3: ='Data Sheet'!G41 -> 45838 | H3: ='Data Sheet'!H41 -> 45930 | I3: ='Data Sheet'!I41 -> 46022 | ... K3: ='Data Sheet'!K41 -> 46203
A4: Sales | B4: ='Data Sheet'!B42 -> 15210 | C4: ='Data Sheet'!C42 -> 15707 | D4: ='Data Sheet'!D42 -> 15926 | E4: ='Data Sheet'!E42 -> 15556 | F4: ='Data Sheet'!F42 -> 15190 | G4: ='Data Sheet'!G42 -> 15757 | H4: ='Data Sheet'!H42 -> 15919 | I4: ='Data Sheet'!I42 -> 16441 | ... K4: ='Data Sheet'!K42 -> 17341
A5: Expenses | B5: ='Data Sheet'!B43 -> 11675 | C5: ='Data Sheet'!C43 -> 11965 | D5: ='Data Sheet'!D43 -> 12139 | E5: ='Data Sheet'!E43 -> 11867 | F5: ='Data Sheet'!F43 -> 11572 | G5: ='Data Sheet'!G43 -> 12118 | H5: ='Data Sheet'!H43 -> 12137 | I5: ='Data Sheet'!I43 -> 12660 | ... K5: ='Data Sheet'!K43 -> 13394
A6: Operating Profit | B6: ='Data Sheet'!B50 -> 3535 | C6: ='Data Sheet'!C50 -> 3742 | D6: ='Data Sheet'!D50 -> 3787 | E6: ='Data Sheet'!E50 -> 3689 | F6: ='Data Sheet'!F50 -> 3618 | G6: ='Data Sheet'!G50 -> 3639 | H6: ='Data Sheet'!H50 -> 3782 | I6: ='Data Sheet'!I50 -> 3781 | ... K6: ='Data Sheet'!K50 -> 3947
A7: Other Income | B7: ='Data Sheet'!B44 -> 309 | C7: ='Data Sheet'!C44 -> 209 | D7: ='Data Sheet'!D44 -> 203 | E7: ='Data Sheet'!E44 -> 733 | F7: ='Data Sheet'!F44 -> 149 | G7: ='Data Sheet'!G44 -> 103 | H7: ='Data Sheet'!H44 -> 269 | I7: ='Data Sheet'!I44 -> 4048 | ... K7: ='Data Sheet'!K44 -> 113
A8: Depreciation | B8: ='Data Sheet'!B45 -> 320 | C8: ='Data Sheet'!C45 -> 329 | D8: ='Data Sheet'!D45 -> 338 | E8: ='Data Sheet'!E45 -> 318 | F8: ='Data Sheet'!F45 -> 318 | G8: ='Data Sheet'!G45 -> 326 | H8: ='Data Sheet'!H45 -> 322 | I8: ='Data Sheet'!I45 -> 337 | ... K8: ='Data Sheet'!K45 -> 353
A9: Interest | B9: ='Data Sheet'!B46 -> 105 | C9: ='Data Sheet'!C46 -> 93 | D9: ='Data Sheet'!D46 -> 110 | E9: ='Data Sheet'!E46 -> 109 | F9: ='Data Sheet'!F46 -> 77 | G9: ='Data Sheet'!G46 -> 122 | H9: ='Data Sheet'!H46 -> 124 | I9: ='Data Sheet'!I46 -> 88 | ... K9: ='Data Sheet'!K46 -> 75
A10: Profit before tax | B10: ='Data Sheet'!B47 -> 3419 | C10: ='Data Sheet'!C47 -> 3529 | D10: ='Data Sheet'!D47 -> 3542 | E10: ='Data Sheet'!E47 -> 3995 | F10: ='Data Sheet'!F47 -> 3372 | G10: ='Data Sheet'!G47 -> 3294 | H10: ='Data Sheet'!H47 -> 3605 | I10: ='Data Sheet'!I47 -> 7404 | ... K10: ='Data Sheet'!K47 -> 3632
A11: Tax | B11: ='Data Sheet'!B48 -> 858 | C11: ='Data Sheet'!C48 -> 917 | D11: ='Data Sheet'!D48 -> 947 | E11: ='Data Sheet'!E48 -> 1006 | F11: ='Data Sheet'!F48 -> 897 | G11: ='Data Sheet'!G48 -> 526 | H11: ='Data Sheet'!H48 -> 911 | I11: ='Data Sheet'!I48 -> 801 | ... K11: ='Data Sheet'!K48 -> 952
A12: Net profit | B12: ='Data Sheet'!B49 -> 2558 | C12: ='Data Sheet'!C49 -> 2610 | D12: ='Data Sheet'!D49 -> 2591 | E12: ='Data Sheet'!E49 -> 2984 | F12: ='Data Sheet'!F49 -> 2464 | G12: ='Data Sheet'!G49 -> 2756 | H12: ='Data Sheet'!H49 -> 2685 | I12: ='Data Sheet'!I49 -> 6607 | ... K12: ='Data Sheet'!K49 -> 2673
A14: OPM | B14: =IF(B4>0,B6/B4,"") -> 0.23241289 | C14: =IF(C4>0,C6/C4,"") -> 0.23823773 | D14: =IF(D4>0,D6/D4,"") -> 0.23778727 | E14: =IF(E4>0,E6/E4,"") -> 0.23714322 | F14: =IF(F4>0,F6/F4,"") -> 0.23818302 | G14: =IF(G4>0,G6/G4,"") -> 0.23094498 | H14: =IF(H4>0,H6/H4,"") -> 0.23757774 | I14: =IF(I4>0,I6/I4,"") -> 0.22997385 | ... K14: =IF(K4>0,K6/K4,"") -> 0.22761086

Sheet Common Size Statement
B2: 1. COMMON SIZE STATEMENT — PROFIT & LOSS ACCOUNT (Base = Net Sales = 100%)
B3: Particulars | C3: FY17 | D3: FY18 | E3: FY19 | F3: FY20 | G3: FY21 | H3: FY22 | I3: FY23 | J3: FY24 | K3: FY25 | L3: FY26
B4: Sales | C4: ='Data Sheet'!B17/'Data Sheet'!B$17 -> 1 | D4: ='Data Sheet'!C17/'Data Sheet'!C$17 -> 1 | E4: ='Data Sheet'!D17/'Data Sheet'!D$17 -> 1 | F4: ='Data Sheet'!E17/'Data Sheet'!E$17 -> 1 | G4: ='Data Sheet'!F17/'Data Sheet'!F$17 -> 1 | H4: ='Data Sheet'!G17/'Data Sheet'!G$17 -> 1 | I4: ='Data Sheet'!H17/'Data Sheet'!H$17 -> 1 | J4: ='Data Sheet'!I17/'Data Sheet'!I$17 -> 1 | ... L4: ='Data Sheet'!K17/'Data Sheet'!K$17 -> 1
B5: Raw Material Cost | C5: ='Data Sheet'!B18/'Data Sheet'!B$17 -> 0.41028888 | D5: ='Data Sheet'!C18/'Data Sheet'!C$17 -> 0.400422 | E5: ='Data Sheet'!D18/'Data Sheet'!D$17 -> 0.4030781 | F5: ='Data Sheet'!E18/'Data Sheet'!E$17 -> 0.39456552 | G5: ='Data Sheet'!F18/'Data Sheet'!F$17 -> 0.42827677 | H5: ='Data Sheet'!G18/'Data Sheet'!G$17 -> 0.43608664 | I5: ='Data Sheet'!H18/'Data Sheet'!H$17 -> 0.46924728 | J5: ='Data Sheet'!I18/'Data Sheet'!I$17 -> 0.4333398 | ... L5: ='Data Sheet'!K18/'Data Sheet'!K$17 -> 0.45228641
B6: Change in Inventory | C6: ='Data Sheet'!B19/'Data Sheet'!B$17 -> -0.0043423195 | D6: ='Data Sheet'!C19/'Data Sheet'!C$17 -> 0.0020256014 | E6: ='Data Sheet'!D19/'Data Sheet'!D$17 -> -0.00030526584 | F6: ='Data Sheet'!E19/'Data Sheet'!E$17 -> 0.0027147274 | G6: ='Data Sheet'!F19/'Data Sheet'!F$17 -> 0.0086118908 | H6: ='Data Sheet'!G19/'Data Sheet'!G$17 -> 0.00041947908 | I6: ='Data Sheet'!H19/'Data Sheet'!H$17 -> 0.0012380324 | J6: ='Data Sheet'!I19/'Data Sheet'!I$17 -> 0.00017771746 | ... L6: ='Data Sheet'!K19/'Data Sheet'!K$17 -> 0.0066544642
B7: Power and Fuel | C7: ='Data Sheet'!B20/'Data Sheet'!B$17 -> 0.008895724 | D7: ='Data Sheet'!C20/'Data Sheet'!C$17 -> 0.0082993389 | E7: ='Data Sheet'!D20/'Data Sheet'!D$17 -> 0.0078351564 | F7: ='Data Sheet'!E20/'Data Sheet'!E$17 -> 0.0075157731 | G7: ='Data Sheet'!F20/'Data Sheet'!F$17 -> 0.0072084715 | H7: ='Data Sheet'!G20/'Data Sheet'!G$17 -> 0.0060633795 | I7: ='Data Sheet'!H20/'Data Sheet'!H$17 -> 0.0063387257 | J7: ='Data Sheet'!I20/'Data Sheet'!I$17 -> 0.0072056353 | ... L7: ='Data Sheet'!K20/'Data Sheet'!K$17 -> 0.0066079295
B8: Other Mfr. Exp | C8: ='Data Sheet'!B21/'Data Sheet'!B$17 -> 0.087057475 | D8: ='Data Sheet'!C21/'Data Sheet'!C$17 -> 0.08434379 | E8: ='Data Sheet'!D21/'Data Sheet'!D$17 -> 0.077359451 | F8: ='Data Sheet'!E21/'Data Sheet'!E$17 -> 0.073046276 | G8: ='Data Sheet'!F21/'Data Sheet'!F$17 -> 0.060984945 | H8: ='Data Sheet'!G21/'Data Sheet'!G$17 -> 0.063951493 | I8: ='Data Sheet'!H21/'Data Sheet'!H$17 -> 0.062578409 | J8: ='Data Sheet'!I21/'Data Sheet'!I$17 -> 0.05468851 | ... L8: ='Data Sheet'!K21/'Data Sheet'!K$17 -> 0.051250233
B9: Employee Cost | C9: ='Data Sheet'!B22/'Data Sheet'!B$17 -> 0.052560159 | D9: ='Data Sheet'!C22/'Data Sheet'!C$17 -> 0.052328035 | E9: ='Data Sheet'!D22/'Data Sheet'!D$17 -> 0.047697787 | F9: ='Data Sheet'!E22/'Data Sheet'!E$17 -> 0.045748184 | G9: ='Data Sheet'!F22/'Data Sheet'!F$17 -> 0.050140342 | H9: ='Data Sheet'!G22/'Data Sheet'!G$17 -> 0.048526103 | I9: ='Data Sheet'!H22/'Data Sheet'!H$17 -> 0.047111258 | J9: ='Data Sheet'!I22/'Data Sheet'!I$17 -> 0.048613804 | ... L9: ='Data Sheet'!K22/'Data Sheet'!K$17 -> 0.04924924
B10: Selling and admin | C10: ='Data Sheet'!B23/'Data Sheet'!B$17 -> 0.20170677 | D10: ='Data Sheet'!C23/'Data Sheet'!C$17 -> 0.20402307 | E10: ='Data Sheet'!D23/'Data Sheet'!D$17 -> 0.19832104 | F10: ='Data Sheet'!E23/'Data Sheet'!E$17 -> 0.1915391 | G10: ='Data Sheet'!F23/'Data Sheet'!F$17 -> 0.16811261 | H10: ='Data Sheet'!G23/'Data Sheet'!G$17 -> 0.15566487 | I10: ='Data Sheet'!H23/'Data Sheet'!H$17 -> 0.14501486 | J10: ='Data Sheet'!I23/'Data Sheet'!I$17 -> 0.17416311 | ... L10: ='Data Sheet'!K23/'Data Sheet'!K$17 -> 0.16665633
B11: Other Expenses | C11: ='Data Sheet'!B24/'Data Sheet'!B$17 -> 0.044327845 | D11: ='Data Sheet'!C24/'Data Sheet'!C$17 -> 0.041637361 | E11: ='Data Sheet'!D24/'Data Sheet'!D$17 -> 0.039506487 | F11: ='Data Sheet'!E24/'Data Sheet'!E$17 -> 0.042430184 | G11: ='Data Sheet'!F24/'Data Sheet'!F$17 -> 0.046674322 | H11: ='Data Sheet'!G24/'Data Sheet'!G$17 -> 0.044979598 | I11: ='Data Sheet'!H24/'Data Sheet'!H$17 -> 0.037421591 | J11: ='Data Sheet'!I24/'Data Sheet'!I$17 -> 0.045334109 | ... L11: ='Data Sheet'!K24/'Data Sheet'!K$17 -> 0.047325805
B12: Other Income | C12: ='Data Sheet'!B25/'Data Sheet'!B$17 -> 0.018273928 | D12: ='Data Sheet'!C25/'Data Sheet'!C$17 -> 0.0099310733 | E12: ='Data Sheet'!D25/'Data Sheet'!D$17 -> 0.0081912999 | F12: ='Data Sheet'!E25/'Data Sheet'!E$17 -> 0.010657819 | G12: ='Data Sheet'!F25/'Data Sheet'!F$17 -> 0.0036148677 | H12: ='Data Sheet'!G25/'Data Sheet'!G$17 -> 0.0041757236 | I12: ='Data Sheet'!H25/'Data Sheet'!H$17 -> 0.0073951799 | J12: ='Data Sheet'!I25/'Data Sheet'!I$17 -> 0.013199561 | ... L12: ='Data Sheet'!K25/'Data Sheet'!K$17 -> 0.076363467
B13: Depreciation | C13: ='Data Sheet'!B26/'Data Sheet'!B$17 -> 0.013026959 | D13: ='Data Sheet'!C26/'Data Sheet'!C$17 -> 0.014629343 | E13: ='Data Sheet'!D26/'Data Sheet'!D$17 -> 0.014372933 | F13: ='Data Sheet'!E26/'Data Sheet'!E$17 -> 0.025186638 | G13: ='Data Sheet'!F26/'Data Sheet'!F$17 -> 0.022837459 | H13: ='Data Sheet'!G26/'Data Sheet'!G$17 -> 0.020802349 | I13: ='Data Sheet'!H26/'Data Sheet'!H$17 -> 0.01876857 | J13: ='Data Sheet'!I26/'Data Sheet'!I$17 -> 0.019645858 | ... L13: ='Data Sheet'!K26/'Data Sheet'!K$17 -> 0.020676925
B14: Interest | C14: ='Data Sheet'!B27/'Data Sheet'!B$17 -> 0.0010554249 | D14: ='Data Sheet'!C27/'Data Sheet'!C$17 -> 0.00073146715 | E14: ='Data Sheet'!D27/'Data Sheet'!D$17 -> 0.00083948105 | F14: ='Data Sheet'!E27/'Data Sheet'!E$17 -> 0.002966091 | G14: ='Data Sheet'!F27/'Data Sheet'!F$17 -> 0.0024878796 | H14: ='Data Sheet'!G27/'Data Sheet'!G$17 -> 0.0020211265 | I14: ='Data Sheet'!H27/'Data Sheet'!H$17 -> 0.0018818092 | J14: ='Data Sheet'!I27/'Data Sheet'!I$17 -> 0.0053961484 | ... L14: ='Data Sheet'!K27/'Data Sheet'!K$17 -> 0.0063597444
B15: Profit before tax | C15: ='Data Sheet'!B28/'Data Sheet'!B$17 -> 0.19501236 | D15: ='Data Sheet'!C28/'Data Sheet'!C$17 -> 0.20554227 | E15: ='Data Sheet'!D28/'Data Sheet'!D$17 -> 0.2188756 | F15: ='Data Sheet'!E28/'Data Sheet'!E$17 -> 0.23037478 | G15: ='Data Sheet'!F28/'Data Sheet'!F$17 -> 0.22550396 | H15: ='Data Sheet'!G28/'Data Sheet'!G$17 -> 0.22649964 | I15: ='Data Sheet'!H28/'Data Sheet'!H$17 -> 0.22027072 | J15: ='Data Sheet'!I28/'Data Sheet'!I$17 -> 0.22499031 | ... L15: ='Data Sheet'!K28/'Data Sheet'!K$17 -> 0.28260532
... B18: Dividend Amount | C18: ='Data Sheet'!B31/'Data Sheet'!B$17 -> 0.11072915 | D18: ='Data Sheet'!C31/'Data Sheet'!C$17 -> 0.12153608 | E18: ='Data Sheet'!D31/'Data Sheet'!D$17 -> 0.12088527 | F18: ='Data Sheet'!E31/'Data Sheet'!E$17 -> 0.13573637 | G18: ='Data Sheet'!F31/'Data Sheet'!F$17 -> 0.20237943 | H18: ='Data Sheet'!G31/'Data Sheet'!G$17 -> 0.15234718 | I18: ='Data Sheet'!H31/'Data Sheet'!H$17 -> 0.15128755 | J18: ='Data Sheet'!I31/'Data Sheet'!I$17 -> 0.15946103 | ... L18: ='Data Sheet'!K31/'Data Sheet'!K$17 -> 0.14945399
B19: EBITDA | C19: =SUM('Data Sheet'!B26:B28)/'Data Sheet'!B$17 -> 0.20909475 | D19: =SUM('Data Sheet'!C26:C28)/'Data Sheet'!C$17 -> 0.22090308 | E19: =SUM('Data Sheet'!D26:D28)/'Data Sheet'!D$17 -> 0.23408802 | F19: =SUM('Data Sheet'!E26:E28)/'Data Sheet'!E$17 -> 0.25852751 | G19: =SUM('Data Sheet'!F26:F28)/'Data Sheet'!F$17 -> 0.25082929 | H19: =SUM('Data Sheet'!G26:G28)/'Data Sheet'!G$17 -> 0.24932311 | I19: =SUM('Data Sheet'!H26:H28)/'Data Sheet'!H$17 -> 0.2409211 | J19: =SUM('Data Sheet'!I26:I28)/'Data Sheet'!I$17 -> 0.25003231 | ... L19: =SUM('Data Sheet'!K26:K28)/'Data Sheet'!K$17 -> 0.30964199
B21: 2. COMMON SIZE STATEMENT — BALANCE SHEET (Base = Total Assets / Total Liabilities = 100%)
B22: Equity & Liabilities
B23: Particulars | C23: FY17 | D23: FY18 | E23: FY19 | F23: FY20 | G23: FY21 | H23: FY22 | I23: FY23 | J23: FY24 | K23: FY25 | L23: FY26
B24: Equity Share Capital | C24: ='Data Sheet'!B57/'Data Sheet'!B$61 -> 0.013752706 | D24: ='Data Sheet'!C57/'Data Sheet'!C$61 -> 0.012092711 | E24: ='Data Sheet'!D57/'Data Sheet'!D$61 -> 0.011594825 | F24: ='Data Sheet'!E57/'Data Sheet'!E$61 -> 0.010718007 | G24: ='Data Sheet'!F57/'Data Sheet'!F$61 -> 0.0034186791 | H24: ='Data Sheet'!G57/'Data Sheet'!G$61 -> 0.0033330497 | I24: ='Data Sheet'!H57/'Data Sheet'!H$61 -> 0.0032157861 | J24: ='Data Sheet'!I57/'Data Sheet'!I$61 -> 0.0029940501 | ... L24: ='Data Sheet'!K57/'Data Sheet'!K$61 -> 0.0029471519
B25: Reserves & Surplus | C25: ='Data Sheet'!B58/'Data Sheet'!B$61 -> 0.41563734 | D25: ='Data Sheet'!C58/'Data Sheet'!C$61 -> 0.39553242 | E25: ='Data Sheet'!D58/'Data Sheet'!D$61 -> 0.41070374 | F25: ='Data Sheet'!E58/'Data Sheet'!E$61 -> 0.3976083 | G25: ='Data Sheet'!F58/'Data Sheet'!F$61 -> 0.6901222 | H25: ='Data Sheet'!G58/'Data Sheet'!G$61 -> 0.69250844 | I25: ='Data Sheet'!H58/'Data Sheet'!H$61 -> 0.68515402 | J25: ='Data Sheet'!I58/'Data Sheet'!I$61 -> 0.64955599 | ... L25: ='Data Sheet'!K58/'Data Sheet'!K$61 -> 0.60829216
B26: Borrowings | C26: ='Data Sheet'!B59/'Data Sheet'!B$61 -> 0.017636572 | D26: ='Data Sheet'!C59/'Data Sheet'!C$61 -> 0 | E26: ='Data Sheet'!D59/'Data Sheet'!D$61 -> 0.0053142949 | F26: ='Data Sheet'!E59/'Data Sheet'!E$61 -> 0 | G26: ='Data Sheet'!F59/'Data Sheet'!F$61 -> 0 | H26: ='Data Sheet'!G59/'Data Sheet'!G$61 -> 0.014793067 | I26: ='Data Sheet'!H59/'Data Sheet'!H$61 -> 0.016681035 | J26: ='Data Sheet'!I59/'Data Sheet'!I$61 -> 0.018907108 | ... L26: ='Data Sheet'!K59/'Data Sheet'!K$61 -> 0.018535704
B27: Other Liabilities | C27: ='Data Sheet'!B60/'Data Sheet'!B$61 -> 0.55297339 | D27: ='Data Sheet'!C60/'Data Sheet'!C$61 -> 0.59237487 | E27: ='Data Sheet'!D60/'Data Sheet'!D$61 -> 0.57238714 | F27: ='Data Sheet'!E60/'Data Sheet'!E$61 -> 0.5916737 | G27: ='Data Sheet'!F60/'Data Sheet'!F$61 -> 0.30645912 | H27: ='Data Sheet'!G60/'Data Sheet'!G$61 -> 0.28936544 | I27: ='Data Sheet'!H60/'Data Sheet'!H$61 -> 0.29494916 | J27: ='Data Sheet'!I60/'Data Sheet'!I$61 -> 0.32854285 | ... L27: ='Data Sheet'!K60/'Data Sheet'!K$61 -> 0.37022499
B28: Total Equity & Liabilities | C28: ='Data Sheet'!B61/'Data Sheet'!B$61 -> 1 | D28: ='Data Sheet'!C61/'Data Sheet'!C$61 -> 1 | E28: ='Data Sheet'!D61/'Data Sheet'!D$61 -> 1 | F28: ='Data Sheet'!E61/'Data Sheet'!E$61 -> 1 | G28: ='Data Sheet'!F61/'Data Sheet'!F$61 -> 1 | H28: ='Data Sheet'!G61/'Data Sheet'!G$61 -> 1 | I28: ='Data Sheet'!H61/'Data Sheet'!H$61 -> 1 | J28: ='Data Sheet'!I61/'Data Sheet'!I$61 -> 1 | ... L28: ='Data Sheet'!K61/'Data Sheet'!K$61 -> 1
B30: Assets
B31: Particulars | C31: FY17 | D31: FY18 | E31: FY19 | F31: FY20 | G31: FY21 | H31: FY22 | I31: FY23 | J31: FY24 | K31: FY25 | L31: FY26
B32: Net Block | C32: ='Data Sheet'!B62/'Data Sheet'!B$66 -> 0.28135744 | D32: ='Data Sheet'!C62/'Data Sheet'!C$66 -> 0.25349905 | E32: ='Data Sheet'!D62/'Data Sheet'!D$66 -> 0.25310001 | F32: ='Data Sheet'!E62/'Data Sheet'!E$66 -> 0.27187019 | G32: ='Data Sheet'!F62/'Data Sheet'!F$66 -> 0.74837067 | H32: ='Data Sheet'!G62/'Data Sheet'!G$66 -> 0.73005134 | I32: ='Data Sheet'!H62/'Data Sheet'!H$66 -> 0.72085608 | J32: ='Data Sheet'!I62/'Data Sheet'!I$66 -> 0.68473289 | ... L32: ='Data Sheet'!K62/'Data Sheet'!K$66 -> 0.72020868
B33: Capital Work-in-Progress | C33: ='Data Sheet'!B63/'Data Sheet'!B$66 -> 0.014580415 | D33: ='Data Sheet'!C63/'Data Sheet'!C$66 -> 0.02580898 | E33: ='Data Sheet'!D63/'Data Sheet'!D$66 -> 0.021793977 | F33: ='Data Sheet'!E63/'Data Sheet'!E$66 -> 0.029623381 | G33: ='Data Sheet'!F63/'Data Sheet'!F$66 -> 0.01083794 | H33: ='Data Sheet'!G63/'Data Sheet'!G$66 -> 0.018622529 | I33: ='Data Sheet'!H63/'Data Sheet'!H$66 -> 0.01549051 | J33: ='Data Sheet'!I63/'Data Sheet'!I$66 -> 0.013059155 | ... L33: ='Data Sheet'!K63/'Data Sheet'!K$66 -> 0.011036143
B34: Investments | C34: ='Data Sheet'!B64/'Data Sheet'!B$66 -> 0.24156373 | D34: ='Data Sheet'!C64/'Data Sheet'!C$66 -> 0.16084425 | E34: ='Data Sheet'!D64/'Data Sheet'!D$66 -> 0.14579419 | F34: ='Data Sheet'!E64/'Data Sheet'!E$66 -> 0.062273607 | G34: ='Data Sheet'!F64/'Data Sheet'!F$66 -> 0.039409369 | H34: ='Data Sheet'!G64/'Data Sheet'!G$66 -> 0.049939012 | I34: ='Data Sheet'!H64/'Data Sheet'!H$66 -> 0.039437853 | J34: ='Data Sheet'!I64/'Data Sheet'!I$66 -> 0.058925455 | ... L34: ='Data Sheet'!K64/'Data Sheet'!K$66 -> 0.054666533
B35: Other Assets | C35: ='Data Sheet'!B65/'Data Sheet'!B$66 -> 0.46249841 | D35: ='Data Sheet'!C65/'Data Sheet'!C$66 -> 0.55984772 | E35: ='Data Sheet'!D65/'Data Sheet'!D$66 -> 0.57931183 | F35: ='Data Sheet'!E65/'Data Sheet'!E$66 -> 0.63623282 | G35: ='Data Sheet'!F65/'Data Sheet'!F$66 -> 0.20138202 | H35: ='Data Sheet'!G65/'Data Sheet'!G$66 -> 0.20138712 | I35: ='Data Sheet'!H65/'Data Sheet'!H$66 -> 0.22421555 | J35: ='Data Sheet'!I65/'Data Sheet'!I$66 -> 0.2432825 | ... L35: ='Data Sheet'!K65/'Data Sheet'!K$66 -> 0.21408864
B36: Total Assets | C36: 1 | D36: 1 | E36: 1 | F36: 1 | G36: 1 | H36: 1 | I36: 1 | J36: 1 | K36: 1 | L36: 1

Sheet Comparative Statement
B2: 1. COMPARATIVE STATEMENT — PROFIT & LOSS ACCOUNT
B3: Absolute Figures (₹ Crore)
B4: Particulars | C4: FY18 vs FY17 | D4: FY19 vs FY18 | E4: FY20 vs FY19 | F4: FY21 vs FY20 | G4: FY22 vs FY21 | H4: FY23 vs FY22 | I4: FY24 vs FY23 | J4: FY25 vs FY24 | K4: FY26 vs FY25
B5: Sales | C5: ='Data Sheet'!C17-'Data Sheet'!B17 -> 2383 | D5: ='Data Sheet'!D17-'Data Sheet'!C17 -> 3765 | E5: ='Data Sheet'!E17-'Data Sheet'!D17 -> 473 | F5: ='Data Sheet'!F17-'Data Sheet'!E17 -> 7245 | G5: ='Data Sheet'!G17-'Data Sheet'!F17 -> 5418 | H5: ='Data Sheet'!H17-'Data Sheet'!G17 -> 8134 | I5: ='Data Sheet'!I17-'Data Sheet'!H17 -> 1316 | J5: ='Data Sheet'!J17-'Data Sheet'!I17 -> -568 | K5: ='Data Sheet'!K17-'Data Sheet'!J17 -> 3140
B6: Raw Material Cost | C6: ='Data Sheet'!C18-'Data Sheet'!B18 -> 627 | D6: ='Data Sheet'!D18-'Data Sheet'!C18 -> 1612 | E6: ='Data Sheet'!E18-'Data Sheet'!D18 -> -148 | F6: ='Data Sheet'!F18-'Data Sheet'!E18 -> 4444 | G6: ='Data Sheet'!G18-'Data Sheet'!F18 -> 2730 | H6: ='Data Sheet'!H18-'Data Sheet'!G18 -> 5556 | I6: ='Data Sheet'!I18-'Data Sheet'!H18 -> -1605 | J6: ='Data Sheet'!J18-'Data Sheet'!I18 -> -220 | K6: ='Data Sheet'!K18-'Data Sheet'!J18 -> 2556
B7: Change in Inventory | C7: ='Data Sheet'!C19-'Data Sheet'!B19 -> 216 | D7: ='Data Sheet'!D19-'Data Sheet'!C19 -> -84 | E7: ='Data Sheet'!E19-'Data Sheet'!D19 -> 120 | F7: ='Data Sheet'!F19-'Data Sheet'!E19 -> 297 | G7: ='Data Sheet'!G19-'Data Sheet'!F19 -> -383 | H7: ='Data Sheet'!H19-'Data Sheet'!G19 -> 53 | I7: ='Data Sheet'!I19-'Data Sheet'!H19 -> -64 | J7: ='Data Sheet'!J19-'Data Sheet'!I19 -> 114 | K7: ='Data Sheet'!K19-'Data Sheet'!J19 -> 304
B8: Power and Fuel | C8: ='Data Sheet'!C20-'Data Sheet'!B20 -> 0 | D8: ='Data Sheet'!D20-'Data Sheet'!C20 -> 13 | E8: ='Data Sheet'!E20-'Data Sheet'!D20 -> -9 | F8: ='Data Sheet'!F20-'Data Sheet'!E20 -> 40 | G8: ='Data Sheet'!G20-'Data Sheet'!F20 -> -21 | H8: ='Data Sheet'!H20-'Data Sheet'!G20 -> 66 | I8: ='Data Sheet'!I20-'Data Sheet'!H20 -> 62 | J8: ='Data Sheet'!J20-'Data Sheet'!I20 -> -43 | K8: ='Data Sheet'!K20-'Data Sheet'!J20 -> 23
B9: Other Mfr. Exp | C9: ='Data Sheet'!C21-'Data Sheet'!B21 -> 111 | D9: ='Data Sheet'!D21-'Data Sheet'!C21 -> 43 | E9: ='Data Sheet'!E21-'Data Sheet'!D21 -> -135 | F9: ='Data Sheet'!F21-'Data Sheet'!E21 -> -38 | G9: ='Data Sheet'!G21-'Data Sheet'!F21 -> 486 | H9: ='Data Sheet'!H21-'Data Sheet'!G21 -> 437 | I9: ='Data Sheet'!I21-'Data Sheet'!H21 -> -406 | J9: ='Data Sheet'!J21-'Data Sheet'!I21 -> 302 | K9: ='Data Sheet'!K21-'Data Sheet'!J21 -> -383
B10: Employee Cost | C10: ='Data Sheet'!C22-'Data Sheet'!B22 -> 117 | D10: ='Data Sheet'!D22-'Data Sheet'!C22 -> 15 | E10: ='Data Sheet'!E22-'Data Sheet'!D22 -> -55 | F10: ='Data Sheet'!F22-'Data Sheet'!E22 -> 538 | G10: ='Data Sheet'!G22-'Data Sheet'!F22 -> 187 | H10: ='Data Sheet'!H22-'Data Sheet'!G22 -> 309 | I10: ='Data Sheet'!I22-'Data Sheet'!H22 -> 155 | J10: ='Data Sheet'!J22-'Data Sheet'!I22 -> -57 | K10: ='Data Sheet'!K22-'Data Sheet'!J22 -> 223
B11: Selling and admin | C11: ='Data Sheet'!C23-'Data Sheet'!B23 -> 563 | D11: ='Data Sheet'!D23-'Data Sheet'!C23 -> 544 | E11: ='Data Sheet'!E23-'Data Sheet'!D23 -> -176 | F11: ='Data Sheet'!F23-'Data Sheet'!E23 -> 286 | G11: ='Data Sheet'!G23-'Data Sheet'!F23 -> 258 | H11: ='Data Sheet'!H23-'Data Sheet'!G23 -> 621 | I11: ='Data Sheet'!I23-'Data Sheet'!H23 -> 1995 | J11: ='Data Sheet'!J23-'Data Sheet'!I23 -> -635 | K11: ='Data Sheet'!K23-'Data Sheet'!J23 -> 599
B12: Other Expenses | C12: ='Data Sheet'!C24-'Data Sheet'!B24 -> 10 | D12: ='Data Sheet'!D24-'Data Sheet'!C24 -> 73 | E12: ='Data Sheet'!E24-'Data Sheet'!D24 -> 135 | F12: ='Data Sheet'!F24-'Data Sheet'!E24 -> 507 | G12: ='Data Sheet'!G24-'Data Sheet'!F24 -> 164 | H12: ='Data Sheet'!H24-'Data Sheet'!G24 -> -92 | I12: ='Data Sheet'!I24-'Data Sheet'!H24 -> 539 | J12: ='Data Sheet'!J24-'Data Sheet'!I24 -> 160 | K12: ='Data Sheet'!K24-'Data Sheet'!J24 -> 85
B13: Other Income | C13: ='Data Sheet'!C25-'Data Sheet'!B25 -> -253 | D13: ='Data Sheet'!D25-'Data Sheet'!C25 -> -31 | E13: ='Data Sheet'!E25-'Data Sheet'!D25 -> 102 | F13: ='Data Sheet'!F25-'Data Sheet'!E25 -> -254 | G13: ='Data Sheet'!G25-'Data Sheet'!F25 -> 49 | H13: ='Data Sheet'!H25-'Data Sheet'!G25 -> 229 | I13: ='Data Sheet'!I25-'Data Sheet'!H25 -> 369 | J13: ='Data Sheet'!J25-'Data Sheet'!I25 -> 538 | K13: ='Data Sheet'!K25-'Data Sheet'!J25 -> 3568
B14: Depreciation | C14: ='Data Sheet'!C26-'Data Sheet'!B26 -> 88 | D14: ='Data Sheet'!D26-'Data Sheet'!C26 -> 45 | E14: ='Data Sheet'!E26-'Data Sheet'!D26 -> 437 | F14: ='Data Sheet'!F26-'Data Sheet'!E26 -> 72 | G14: ='Data Sheet'!G26-'Data Sheet'!F26 -> 17 | H14: ='Data Sheet'!H26-'Data Sheet'!G26 -> 46 | I14: ='Data Sheet'!I26-'Data Sheet'!H26 -> 79 | J14: ='Data Sheet'!J26-'Data Sheet'!I26 -> 37 | K14: ='Data Sheet'!K26-'Data Sheet'!J26 -> 80
B15: Interest | C15: ='Data Sheet'!C27-'Data Sheet'!B27 -> -9 | D15: ='Data Sheet'!D27-'Data Sheet'!C27 -> 7 | E15: ='Data Sheet'!E27-'Data Sheet'!D27 -> 85 | F15: ='Data Sheet'!F27-'Data Sheet'!E27 -> -1 | G15: ='Data Sheet'!G27-'Data Sheet'!F27 -> -11 | H15: ='Data Sheet'!H27-'Data Sheet'!G27 -> 8 | I15: ='Data Sheet'!I27-'Data Sheet'!H27 -> 220 | J15: ='Data Sheet'!J27-'Data Sheet'!I27 -> 47 | K15: ='Data Sheet'!K27-'Data Sheet'!J27 -> 29
B16: Profit before tax | C16: ='Data Sheet'!C28-'Data Sheet'!B28 -> 839 | D16: ='Data Sheet'!D28-'Data Sheet'!C28 -> 1298 | E16: ='Data Sheet'!E28-'Data Sheet'!D28 -> 561 | F16: ='Data Sheet'!F28-'Data Sheet'!E28 -> 1440 | G16: ='Data Sheet'!G28-'Data Sheet'!F28 -> 1274 | H16: ='Data Sheet'!H28-'Data Sheet'!G28 -> 1465 | I16: ='Data Sheet'!I28-'Data Sheet'!H28 -> 582 | J16: ='Data Sheet'!J28-'Data Sheet'!I28 -> 493 | K16: ='Data Sheet'!K28-'Data Sheet'!J28 -> 3800
... B19: Dividend Amount | C19: ='Data Sheet'!C31-'Data Sheet'!B31 -> 648 | D19: ='Data Sheet'!D31-'Data Sheet'!C31 -> 432 | E19: ='Data Sheet'!E31-'Data Sheet'!D31 -> 648 | F19: ='Data Sheet'!F31-'Data Sheet'!E31 -> 4117.5 | G19: ='Data Sheet'!G31-'Data Sheet'!F31 -> -1527.5 | H19: ='Data Sheet'!H31-'Data Sheet'!G31 -> 1175 | I19: ='Data Sheet'!I31-'Data Sheet'!H31 -> 705 | J19: ='Data Sheet'!J31-'Data Sheet'!I31 -> 2585 | K19: ='Data Sheet'!K31-'Data Sheet'!J31 -> -2820
B21: Increase / (Decrease) over Previous Year (%)
B22: Particulars | C22: FY18 vs FY17 | D22: FY19 vs FY18 | E22: FY20 vs FY19 | F22: FY21 vs FY20 | G22: FY22 vs FY21 | H22: FY23 vs FY22 | I22: FY24 vs FY23 | J22: FY25 vs FY24 | K22: FY26 vs FY25
B23: Sales | C23: ='Data Sheet'!C17/'Data Sheet'!B17-1 -> 0.071859357 | D23: ='Data Sheet'!D17/'Data Sheet'!C17-1 -> 0.10592207 | E23: ='Data Sheet'!E17/'Data Sheet'!D17-1 -> 0.012032562 | F23: ='Data Sheet'!F17/'Data Sheet'!E17-1 -> 0.18211296 | G23: ='Data Sheet'!G17/'Data Sheet'!F17-1 -> 0.11520796 | H23: ='Data Sheet'!H17/'Data Sheet'!G17-1 -> 0.15509286 | I23: ='Data Sheet'!I17/'Data Sheet'!H17-1 -> 0.021723341 | J23: ='Data Sheet'!J17/'Data Sheet'!I17-1 -> -0.0091766835 | K23: ='Data Sheet'!K17/'Data Sheet'!J17-1 -> 0.051200104
B24: Raw Material Cost | C24: ='Data Sheet'!C18/'Data Sheet'!B18-1 -> 0.046082611 | D24: ='Data Sheet'!D18/'Data Sheet'!C18-1 -> 0.11325792 | E24: ='Data Sheet'!E18/'Data Sheet'!D18-1 -> -0.009340486 | F24: ='Data Sheet'!F18/'Data Sheet'!E18-1 -> 0.28311142 | G24: ='Data Sheet'!G18/'Data Sheet'!F18-1 -> 0.13554441 | H24: ='Data Sheet'!H18/'Data Sheet'!G18-1 -> 0.24292773 | I24: ='Data Sheet'!I18/'Data Sheet'!H18-1 -> -0.056460407 | J24: ='Data Sheet'!J18/'Data Sheet'!I18-1 -> -0.0082022221 | K24: ='Data Sheet'!K18/'Data Sheet'!J18-1 -> 0.096083001
B25: Change in Inventory | C25: ='Data Sheet'!C19/'Data Sheet'!B19-1 -> -1.5 | D25: ='Data Sheet'!D19/'Data Sheet'!C19-1 -> -1.1666667 | E25: ='Data Sheet'!E19/'Data Sheet'!D19-1 -> -10 | F25: ='Data Sheet'!F19/'Data Sheet'!E19-1 -> 2.75 | G25: ='Data Sheet'!G19/'Data Sheet'!F19-1 -> -0.94567901 | H25: ='Data Sheet'!H19/'Data Sheet'!G19-1 -> 2.4090909 | I25: ='Data Sheet'!I19/'Data Sheet'!H19-1 -> -0.85333333 | J25: ='Data Sheet'!J19/'Data Sheet'!I19-1 -> 10.363636 | K25: ='Data Sheet'!K19/'Data Sheet'!J19-1 -> 2.432
B26: Power and Fuel | C26: ='Data Sheet'!C20/'Data Sheet'!B20-1 -> 0 | D26: ='Data Sheet'!D20/'Data Sheet'!C20-1 -> 0.044067797 | E26: ='Data Sheet'!E20/'Data Sheet'!D20-1 -> -0.029220779 | F26: ='Data Sheet'!F20/'Data Sheet'!E20-1 -> 0.13377926 | G26: ='Data Sheet'!G20/'Data Sheet'!F20-1 -> -0.061946903 | H26: ='Data Sheet'!H20/'Data Sheet'!G20-1 -> 0.20754717 | I26: ='Data Sheet'!I20/'Data Sheet'!H20-1 -> 0.16145833 | J26: ='Data Sheet'!J20/'Data Sheet'!I20-1 -> -0.096412556 | K26: ='Data Sheet'!K20/'Data Sheet'!J20-1 -> 0.05707196
B27: Other Mfr. Exp | C27: ='Data Sheet'!C21/'Data Sheet'!B21-1 -> 0.038448216 | D27: ='Data Sheet'!D21/'Data Sheet'!C21-1 -> 0.014342895 | E27: ='Data Sheet'!E21/'Data Sheet'!D21-1 -> -0.044393292 | F27: ='Data Sheet'!F21/'Data Sheet'!E21-1 -> -0.013076394 | G27: ='Data Sheet'!G21/'Data Sheet'!F21-1 -> 0.16945607 | H27: ='Data Sheet'!H21/'Data Sheet'!G21-1 -> 0.13029219 | I27: ='Data Sheet'!I21/'Data Sheet'!H21-1 -> -0.10709575 | J27: ='Data Sheet'!J21/'Data Sheet'!I21-1 -> 0.089217134 | K27: ='Data Sheet'!K21/'Data Sheet'!J21-1 -> -0.10387849
B28: Employee Cost | C28: ='Data Sheet'!C22/'Data Sheet'!B22-1 -> 0.067125645 | D28: ='Data Sheet'!D22/'Data Sheet'!C22-1 -> 0.0080645161 | E28: ='Data Sheet'!E22/'Data Sheet'!D22-1 -> -0.029333333 | F28: ='Data Sheet'!F22/'Data Sheet'!E22-1 -> 0.2956044 | G28: ='Data Sheet'!G22/'Data Sheet'!F22-1 -> 0.079304495 | H28: ='Data Sheet'!H22/'Data Sheet'!G22-1 -> 0.12141454 | I28: ='Data Sheet'!I22/'Data Sheet'!H22-1 -> 0.054309741 | J28: ='Data Sheet'!J22/'Data Sheet'!I22-1 -> -0.01894317 | K28: ='Data Sheet'!K22/'Data Sheet'!J22-1 -> 0.075542005
B29: Selling and admin | C29: ='Data Sheet'!C23/'Data Sheet'!B23-1 -> 0.084168037 | D29: ='Data Sheet'!D23/'Data Sheet'!C23-1 -> 0.075013789 | E29: ='Data Sheet'!E23/'Data Sheet'!D23-1 -> -0.02257568 | F29: ='Data Sheet'!F23/'Data Sheet'!E23-1 -> 0.037532808 | G29: ='Data Sheet'!G23/'Data Sheet'!F23-1 -> 0.032633443 | H29: ='Data Sheet'!H23/'Data Sheet'!G23-1 -> 0.076065654 | I29: ='Data Sheet'!I23/'Data Sheet'!H23-1 -> 0.22709163 | J29: ='Data Sheet'!J23/'Data Sheet'!I23-1 -> -0.05890538 | K29: ='Data Sheet'!K23/'Data Sheet'!J23-1 -> 0.059043864
B30: Other Expenses | C30: ='Data Sheet'!C24/'Data Sheet'!B24-1 -> 0.0068027211 | D30: ='Data Sheet'!D24/'Data Sheet'!C24-1 -> 0.049324324 | E30: ='Data Sheet'!E24/'Data Sheet'!D24-1 -> 0.086928525 | F30: ='Data Sheet'!F24/'Data Sheet'!E24-1 -> 0.30035545 | G30: ='Data Sheet'!G24/'Data Sheet'!F24-1 -> 0.074715262 | H30: ='Data Sheet'!H24/'Data Sheet'!G24-1 -> -0.038999576 | I30: ='Data Sheet'!I24/'Data Sheet'!H24-1 -> 0.23775915 | J30: ='Data Sheet'!J24/'Data Sheet'!I24-1 -> 0.05702067 | K30: ='Data Sheet'!K24/'Data Sheet'!J24-1 -> 0.028658125
B31: Other Income | C31: ='Data Sheet'!C25/'Data Sheet'!B25-1 -> -0.41749175 | D31: ='Data Sheet'!D25/'Data Sheet'!C25-1 -> -0.087818697 | E31: ='Data Sheet'!E25/'Data Sheet'!D25-1 -> 0.31677019 | F31: ='Data Sheet'!F25/'Data Sheet'!E25-1 -> -0.5990566 | G31: ='Data Sheet'!G25/'Data Sheet'!F25-1 -> 0.28823529 | H31: ='Data Sheet'!H25/'Data Sheet'!G25-1 -> 1.0456621 | I31: ='Data Sheet'!I25/'Data Sheet'!H25-1 -> 0.82366071 | J31: ='Data Sheet'!J25/'Data Sheet'!I25-1 -> 0.65850673 | K31: ='Data Sheet'!K25/'Data Sheet'!J25-1 -> 2.6332103
B32: Depreciation | C32: ='Data Sheet'!C26/'Data Sheet'!B26-1 -> 0.2037037 | D32: ='Data Sheet'!D26/'Data Sheet'!C26-1 -> 0.086538462 | E32: ='Data Sheet'!E26/'Data Sheet'!D26-1 -> 0.77345133 | F32: ='Data Sheet'!F26/'Data Sheet'!E26-1 -> 0.071856287 | G32: ='Data Sheet'!G26/'Data Sheet'!F26-1 -> 0.015828678 | H32: ='Data Sheet'!H26/'Data Sheet'!G26-1 -> 0.042163153 | I32: ='Data Sheet'!I26/'Data Sheet'!H26-1 -> 0.069481091 | J32: ='Data Sheet'!J26/'Data Sheet'!I26-1 -> 0.030427632 | K32: ='Data Sheet'!K26/'Data Sheet'!J26-1 -> 0.063846768
B33: Interest | C33: ='Data Sheet'!C27/'Data Sheet'!B27-1 -> -0.25714286 | D33: ='Data Sheet'!D27/'Data Sheet'!C27-1 -> 0.26923077 | E33: ='Data Sheet'!E27/'Data Sheet'!D27-1 -> 2.5757576 | F33: ='Data Sheet'!F27/'Data Sheet'!E27-1 -> -0.0084745763 | G33: ='Data Sheet'!G27/'Data Sheet'!F27-1 -> -0.094017094 | H33: ='Data Sheet'!H27/'Data Sheet'!G27-1 -> 0.075471698 | I33: ='Data Sheet'!I27/'Data Sheet'!H27-1 -> 1.9298246 | J33: ='Data Sheet'!J27/'Data Sheet'!I27-1 -> 0.14071856 | K33: ='Data Sheet'!K27/'Data Sheet'!J27-1 -> 0.076115486
B34: Profit before tax | C34: ='Data Sheet'!C28/'Data Sheet'!B28-1 -> 0.12973558 | D34: ='Data Sheet'!D28/'Data Sheet'!C28-1 -> 0.1776622 | E34: ='Data Sheet'!E28/'Data Sheet'!D28-1 -> 0.065202232 | F34: ='Data Sheet'!F28/'Data Sheet'!E28-1 -> 0.15711948 | G34: ='Data Sheet'!G28/'Data Sheet'!F28-1 -> 0.12013201 | H34: ='Data Sheet'!H28/'Data Sheet'!G28-1 -> 0.12332688 | I34: ='Data Sheet'!I28/'Data Sheet'!H28-1 -> 0.043615108 | J34: ='Data Sheet'!J28/'Data Sheet'!I28-1 -> 0.035401407 | K34: ='Data Sheet'!K28/'Data Sheet'!J28-1 -> 0.26354116
... B37: Dividend Amount | C37: ='Data Sheet'!C31/'Data Sheet'!B31-1 -> 0.17647059 | D37: ='Data Sheet'!D31/'Data Sheet'!C31-1 -> 0.1 | E37: ='Data Sheet'!E31/'Data Sheet'!D31-1 -> 0.13636364 | F37: ='Data Sheet'!F31/'Data Sheet'!E31-1 -> 0.7625 | G37: ='Data Sheet'!G31/'Data Sheet'!F31-1 -> -0.16049383 | H37: ='Data Sheet'!H31/'Data Sheet'!G31-1 -> 0.14705882 | I37: ='Data Sheet'!I31/'Data Sheet'!H31-1 -> 0.076923077 | J37: ='Data Sheet'!J31/'Data Sheet'!I31-1 -> 0.26190476 | K37: ='Data Sheet'!K31/'Data Sheet'!J31-1 -> -0.22641509
B39: 2. COMPARATIVE STATEMENT — BALANCE SHEET
B40: Increase / (Decrease) over Previous Year (₹ Crore)
B41: Particulars | C41: FY18 vs FY17 | D41: FY19 vs FY18 | E41: FY20 vs FY19 | F41: FY21 vs FY20 | G41: FY22 vs FY21 | H41: FY23 vs FY22 | I41: FY24 vs FY23 | J41: FY25 vs FY24 | K41: FY26 vs FY25
B42: Equity Share Capital | C42: ='Data Sheet'!C57-'Data Sheet'!B57 -> 0 | D42: ='Data Sheet'!D57-'Data Sheet'!C57 -> 0 | E42: ='Data Sheet'!E57-'Data Sheet'!D57 -> 0 | F42: ='Data Sheet'!F57-'Data Sheet'!E57 -> 19 | G42: ='Data Sheet'!G57-'Data Sheet'!F57 -> 0 | H42: ='Data Sheet'!H57-'Data Sheet'!G57 -> 0 | I42: ='Data Sheet'!I57-'Data Sheet'!H57 -> 0 | J42: ='Data Sheet'!J57-'Data Sheet'!I57 -> 0 | K42: ='Data Sheet'!K57-'Data Sheet'!J57 -> 0
B43: Reserves & Surplus | C43: ='Data Sheet'!C58-'Data Sheet'!B58 -> 537 | D43: ='Data Sheet'!D58-'Data Sheet'!C58 -> 586 | E43: ='Data Sheet'!E58-'Data Sheet'!D58 -> 362 | F43: ='Data Sheet'!F58-'Data Sheet'!E58 -> 39426 | G43: ='Data Sheet'!G58-'Data Sheet'!F58 -> 1387 | H43: ='Data Sheet'!H58-'Data Sheet'!G58 -> 1243 | I43: ='Data Sheet'!I58-'Data Sheet'!H58 -> 914 | J43: ='Data Sheet'!J58-'Data Sheet'!I58 -> -1816 | K43: ='Data Sheet'!K58-'Data Sheet'!J58 -> -663
B44: Borrowings | C44: ='Data Sheet'!C59-'Data Sheet'!B59 -> -277 | D44: ='Data Sheet'!D59-'Data Sheet'!C59 -> 99 | E44: ='Data Sheet'!E59-'Data Sheet'!D59 -> -99 | F44: ='Data Sheet'!F59-'Data Sheet'!E59 -> 0 | G44: ='Data Sheet'!G59-'Data Sheet'!F59 -> 1043 | H44: ='Data Sheet'!H59-'Data Sheet'!G59 -> 176 | I44: ='Data Sheet'!I59-'Data Sheet'!H59 -> 265 | J44: ='Data Sheet'!J59-'Data Sheet'!I59 -> 164 | K44: ='Data Sheet'!K59-'Data Sheet'!J59 -> -170
B45: Other Liabilities | C45: ='Data Sheet'!C60-'Data Sheet'!B60 -> 1896 | D45: ='Data Sheet'!D60-'Data Sheet'!C60 -> 82 | E45: ='Data Sheet'!E60-'Data Sheet'!D60 -> 1261 | F45: ='Data Sheet'!F60-'Data Sheet'!E60 -> 9142 | G45: ='Data Sheet'!G60-'Data Sheet'!F60 -> -664 | H45: ='Data Sheet'!H60-'Data Sheet'!G60 -> 1152 | I45: ='Data Sheet'!I60-'Data Sheet'!H60 -> 4233 | J45: ='Data Sheet'!J60-'Data Sheet'!I60 -> 3026 | K45: ='Data Sheet'!K60-'Data Sheet'!J60 -> 708
B46: Total Equity & Liabilities | C46: ='Data Sheet'!C61-'Data Sheet'!B61 -> 2156 | D46: ='Data Sheet'!D61-'Data Sheet'!C61 -> 767 | E46: ='Data Sheet'!E61-'Data Sheet'!D61 -> 1524 | F46: ='Data Sheet'!F61-'Data Sheet'!E61 -> 48587 | G46: ='Data Sheet'!G61-'Data Sheet'!F61 -> 1766 | H46: ='Data Sheet'!H61-'Data Sheet'!G61 -> 2571 | I46: ='Data Sheet'!I61-'Data Sheet'!H61 -> 5412 | J46: ='Data Sheet'!J61-'Data Sheet'!I61 -> 1374 | K46: ='Data Sheet'!K61-'Data Sheet'!J61 -> -125
B47: Net Block | C47: ='Data Sheet'!C62-'Data Sheet'!B62 -> 109 | D47: ='Data Sheet'!D62-'Data Sheet'!C62 -> 187 | E47: ='Data Sheet'!E62-'Data Sheet'!D62 -> 764 | F47: ='Data Sheet'!F62-'Data Sheet'!E62 -> 45964 | G47: ='Data Sheet'!G62-'Data Sheet'!F62 -> 30 | H47: ='Data Sheet'!H62-'Data Sheet'!G62 -> 1205 | I47: ='Data Sheet'!I62-'Data Sheet'!H62 -> 1066 | J47: ='Data Sheet'!J62-'Data Sheet'!I62 -> 591 | K47: ='Data Sheet'!K62-'Data Sheet'!J62 -> 3093
B48: Capital Work-in-Progress | C48: ='Data Sheet'!C63-'Data Sheet'!B63 -> 232 | D48: ='Data Sheet'!D63-'Data Sheet'!C63 -> -55 | E48: ='Data Sheet'!E63-'Data Sheet'!D63 -> 191 | F48: ='Data Sheet'!F63-'Data Sheet'!E63 -> 148 | G48: ='Data Sheet'!G63-'Data Sheet'!F63 -> 568 | H48: ='Data Sheet'!H63-'Data Sheet'!G63 -> -181 | I48: ='Data Sheet'!I63-'Data Sheet'!H63 -> -107 | J48: ='Data Sheet'!J63-'Data Sheet'!I63 -> -16 | K48: ='Data Sheet'!K63-'Data Sheet'!J63 -> -129
B49: Investments | C49: ='Data Sheet'!C64-'Data Sheet'!B64 -> -921 | D49: ='Data Sheet'!D64-'Data Sheet'!C64 -> -157 | E49: ='Data Sheet'!E64-'Data Sheet'!D64 -> -1461 | F49: ='Data Sheet'!F64-'Data Sheet'!E64 -> 1454 | G49: ='Data Sheet'!G64-'Data Sheet'!F64 -> 812 | H49: ='Data Sheet'!H64-'Data Sheet'!G64 -> -639 | I49: ='Data Sheet'!I64-'Data Sheet'!H64 -> 1743 | J49: ='Data Sheet'!J64-'Data Sheet'!I64 -> -815 | K49: ='Data Sheet'!K64-'Data Sheet'!J64 -> 549
B50: Other Assets | C50: ='Data Sheet'!C65-'Data Sheet'!B65 -> 2736 | D50: ='Data Sheet'!D65-'Data Sheet'!C65 -> 792 | E50: ='Data Sheet'!E65-'Data Sheet'!D65 -> 2030 | F50: ='Data Sheet'!F65-'Data Sheet'!E65 -> 1021 | G50: ='Data Sheet'!G65-'Data Sheet'!F65 -> 356 | H50: ='Data Sheet'!H65-'Data Sheet'!G65 -> 2186 | I50: ='Data Sheet'!I65-'Data Sheet'!H65 -> 2710 | J50: ='Data Sheet'!J65-'Data Sheet'!I65 -> 1614 | K50: ='Data Sheet'!K65-'Data Sheet'!J65 -> -3638
B51: Total Assets | C51: ='Data Sheet'!C66-'Data Sheet'!B66 -> 2156 | D51: ='Data Sheet'!D66-'Data Sheet'!C66 -> 767 | E51: ='Data Sheet'!E66-'Data Sheet'!D66 -> 1524 | F51: ='Data Sheet'!F66-'Data Sheet'!E66 -> 48587 | G51: ='Data Sheet'!G66-'Data Sheet'!F66 -> 1766 | H51: ='Data Sheet'!H66-'Data Sheet'!G66 -> 2571 | I51: ='Data Sheet'!I66-'Data Sheet'!H66 -> 5412 | J51: ='Data Sheet'!J66-'Data Sheet'!I66 -> 1374 | K51: ='Data Sheet'!K66-'Data Sheet'!J66 -> -125
B53: Increase / (Decrease) over Previous Year (%)
B54: Particulars | C54: FY18 vs FY17 | D54: FY19 vs FY18 | E54: FY20 vs FY19 | F54: FY21 vs FY20 | G54: FY22 vs FY21 | H54: FY23 vs FY22 | I54: FY24 vs FY23 | J54: FY25 vs FY24 | K54: FY26 vs FY25
B55: Equity Share Capital | C55: ='Data Sheet'!C57/'Data Sheet'!B57-1 -> 0 | D55: ='Data Sheet'!D57/'Data Sheet'!C57-1 -> 0 | E55: ='Data Sheet'!E57/'Data Sheet'!D57-1 -> 0 | F55: ='Data Sheet'!F57/'Data Sheet'!E57-1 -> 0.087962963 | G55: ='Data Sheet'!G57/'Data Sheet'!F57-1 -> 0 | H55: ='Data Sheet'!H57/'Data Sheet'!G57-1 -> 0 | I55: ='Data Sheet'!I57/'Data Sheet'!H57-1 -> 0 | J55: ='Data Sheet'!J57/'Data Sheet'!I57-1 -> 0 | K55: ='Data Sheet'!K57/'Data Sheet'!J57-1 -> 0
B56: Reserves & Surplus | C56: ='Data Sheet'!C58/'Data Sheet'!B58-1 -> 0.082261029 | D56: ='Data Sheet'!D58/'Data Sheet'!C58-1 -> 0.082944091 | E56: ='Data Sheet'!E58/'Data Sheet'!D58-1 -> 0.047314077 | F56: ='Data Sheet'!F58/'Data Sheet'!E58-1 -> 4.9202546 | G56: ='Data Sheet'!G58/'Data Sheet'!F58-1 -> 0.029237547 | H56: ='Data Sheet'!H58/'Data Sheet'!G58-1 -> 0.025457748 | I56: ='Data Sheet'!I58/'Data Sheet'!H58-1 -> 0.018254808 | J56: ='Data Sheet'!J58/'Data Sheet'!I58-1 -> -0.035619716 | K56: ='Data Sheet'!K58/'Data Sheet'!J58-1 -> -0.013484654
B57: Borrowings | C57: ='Data Sheet'!C59/'Data Sheet'!B59-1 -> -1 | D57: =IFERROR('Data Sheet'!D59/'Data Sheet'!C59-1,0) -> 0 | E57: =IFERROR('Data Sheet'!E59/'Data Sheet'!D59-1,0) -> -1 | F57: =IFERROR('Data Sheet'!F59/'Data Sheet'!E59-1,0) -> 0 | G57: =IFERROR('Data Sheet'!G59/'Data Sheet'!F59-1,0) -> 0 | H57: ='Data Sheet'!H59/'Data Sheet'!G59-1 -> 0.16874401 | I57: ='Data Sheet'!I59/'Data Sheet'!H59-1 -> 0.2173913 | J57: ='Data Sheet'!J59/'Data Sheet'!I59-1 -> 0.11051213 | K57: ='Data Sheet'!K59/'Data Sheet'!J59-1 -> -0.10315534
B58: Other Liabilities | C58: ='Data Sheet'!C60/'Data Sheet'!B60-1 -> 0.21830743 | D58: ='Data Sheet'!D60/'Data Sheet'!C60-1 -> 0.0077497401 | E58: ='Data Sheet'!E60/'Data Sheet'!D60-1 -> 0.1182594 | F58: ='Data Sheet'!F60/'Data Sheet'!E60-1 -> 0.76668903 | G58: ='Data Sheet'!G60/'Data Sheet'!F60-1 -> -0.031519985 | H58: ='Data Sheet'!H60/'Data Sheet'!G60-1 -> 0.056465052 | I58: ='Data Sheet'!I60/'Data Sheet'!H60-1 -> 0.19639046 | J58: ='Data Sheet'!J60/'Data Sheet'!I60-1 -> 0.11734595 | K58: ='Data Sheet'!K60/'Data Sheet'!J60-1 -> 0.024572242
B59: Total Equity & Liabilities | C59: ='Data Sheet'!C61/'Data Sheet'!B61-1 -> 0.13727238 | D59: ='Data Sheet'!D61/'Data Sheet'!C61-1 -> 0.04294032 | E59: ='Data Sheet'!E61/'Data Sheet'!D61-1 -> 0.081807934 | F59: ='Data Sheet'!F61/'Data Sheet'!E61-1 -> 2.4109066 | G59: ='Data Sheet'!G61/'Data Sheet'!F61-1 -> 0.02569101 | H59: ='Data Sheet'!H61/'Data Sheet'!G61-1 -> 0.036464982 | I59: ='Data Sheet'!I61/'Data Sheet'!H61-1 -> 0.074058869 | J59: ='Data Sheet'!J61/'Data Sheet'!I61-1 -> 0.017505638 | K59: ='Data Sheet'!K61/'Data Sheet'!J61-1 -> -0.0015651804
B60: Net Block | C60: ='Data Sheet'!C62/'Data Sheet'!B62-1 -> 0.024666214 | D60: ='Data Sheet'!D62/'Data Sheet'!C62-1 -> 0.041298587 | E60: ='Data Sheet'!E62/'Data Sheet'!D62-1 -> 0.16203606 | F60: ='Data Sheet'!F62/'Data Sheet'!E62-1 -> 8.3891221 | G60: ='Data Sheet'!G62/'Data Sheet'!F62-1 -> 0.00058316972 | H60: ='Data Sheet'!H62/'Data Sheet'!G62-1 -> 0.023410332 | I60: ='Data Sheet'!I62/'Data Sheet'!H62-1 -> 0.020236152 | J60: ='Data Sheet'!J62/'Data Sheet'!I62-1 -> 0.010996576 | K60: ='Data Sheet'!K62/'Data Sheet'!J62-1 -> 0.056924634
B61: Capital Work-in-Progress | C61: ='Data Sheet'!C63/'Data Sheet'!B63-1 -> 1.0131004 | D61: ='Data Sheet'!D63/'Data Sheet'!C63-1 -> -0.11930586 | E61: ='Data Sheet'!E63/'Data Sheet'!D63-1 -> 0.47044335 | F61: ='Data Sheet'!F63/'Data Sheet'!E63-1 -> 0.2479062 | G61: ='Data Sheet'!G63/'Data Sheet'!F63-1 -> 0.76241611 | H61: ='Data Sheet'!H63/'Data Sheet'!G63-1 -> -0.13785225 | I61: ='Data Sheet'!I63/'Data Sheet'!H63-1 -> -0.094522968 | J61: ='Data Sheet'!J63/'Data Sheet'!I63-1 -> -0.015609756 | K61: ='Data Sheet'!K63/'Data Sheet'!J63-1 -> -0.12784936
B62: Investments | C62: ='Data Sheet'!C64/'Data Sheet'!B64-1 -> -0.24275171 | D62: ='Data Sheet'!D64/'Data Sheet'!C64-1 -> -0.054646711 | E62: ='Data Sheet'!E64/'Data Sheet'!D64-1 -> -0.53792342 | F62: ='Data Sheet'!F64/'Data Sheet'!E64-1 -> 1.1585657 | G62: ='Data Sheet'!G64/'Data Sheet'!F64-1 -> 0.2997416 | H62: ='Data Sheet'!H64/'Data Sheet'!G64-1 -> -0.18148253 | I62: ='Data Sheet'!I64/'Data Sheet'!H64-1 -> 0.60478834 | J62: ='Data Sheet'!J64/'Data Sheet'!I64-1 -> -0.17621622 | K62: ='Data Sheet'!K64/'Data Sheet'!J64-1 -> 0.14409449
B63: Other Assets | C63: ='Data Sheet'!C65/'Data Sheet'!B65-1 -> 0.37665198 | D63: ='Data Sheet'!D65/'Data Sheet'!C65-1 -> 0.0792 | E63: ='Data Sheet'!E65/'Data Sheet'!D65-1 -> 0.1881023 | F63: ='Data Sheet'!F65/'Data Sheet'!E65-1 -> 0.079628763 | G63: ='Data Sheet'!G65/'Data Sheet'!F65-1 -> 0.025716969 | H63: ='Data Sheet'!H65/'Data Sheet'!G65-1 -> 0.1539545 | I63: ='Data Sheet'!I65/'Data Sheet'!H65-1 -> 0.16539518 | J63: ='Data Sheet'!J65/'Data Sheet'!I65-1 -> 0.084524745 | K63: ='Data Sheet'!K65/'Data Sheet'!J65-1 -> -0.17567241
B64: Total Assets | C64: ='Data Sheet'!C66/'Data Sheet'!B66-1 -> 0.13727238 | D64: ='Data Sheet'!D66/'Data Sheet'!C66-1 -> 0.04294032 | E64: ='Data Sheet'!E66/'Data Sheet'!D66-1 -> 0.081807934 | F64: ='Data Sheet'!F66/'Data Sheet'!E66-1 -> 2.4109066 | G64: ='Data Sheet'!G66/'Data Sheet'!F66-1 -> 0.02569101 | H64: ='Data Sheet'!H66/'Data Sheet'!G66-1 -> 0.036464982 | I64: ='Data Sheet'!I66/'Data Sheet'!H66-1 -> 0.074058869 | J64: ='Data Sheet'!J66/'Data Sheet'!I66-1 -> 0.017505638 | K64: ='Data Sheet'!K66/'Data Sheet'!J66-1 -> -0.0015651804

Sheet Ratio analysis
B2: Ratio | C2: FY17 | D2: FY18 | E2: FY19 | F2: FY20 | G2: FY21 | H2: FY22 | I2: FY23 | J2: FY24 | K2: FY25 | L2: FY26
B3: 1. LIQUIDITY RATIOS
B4: Current Ratio (Current Assets ÷ Current Liabilities) | C4: ='Data Sheet'!B65/'Data Sheet'!B60 -> 0.83638457 | D4: ='Data Sheet'!C65/'Data Sheet'!C60 -> 0.94509026 | E4: ='Data Sheet'!D65/'Data Sheet'!D60 -> 1.0120979 | F4: ='Data Sheet'!E65/'Data Sheet'!E60 -> 1.0753103 | G4: ='Data Sheet'!F65/'Data Sheet'!F60 -> 0.65712523 | H4: ='Data Sheet'!G65/'Data Sheet'!G60 -> 0.69596118 | I4: ='Data Sheet'!H65/'Data Sheet'!H60 -> 0.76018372 | J4: ='Data Sheet'!I65/'Data Sheet'!I60 -> 0.74048939 | ... L4: ='Data Sheet'!K65/'Data Sheet'!K60 -> 0.57826632
B5: Quick Ratio ((Current Assets − Inventory) ÷ Current Liabilities) | C5: =('Data Sheet'!B65-'Data Sheet'!B68)/'Data Sheet'!B60 -> 0.54381117 | D5: =('Data Sheet'!C65-'Data Sheet'!C68)/'Data Sheet'!C60 -> 0.70758907 | E5: =('Data Sheet'!D65-'Data Sheet'!D68)/'Data Sheet'!D60 -> 0.77070243 | F5: =('Data Sheet'!E65-'Data Sheet'!E68)/'Data Sheet'!E60 -> 0.8432573 | G5: =('Data Sheet'!F65-'Data Sheet'!F68)/'Data Sheet'!F60 -> 0.48723061 | H5: =('Data Sheet'!G65-'Data Sheet'!G68)/'Data Sheet'!G60 -> 0.49519655 | I5: =('Data Sheet'!H65-'Data Sheet'!H68)/'Data Sheet'!H60 -> 0.56295815 | J5: =('Data Sheet'!I65-'Data Sheet'!I68)/'Data Sheet'!I60 -> 0.58451933 | ... L5: =('Data Sheet'!K65-'Data Sheet'!K68)/'Data Sheet'!K60 -> 0.41604282
B7: 2. PROFITABILITY RATIOS
B8: Gross Profit Margin ((Sales − Material Cost) ÷ Sales) | C8: =('Data Sheet'!B17-(SUM('Data Sheet'!B18:B21)))/'Data Sheet'!B17 -> 0.49810024 | D8: =('Data Sheet'!C17-(SUM('Data Sheet'!C18:C21)))/'Data Sheet'!C17 -> 0.50490927 | E8: =('Data Sheet'!D17-(SUM('Data Sheet'!D18:D21)))/'Data Sheet'!D17 -> 0.51203256 | F8: =('Data Sheet'!E17-(SUM('Data Sheet'!E18:E21)))/'Data Sheet'!E17 -> 0.52215771 | G8: =('Data Sheet'!F17-(SUM('Data Sheet'!F18:F21)))/'Data Sheet'!F17 -> 0.49491792 | H8: =('Data Sheet'!G17-(SUM('Data Sheet'!G18:G21)))/'Data Sheet'!G17 -> 0.49347901 | I8: =('Data Sheet'!H17-(SUM('Data Sheet'!H18:H21)))/'Data Sheet'!H17 -> 0.46059756 | J8: =('Data Sheet'!I17-(SUM('Data Sheet'!I18:I21)))/'Data Sheet'!I17 -> 0.50458834 | ... L8: =('Data Sheet'!K17-(SUM('Data Sheet'!K18:K21)))/'Data Sheet'!K17 -> 0.48320097
B9: Operating Profit Margin (Operating Profit ÷ Sales) | C9: =('Data Sheet'!B28+'Data Sheet'!B27)/'Data Sheet'!B17 -> 0.19606779 | D9: =('Data Sheet'!C28+'Data Sheet'!C27)/'Data Sheet'!C17 -> 0.20627374 | E9: =('Data Sheet'!D28+'Data Sheet'!D27)/'Data Sheet'!D17 -> 0.21971509 | F9: =('Data Sheet'!E28+'Data Sheet'!E27)/'Data Sheet'!E17 -> 0.23334087 | G9: =('Data Sheet'!F28+'Data Sheet'!F27)/'Data Sheet'!F17 -> 0.22799183 | H9: =('Data Sheet'!G28+'Data Sheet'!G27)/'Data Sheet'!G17 -> 0.22852076 | I9: =('Data Sheet'!H28+'Data Sheet'!H27)/'Data Sheet'!H17 -> 0.22215253 | J9: =('Data Sheet'!I28+'Data Sheet'!I27)/'Data Sheet'!I17 -> 0.23038645 | ... L9: =('Data Sheet'!K28+'Data Sheet'!K27)/'Data Sheet'!K17 -> 0.28896507
B10: Net Profit Margin (Net Profit ÷ Sales) | C10: ='Data Sheet'!B30/'Data Sheet'!B17 -> 0.13497377 | D10: ='Data Sheet'!C30/'Data Sheet'!C17 -> 0.1466873 | E10: ='Data Sheet'!D30/'Data Sheet'!D17 -> 0.15400661 | F10: ='Data Sheet'!E30/'Data Sheet'!E17 -> 0.16962019 | G10: ='Data Sheet'!F30/'Data Sheet'!F17 -> 0.1700051 | H10: ='Data Sheet'!G30/'Data Sheet'!G17 -> 0.16929794 | I10: ='Data Sheet'!H30/'Data Sheet'!H17 -> 0.16705183 | J10: ='Data Sheet'!I30/'Data Sheet'!I17 -> 0.16603658 | ... L10: ='Data Sheet'!K30/'Data Sheet'!K17 -> 0.23329404
B11: Return on Assets (ROA) (Net Profit ÷ Total Assets) | C11: ='Data Sheet'!B30/'Data Sheet'!B66 -> 0.28498663 | D11: ='Data Sheet'!C30/AVERAGE('Data Sheet'!B61:C61) -> 0.310653 | E11: ='Data Sheet'!D30/AVERAGE('Data Sheet'!C61:D61) -> 0.33180784 | F11: ='Data Sheet'!E30/AVERAGE('Data Sheet'!D61:E61) -> 0.34799649 | G11: ='Data Sheet'!F30/AVERAGE('Data Sheet'!E61:F61) -> 0.17987918 | H11: ='Data Sheet'!G30/AVERAGE('Data Sheet'!F61:G61) -> 0.1275297 | I11: ='Data Sheet'!H30/AVERAGE('Data Sheet'!G61:H61) -> 0.14096376 | J11: ='Data Sheet'!I30/AVERAGE('Data Sheet'!H61:I61) -> 0.13561089 | K11: ='Data Sheet'!J30/AVERAGE('Data Sheet'!I61:J61) -> 0.13449783 | L11: ='Data Sheet'!K30/AVERAGE('Data Sheet'!J61:K61) -> 0.18847
B12: Return on Equity (ROE) (Net Profit ÷ Shareholders' Equity) | C12: ='Data Sheet'!B30/SUM('Data Sheet'!B57:B58) -> 0.66370107 | D12: ='Data Sheet'!C30/(AVERAGE(SUM('Data Sheet'!C57:C58),SUM('Data Sheet'!B57:B58))) -> 0.74352941 | E12: ='Data Sheet'!D30/(AVERAGE(SUM('Data Sheet'!D57:D58),SUM('Data Sheet'!C57:C58))) -> 0.79931344 | F12: ='Data Sheet'!E30/(AVERAGE(SUM('Data Sheet'!E57:E58),SUM('Data Sheet'!D57:D58))) -> 0.83846918 | G12: ='Data Sheet'!F30/(AVERAGE(SUM('Data Sheet'!F57:F58),SUM('Data Sheet'!E57:E58))) -> 0.28603116 | H12: ='Data Sheet'!G30/(AVERAGE(SUM('Data Sheet'!G57:G58),SUM('Data Sheet'!F57:F58))) -> 0.18357368 | I12: ='Data Sheet'!H30/(AVERAGE(SUM('Data Sheet'!H57:H58),SUM('Data Sheet'!G57:G58))) -> 0.20369345 | J12: ='Data Sheet'!I30/(AVERAGE(SUM('Data Sheet'!I57:I58),SUM('Data Sheet'!H57:H58))) -> 0.20245858 | K12: ='Data Sheet'!J30/(AVERAGE(SUM('Data Sheet'!J57:J58),SUM('Data Sheet'!I57:I58))) -> 0.21166766 | L12: ='Data Sheet'!K30/(AVERAGE(SUM('Data Sheet'!K57:K58),SUM('Data Sheet'!J57:J58))) -> 0.30649779
B13: Return on Capital Employed (ROCE) (EBIT ÷ Capital Employed) | C13: =SUM('Data Sheet'!B28,'Data Sheet'!B27)/SUM('Data Sheet'!B57:B58) -> 0.96411625 | D13: =SUM('Data Sheet'!C28,'Data Sheet'!C27)/(AVERAGE(SUM('Data Sheet'!C57:C58),SUM('Data Sheet'!B57:B58))) -> 1.0455615 | E13: =SUM('Data Sheet'!D28,'Data Sheet'!D27)/(AVERAGE(SUM('Data Sheet'!D57:D58),SUM('Data Sheet'!C57:C58))) -> 1.1403486 | F13: =SUM('Data Sheet'!E28,'Data Sheet'!E27)/(AVERAGE(SUM('Data Sheet'!E57:E58),SUM('Data Sheet'!D57:D58))) -> 1.1534543 | G13: =SUM('Data Sheet'!F28,'Data Sheet'!F27)/(AVERAGE(SUM('Data Sheet'!F57:F58),SUM('Data Sheet'!E57:E58))) -> 0.38359301 | H13: =SUM('Data Sheet'!G28,'Data Sheet'!G27)/(AVERAGE(SUM('Data Sheet'!G57:G58),SUM('Data Sheet'!F57:F58))) -> 0.24779036 | I13: =SUM('Data Sheet'!H28,'Data Sheet'!H27)/(AVERAGE(SUM('Data Sheet'!H57:H58),SUM('Data Sheet'!G57:G58))) -> 0.27088009 | J13: =SUM('Data Sheet'!I28,'Data Sheet'!I27)/(AVERAGE(SUM('Data Sheet'!I57:I58),SUM('Data Sheet'!H57:H58))) -> 0.28092433 | K13: =SUM('Data Sheet'!J28,'Data Sheet'!J27)/(AVERAGE(SUM('Data Sheet'!J57:J58),SUM('Data Sheet'!I57:I58))) -> 0.29417611 | L13: =SUM('Data Sheet'!K28,'Data Sheet'!K27)/(AVERAGE(SUM('Data Sheet'!K57:K58),SUM('Data Sheet'!J57:J58))) -> 0.37963746
B15: 3. EFFICIENCY RATIOS
B16: Inventory Turnover (COGS ÷ Inventory) | C16: =(SUM('Data Sheet'!B18:B21)/'Data Sheet'!B68) -> 6.5501771 | D16: =(SUM('Data Sheet'!C18:C21))/AVERAGE('Data Sheet'!B68:C68) -> 6.9639889 | E16: =(SUM('Data Sheet'!D18:D21))/AVERAGE('Data Sheet'!C68:D68) -> 7.5415766 | F16: =(SUM('Data Sheet'!E18:E21))/AVERAGE('Data Sheet'!D68:E68) -> 7.1185171 | G16: =(SUM('Data Sheet'!F18:F21))/AVERAGE('Data Sheet'!E68:F68) -> 7.4859754 | H16: =(SUM('Data Sheet'!G18:G21))/AVERAGE('Data Sheet'!F68:G68) -> 6.9224756 | I16: =(SUM('Data Sheet'!H18:H21))/AVERAGE('Data Sheet'!G68:H68) -> 7.8296394 | J16: =(SUM('Data Sheet'!I18:I21))/AVERAGE('Data Sheet'!H68:I68) -> 7.4130303 | K16: =(SUM('Data Sheet'!J18:J21))/AVERAGE('Data Sheet'!I68:J68) -> 7.3052033 | L16: =(SUM('Data Sheet'!K18:K21))/AVERAGE('Data Sheet'!J68:K68) -> 7.2396784
B17: Debtors Turnover (Sales ÷ Trade Receivables) | C17: ='Data Sheet'!B17/'Data Sheet'!B67 -> 30.564055 | D17: ='Data Sheet'!C17/AVERAGE('Data Sheet'!B67:C67) -> 29.682672 | E17: ='Data Sheet'!D17/AVERAGE('Data Sheet'!C67:D67) -> 25.150352 | F17: ='Data Sheet'!E17/AVERAGE('Data Sheet'!D67:E67) -> 26.835076 | G17: ='Data Sheet'!F17/AVERAGE('Data Sheet'!E67:F67) -> 32.355005 | H17: ='Data Sheet'!G17/AVERAGE('Data Sheet'!F67:G67) -> 26.262394 | I17: ='Data Sheet'!H17/AVERAGE('Data Sheet'!G67:H67) -> 22.795861 | J17: ='Data Sheet'!I17/AVERAGE('Data Sheet'!H67:I67) -> 20.37393 | K17: ='Data Sheet'!J17/AVERAGE('Data Sheet'!I67:J67) -> 17.995305 | L17: ='Data Sheet'!K17/AVERAGE('Data Sheet'!J67:K67) -> 17.912754
B18: Asset Turnover (Sales ÷ Total Assets) | C18: 2.1114224 | D18: 1.9899787 | E18: 2.1101508 | F18: 1.9740485 | G18: 0.68414315 | H18: 0.74385159 | I18: 0.8289886 | J18: 0.78859458 | K18: 0.76791505 | L18: 0.80849783
B19: Working Capital Turnover (Sales ÷ Working Capital) | C19: ='Data Sheet'!B17/('Data Sheet'!B65-'Data Sheet'!B60) -> -23.337087 | D19: ='Data Sheet'!C17/(AVERAGE(('Data Sheet'!C65-'Data Sheet'!C60),('Data Sheet'!B65-'Data Sheet'!B60))) -> -35.509491 | E19: ='Data Sheet'!D17/(AVERAGE(('Data Sheet'!D65-'Data Sheet'!D60),('Data Sheet'!C65-'Data Sheet'!C60))) -> -173.93805 | F19: ='Data Sheet'!E17/(AVERAGE(('Data Sheet'!E65-'Data Sheet'!E60),('Data Sheet'!D65-'Data Sheet'!D60))) -> 77.474197 | G19: ='Data Sheet'!F17/(AVERAGE(('Data Sheet'!F65-'Data Sheet'!F60),('Data Sheet'!E65-'Data Sheet'!E60))) -> -14.870514 | H19: ='Data Sheet'!G17/(AVERAGE(('Data Sheet'!G65-'Data Sheet'!G60),('Data Sheet'!F65-'Data Sheet'!F60))) -> -7.8126024 | I19: ='Data Sheet'!H17/(AVERAGE(('Data Sheet'!H65-'Data Sheet'!H60),('Data Sheet'!G65-'Data Sheet'!G60))) -> -10.654238 | J19: ='Data Sheet'!I17/(AVERAGE(('Data Sheet'!I65-'Data Sheet'!I60),('Data Sheet'!H65-'Data Sheet'!H60))) -> -10.436894 | K19: ='Data Sheet'!J17/(AVERAGE(('Data Sheet'!J65-'Data Sheet'!J60),('Data Sheet'!I65-'Data Sheet'!I60))) -> -8.2898081 | L19: ='Data Sheet'!K17/(AVERAGE(('Data Sheet'!K65-'Data Sheet'!K60),('Data Sheet'!J65-'Data Sheet'!J60))) -> -6.2730369
B21: 4. SOLVENCY RATIOS
B22: Debt-Equity Ratio (Borrowings ÷ Shareholders' Equity) | C22: ='Data Sheet'!B59/SUM('Data Sheet'!B57:B58) -> 0.041073547 | D22: ='Data Sheet'!C59/(AVERAGE(('Data Sheet'!C57:C58),('Data Sheet'!B57:B58))) -> 0 | E22: ='Data Sheet'!D59/(AVERAGE(('Data Sheet'!D57:D58),('Data Sheet'!C57:C58))) -> 0.026142065 | F22: ='Data Sheet'!E59/(AVERAGE(('Data Sheet'!E57:E58),('Data Sheet'!D57:D58))) -> 0 | G22: ='Data Sheet'!F59/(AVERAGE(('Data Sheet'!F57:F58),('Data Sheet'!E57:E58))) -> 0 | H22: ='Data Sheet'!G59/(AVERAGE(('Data Sheet'!G57:G58),('Data Sheet'!F57:F58))) -> 0.043128134 | I22: ='Data Sheet'!H59/(AVERAGE(('Data Sheet'!H57:H58),('Data Sheet'!G57:G58))) -> 0.049071605 | J22: ='Data Sheet'!I59/(AVERAGE(('Data Sheet'!I57:I58),('Data Sheet'!H57:H58))) -> 0.058470085 | K22: ='Data Sheet'!J59/(AVERAGE(('Data Sheet'!J57:J58),('Data Sheet'!I57:I58))) -> 0.065513814 | L22: ='Data Sheet'!K59/(AVERAGE(('Data Sheet'!K57:K58),('Data Sheet'!J57:J58))) -> 0.060239859
B23: Interest Coverage Ratio (EBIT ÷ Interest Expense) | C23: =SUM('Data Sheet'!B28,'Data Sheet'!B27)/'Data Sheet'!B27 -> 185.77143 | D23: =SUM('Data Sheet'!C28,'Data Sheet'!C27)/'Data Sheet'!C27 -> 282 | E23: =SUM('Data Sheet'!D28,'Data Sheet'!D27)/'Data Sheet'!D27 -> 261.72727 | F23: =SUM('Data Sheet'!E28,'Data Sheet'!E27)/'Data Sheet'!E27 -> 78.669492 | G23: =SUM('Data Sheet'!F28,'Data Sheet'!F27)/'Data Sheet'!F27 -> 91.641026 | H23: =SUM('Data Sheet'!G28,'Data Sheet'!G27)/'Data Sheet'!G27 -> 113.06604 | I23: =SUM('Data Sheet'!H28,'Data Sheet'!H27)/'Data Sheet'!H27 -> 118.05263 | J23: =SUM('Data Sheet'!I28,'Data Sheet'!I27)/'Data Sheet'!I27 -> 42.694611 | ... L23: =SUM('Data Sheet'!K28,'Data Sheet'!K27)/'Data Sheet'!K27 -> 45.436585
B24: Debt Service Coverage Ratio (approx.) (Cash from Operations ÷ Interest Expense) | C24: =SUM('Data Sheet'!B28,'Data Sheet'!B27)/SUM('Data Sheet'!B27,ABS('Cash Flow Data'!C31)) -> 171.10526 | D24: =SUM('Data Sheet'!C28,'Data Sheet'!C27)/SUM('Data Sheet'!C27,ABS('Cash Flow Data'!D31)) -> 282 | E24: =SUM('Data Sheet'!D28,'Data Sheet'!D27)/SUM('Data Sheet'!D27,ABS('Cash Flow Data'!E31)) -> 21.977099 | F24: =SUM('Data Sheet'!E28,'Data Sheet'!E27)/SUM('Data Sheet'!E27,ABS('Cash Flow Data'!F31)) -> 23.501266 | G24: =SUM('Data Sheet'!F28,'Data Sheet'!F27)/SUM('Data Sheet'!F27,ABS('Cash Flow Data'!G31)) -> 91.641026 | H24: =SUM('Data Sheet'!G28,'Data Sheet'!G27)/SUM('Data Sheet'!G27,ABS('Cash Flow Data'!H31)) -> 58.463415 | I24: =SUM('Data Sheet'!H28,'Data Sheet'!H27)/SUM('Data Sheet'!H27,ABS('Cash Flow Data'!I31)) -> 44.562914 | J24: =SUM('Data Sheet'!I28,'Data Sheet'!I27)/SUM('Data Sheet'!I27,ABS('Cash Flow Data'!J31)) -> 36.658098 | ... L24: =SUM('Data Sheet'!K28,'Data Sheet'!K27)/SUM('Data Sheet'!K27,ABS('Cash Flow Data'!L31)) -> 37.634343
B26: 5. MARKET RATIOS
B27: Earnings Per Share (EPS) (Net Profit ÷ Weighted Avg. Shares) | C27: ='Data Sheet'!B30/'Data Sheet'!B93 -> 20.681052 | D27: ='Data Sheet'!C30/'Data Sheet'!C93 -> 24.088704 | E27: ='Data Sheet'!D30/'Data Sheet'!D93 -> 27.966924 | F27: ='Data Sheet'!E30/'Data Sheet'!E93 -> 31.171471 | G27: ='Data Sheet'!F30/'Data Sheet'!F93 -> 34.027068 | H27: ='Data Sheet'!G30/'Data Sheet'!G93 -> 37.789411 | I27: ='Data Sheet'!H30/'Data Sheet'!H93 -> 43.071161 | J27: ='Data Sheet'!I30/'Data Sheet'!I93 -> 43.73936 | ... L27: ='Data Sheet'!K30/'Data Sheet'!K93 -> 64.010895
B28: Price-to-Earnings (P/E) Ratio (Market Price ÷ EPS) | C28: ='Data Sheet'!B90/('Data Sheet'!B30/'Data Sheet'!B93) -> 42.193696 | D28: ='Data Sheet'!C90/('Data Sheet'!C30/'Data Sheet'!C93) -> 52.975453 | E28: ='Data Sheet'!D90/('Data Sheet'!D30/'Data Sheet'!D93) -> 58.409356 | F28: ='Data Sheet'!E90/('Data Sheet'!E30/'Data Sheet'!E93) -> 70.571903 | G28: ='Data Sheet'!F90/('Data Sheet'!F30/'Data Sheet'!F93) -> 68.390258 | H28: ='Data Sheet'!G90/('Data Sheet'!G30/'Data Sheet'!G93) -> 51.884905 | I28: ='Data Sheet'!H90/('Data Sheet'!H30/'Data Sheet'!H93) -> 56.892824 | J28: ='Data Sheet'!I90/('Data Sheet'!I30/'Data Sheet'!I93) -> 49.546678 | ... L28: ='Data Sheet'!K90/('Data Sheet'!K30/'Data Sheet'!K93) -> 32.107034
B29: Dividend Payout Ratio (Dividend Paid ÷ Net Profit) | C29: ='Data Sheet'!B31/'Data Sheet'!B30 -> 0.82037534 | D29: ='Data Sheet'!C31/'Data Sheet'!C30 -> 0.82853855 | E29: ='Data Sheet'!D31/'Data Sheet'!D30 -> 0.78493558 | F29: ='Data Sheet'!E31/'Data Sheet'!E30 -> 0.80023711 | G29: ='Data Sheet'!F31/'Data Sheet'!F30 -> 1.1904315 | H29: ='Data Sheet'!G31/'Data Sheet'!G30 -> 0.89987611 | I29: ='Data Sheet'!H31/'Data Sheet'!H30 -> 0.90563241 | J29: ='Data Sheet'!I31/'Data Sheet'!I30 -> 0.960397 | ... L29: ='Data Sheet'!K31/'Data Sheet'!K30 -> 0.640625
B30: Book Value per Share (BVPS) (Shareholders' Equity ÷ Shares Outstanding) | C30: =SUM('Data Sheet'!B57:B58)/'Data Sheet'!B93 -> 31.16019 | D30: =SUM('Data Sheet'!C57:C58)/'Data Sheet'!C93 -> 33.638254 | E30: =SUM('Data Sheet'!D57:D58)/'Data Sheet'!D93 -> 36.342218 | F30: =SUM('Data Sheet'!E57:E58)/'Data Sheet'!E93 -> 38.012749 | G30: =SUM('Data Sheet'!F57:F58)/'Data Sheet'!F93 -> 202.90262 | H30: =SUM('Data Sheet'!G57:G58)/'Data Sheet'!G93 -> 208.80575 | I30: =SUM('Data Sheet'!H57:H58)/'Data Sheet'!H93 -> 214.09602 | J30: =SUM('Data Sheet'!I57:I58)/'Data Sheet'!I93 -> 217.98604 | ... L30: =SUM('Data Sheet'!K57:K58)/'Data Sheet'!K93 -> 207.43531

Sheet Dupont
B2: Return on Equity (ROE)
C3: 44651 | D3: 45016 | E3: 45382 | F3: 45747 | G3: 46112
B4: Net Profit | C4: ='Data Sheet'!G30 -> 8879 | D4: ='Data Sheet'!H30 -> 10120 | E4: ='Data Sheet'!I30 -> 10277 | F4: ='Data Sheet'!J30 -> 10649 | G4: ='Data Sheet'!K30 -> 15040
B5: Average Shareholder Equity | C5: =AVERAGE(SUM('Data Sheet'!F57:F58),SUM('Data Sheet'!G57:G58)) -> 48367.5 | D5: =AVERAGE(SUM('Data Sheet'!G57:G58),SUM('Data Sheet'!H57:H58)) -> 49682.5 | E5: =AVERAGE(SUM('Data Sheet'!H57:H58),SUM('Data Sheet'!I57:I58)) -> 50761 | F5: =AVERAGE(SUM('Data Sheet'!I57:I58),SUM('Data Sheet'!J57:J58)) -> 50310 | G5: =AVERAGE(SUM('Data Sheet'!J57:J58),SUM('Data Sheet'!K57:K58)) -> 49070.5
B6: Return on Equity | C6: =C4/C5 -> 0.18357368 | D6: =D4/D5 -> 0.20369345 | E6: =E4/E5 -> 0.20245858 | F6: =F4/F5 -> 0.21166766 | G6: =G4/G5 -> 0.30649779
B8: ROE - Dupont Equation
C9: =C3 -> 44651 | D9: =D3 -> 45016 | E9: =E3 -> 45382 | F9: =F3 -> 45747 | G9: =G3 -> 46112
B10: Net Profit | C10: =C4 -> 8879 | D10: =D4 -> 10120 | E10: =E4 -> 10277 | F10: =F4 -> 10649 | G10: =G4 -> 15040
B11: Revenue | C11: 52446 | D11: 60580 | E11: 61896 | F11: 61328 | G11: 64468
B12: Net Profit Margin (A) | C12: =C10/C11 -> 0.16929794 | D12: =D10/D11 -> 0.16705183 | E12: =E10/E11 -> 0.16603658 | F12: =F10/F11 -> 0.1736401 | G12: =G10/G11 -> 0.23329404
B14: Revenue | C14: =C11 -> 52446 | D14: =D11 -> 60580 | E14: =E11 -> 61896 | F14: =F11 -> 61328 | G14: =G11 -> 64468
B15: Average Total Asset | C15: =AVERAGE('Data Sheet'!F66:G66) -> 69623 | D15: =AVERAGE('Data Sheet'!G66:H66) -> 71791.5 | E15: =AVERAGE('Data Sheet'!H66:I66) -> 75783 | F15: =AVERAGE('Data Sheet'!I66:J66) -> 79176 | G15: =AVERAGE('Data Sheet'!J66:K66) -> 79800.5
B16: Asset Turnover Ratio (B) | C16: =C14/C15 -> 0.75328555 | D16: =D14/D15 -> 0.84383249 | E16: =E14/E15 -> 0.8167531 | F16: =F14/F15 -> 0.77457815 | G16: =G14/G15 -> 0.80786461
B18: Average Total Asset | C18: =C15 -> 69623 | D18: =D15 -> 71791.5 | E18: =E15 -> 75783 | F18: =F15 -> 79176 | G18: =G15 -> 79800.5
B19: Average Shareholder Equity | C19: =C5 -> 48367.5 | D19: =D5 -> 49682.5 | E19: =E5 -> 50761 | F19: =F5 -> 50310 | G19: =G5 -> 49070.5
B20: Equity Multiplier (C) | C20: =C18/C19 -> 1.4394583 | D20: =D18/D19 -> 1.4450058 | E20: =E18/E19 -> 1.4929375 | F20: =F18/F19 -> 1.5737627 | G20: =G18/G19 -> 1.6262418
B22: Return on Equity (A*B*C) | C22: =C12*C16*C20 -> 0.18357368 | D22: =D12*D16*D20 -> 0.20369345 | E22: =E12*E16*E20 -> 0.20245858 | F22: =F12*F16*F20 -> 0.21166766 | G22: =G12*G16*G20 -> 0.30649779
B24: Return on Asset (ROA)
C25: =C3 -> 44651 | D25: =D3 -> 45016 | E25: =E3 -> 45382 | F25: =F3 -> 45747 | G25: =G3 -> 46112
B26: Net Profit | C26: =C10 -> 8879 | D26: =D10 -> 10120 | E26: =E10 -> 10277 | F26: =F10 -> 10649 | G26: =G10 -> 15040
B27: Average Total Asset | C27: =C15 -> 69623 | D27: =D15 -> 71791.5 | E27: =E15 -> 75783 | F27: =F15 -> 79176 | G27: =G15 -> 79800.5
B28: Return on Equity | C28: =C26/C27 -> 0.1275297 | D28: =D26/D27 -> 0.14096376 | E28: =E26/E27 -> 0.13561089 | F28: =F26/F27 -> 0.13449783 | G28: =G26/G27 -> 0.18847
B30: ROA - Dupont Equation
C31: =C3 -> 44651 | D31: =D3 -> 45016 | E31: =E3 -> 45382 | F31: =F3 -> 45747 | G31: =G3 -> 46112
B32: Net Profit | C32: =C26 -> 8879 | D32: =D26 -> 10120 | E32: =E26 -> 10277 | F32: =F26 -> 10649 | G32: =G26 -> 15040
B33: Revenue | C33: =C14 -> 52446 | D33: =D14 -> 60580 | E33: =E14 -> 61896 | F33: =F14 -> 61328 | G33: =G14 -> 64468
B34: Net Profit Margin (A) | C34: =C32/C33 -> 0.16929794 | D34: =D32/D33 -> 0.16705183 | E34: =E32/E33 -> 0.16603658 | F34: =F32/F33 -> 0.1736401 | G34: =G32/G33 -> 0.23329404
B36: Revenue | C36: =C33 -> 52446 | D36: =D33 -> 60580 | E36: =E33 -> 61896 | F36: =F33 -> 61328 | G36: =G33 -> 64468
B37: Average Total Asset | C37: =C15 -> 69623 | D37: =D15 -> 71791.5 | E37: =E15 -> 75783 | F37: =F15 -> 79176 | G37: =G15 -> 79800.5
B38: Asset Turnover Ratio (B) | C38: =C36/C37 -> 0.75328555 | D38: =D36/D37 -> 0.84383249 | E38: =E36/E37 -> 0.8167531 | F38: =F36/F37 -> 0.77457815 | G38: =G36/G37 -> 0.80786461
B40: Return on Asset (A*B) | C40: =C34*C38 -> 0.1275297 | D40: =D34*D38 -> 0.14096376 | E40: =E34*E38 -> 0.13561089 | F40: =F34*F38 -> 0.13449783 | G40: =G34*G38 -> 0.18847

Sheet Altman Z Score
J2: Weights
B3: Working Capital / Total Assets | J3: 1.2
C4: ='Data Sheet'!E16 -> 43921 | D4: ='Data Sheet'!F16 -> 44286 | E4: ='Data Sheet'!G16 -> 44651 | F4: ='Data Sheet'!H16 -> 45016 | G4: ='Data Sheet'!I16 -> 45382 | H4: ='Data Sheet'!J16 -> 45747 | I4: ='Data Sheet'!K16 -> 46112
B5: Working Capital | C5: =IFERROR('Data Sheet'!E65-'Data Sheet'!E60,0) -> 898 | D5: =IFERROR('Data Sheet'!F65-'Data Sheet'!F60,0) -> -7223 | E5: =IFERROR('Data Sheet'!G65-'Data Sheet'!G60,0) -> -6203 | F5: =IFERROR('Data Sheet'!H65-'Data Sheet'!H60,0) -> -5169 | G5: =IFERROR('Data Sheet'!I65-'Data Sheet'!I60,0) -> -6692 | H5: =IFERROR('Data Sheet'!J65-'Data Sheet'!J60,0) -> -8104 | I5: =IFERROR('Data Sheet'!K65-'Data Sheet'!K60,0) -> -12450
B6: Total Asset | C6: =IFERROR(AVERAGE('Data Sheet'!D66:E66),0) -> 19391 | D6: =IFERROR(AVERAGE('Data Sheet'!E66:F66),0) -> 44446.5 | E6: =IFERROR(AVERAGE('Data Sheet'!F66:G66),0) -> 69623 | F6: =IFERROR(AVERAGE('Data Sheet'!G66:H66),0) -> 71791.5 | G6: =IFERROR(AVERAGE('Data Sheet'!H66:I66),0) -> 75783 | H6: =IFERROR(AVERAGE('Data Sheet'!I66:J66),0) -> 79176 | I6: =IFERROR(AVERAGE('Data Sheet'!J66:K66),0) -> 79800.5
B7: =B3 -> Working Capital / Total Assets | C7: =C5/C6 -> 0.046310144 | D7: =D5/D6 -> -0.16250998 | E7: =E5/E6 -> -0.089094121 | F7: =F5/F6 -> -0.072000167 | G7: =G5/G6 -> -0.088304765 | H7: =H5/H6 -> -0.10235425 | I7: =I5/I6 -> -0.15601406
B9: Retained Earnings / Total Assets | J9: 1.4
C10: =C4 -> 43921 | D10: =D4 -> 44286 | E10: =E4 -> 44651 | F10: =F4 -> 45016 | G10: =G4 -> 45382 | H10: =H4 -> 45747 | I10: =I4 -> 46112
B11: Retained Earnings | C11: ='Data Sheet'!E58 -> 8013 | D11: ='Data Sheet'!F58 -> 47439 | E11: ='Data Sheet'!G58 -> 48826 | F11: ='Data Sheet'!H58 -> 50069 | G11: ='Data Sheet'!I58 -> 50983 | H11: ='Data Sheet'!J58 -> 49167 | I11: ='Data Sheet'!K58 -> 48504
B12: Total Asset | C12: =C6 -> 19391 | D12: =D6 -> 44446.5 | E12: =E6 -> 69623 | F12: =F6 -> 71791.5 | G12: =G6 -> 75783 | H12: =H6 -> 79176 | I12: =I6 -> 79800.5
B13: =B9 -> Retained Earnings / Total Assets | C13: =C11/C12 -> 0.41323294 | D13: =D11/D12 -> 1.0673281 | E13: =E11/E12 -> 0.70129124 | F13: =F11/F12 -> 0.6974224 | G13: =G11/G12 -> 0.67274983 | H13: =H11/H12 -> 0.62098363 | I13: =I11/I12 -> 0.60781574
B15: EBIT / Total Assets | J15: 3.3
C16: =C4 -> 43921 | D16: =D4 -> 44286 | E16: =E4 -> 44651 | F16: =F4 -> 45016 | G16: =G4 -> 45382 | H16: =H4 -> 45747 | I16: =I4 -> 46112
B17: EBIT | C17: =SUM('Data Sheet'!E28,'Data Sheet'!E27) -> 9283 | D17: =SUM('Data Sheet'!F28,'Data Sheet'!F27) -> 10722 | E17: =SUM('Data Sheet'!G28,'Data Sheet'!G27) -> 11985 | F17: =SUM('Data Sheet'!H28,'Data Sheet'!H27) -> 13458 | G17: =SUM('Data Sheet'!I28,'Data Sheet'!I27) -> 14260 | H17: =SUM('Data Sheet'!J28,'Data Sheet'!J27) -> 14800 | I17: =SUM('Data Sheet'!K28,'Data Sheet'!K27) -> 18629
B18: Total Asset | C18: =C6 -> 19391 | D18: =D6 -> 44446.5 | E18: =E6 -> 69623 | F18: =F6 -> 71791.5 | G18: =G6 -> 75783 | H18: =H6 -> 79176 | I18: =I6 -> 79800.5
B19: =B15 -> EBIT / Total Assets | C19: =C17/C18 -> 0.47872724 | D19: =D17/D18 -> 0.24123384 | E19: =E17/E18 -> 0.17214139 | F19: =F17/F18 -> 0.18745952 | G19: =G17/G18 -> 0.18816885 | H19: =H17/H18 -> 0.18692533 | I19: =I17/I18 -> 0.23344465
B21: Revenue / Total Assets | J21: 1
C22: =C10 -> 43921 | D22: =D10 -> 44286 | E22: =E10 -> 44651 | F22: =F10 -> 45016 | G22: =G10 -> 45382 | H22: =H10 -> 45747 | I22: =I10 -> 46112
B23: Revenue | C23: ='Data Sheet'!E17 -> 39783 | D23: ='Data Sheet'!F17 -> 47028 | E23: ='Data Sheet'!G17 -> 52446 | F23: ='Data Sheet'!H17 -> 60580 | G23: ='Data Sheet'!I17 -> 61896 | H23: ='Data Sheet'!J17 -> 61328 | I23: ='Data Sheet'!K17 -> 64468
B24: Total Asset | C24: =C12 -> 19391 | D24: =D12 -> 44446.5 | E24: =E12 -> 69623 | F24: =F12 -> 71791.5 | G24: =G12 -> 75783 | H24: =H12 -> 79176 | I24: =I12 -> 79800.5
B25: =B21 -> Revenue / Total Assets | C25: =C23/C24 -> 2.0516219 | D25: =D23/D24 -> 1.0580811 | E25: =E23/E24 -> 0.75328555 | F25: =F23/F24 -> 0.84383249 | G25: =G23/G24 -> 0.8167531 | H25: =H23/H24 -> 0.77457815 | I25: =I23/I24 -> 0.80786461
B27: Market Cap. / Long term liabilities | J27: 0.6
C28: =C4 -> 43921 | D28: =D4 -> 44286 | E28: =E4 -> 44651 | F28: =F4 -> 45016 | G28: =G4 -> 45382 | H28: =H4 -> 45747 | I28: =I4 -> 46112
B29: Market Cap. | C29: =PRODUCT('Data Sheet'!C90,'Data Sheet'!C93) -> 276214.01 | D29: =PRODUCT('Data Sheet'!D90,'Data Sheet'!D93) -> 353610.24 | E29: =PRODUCT('Data Sheet'!E90,'Data Sheet'!E93) -> 476219.2 | F29: =PRODUCT('Data Sheet'!F90,'Data Sheet'!F93) -> 546780.12 | G29: =PRODUCT('Data Sheet'!G90,'Data Sheet'!G93) -> 460686.07 | H29: =PRODUCT('Data Sheet'!H90,'Data Sheet'!H93) -> 575755.38 | I29: =PRODUCT('Data Sheet'!I90,'Data Sheet'!I93) -> 509191.21
B30: Total Liabilites | C30: ='Data Sheet'!E61 -> 20153 | D30: ='Data Sheet'!F61 -> 68740 | E30: ='Data Sheet'!G61 -> 70506 | F30: ='Data Sheet'!H61 -> 73077 | G30: ='Data Sheet'!I61 -> 78489 | H30: ='Data Sheet'!J61 -> 79863 | I30: ='Data Sheet'!K61 -> 79738
B31: Market Cap. / Long term liabilities | C31: =IFERROR(C29/C30,0) -> 13.705851 | D31: =IFERROR(D29/D30,0) -> 5.1441699 | E31: =IFERROR(E29/E30,0) -> 6.7543074 | F31: =IFERROR(F29/F30,0) -> 7.4822463 | G31: =IFERROR(G29/G30,0) -> 5.8694349 | H31: =IFERROR(H29/H30,0) -> 7.2092882 | I31: =IFERROR(I29/I30,0) -> 6.3858037
B33: Altman's Z Score
C34: =C4 -> 43921 | D34: =D4 -> 44286 | E34: =E4 -> 44651 | F34: =F4 -> 45016 | G34: =G4 -> 45382 | H34: =H4 -> 45747 | I34: =I4 -> 46112
B35: Final Score | C35: =(C7*$J$3+C13*$J$9+C19*$J$15+C25*$J$21+C31*$J$27) -> 12.489031 | D35: =(D7*$J$3+D13*$J$9+D19*$J$15+D25*$J$21+D31*$J$27) -> 6.2399021 | E35: =(E7*$J$3+E13*$J$9+E19*$J$15+E25*$J$21+E31*$J$27) -> 6.2488314 | F35: =(F7*$J$3+F13*$J$9+F19*$J$15+F25*$J$21+F31*$J$27) -> 6.8417879 | G35: =(G7*$J$3+G13*$J$9+G19*$J$15+G25*$J$21+G31*$J$27) -> 5.7952553 | H35: =(H7*$J$3+H13*$J$9+H19*$J$15+H25*$J$21+H31*$J$27) -> 6.4635566 | I35: =(I7*$J$3+I13*$J$9+I19*$J$15+I25*$J$21+I31*$J$27) -> 6.0734393
B37: Verdict | C37: {=_xlfn.IFS(C35<1.81,"Distressed",C35<3,"Grey Zone",C35>2,"Stable")} -> Stable | D37: {=_xlfn.IFS(D35<1.81,"Distressed",D35<3,"Grey Zone",D35>2,"Stable")} -> Stable | E37: {=_xlfn.IFS(E35<1.81,"Distressed",E35<3,"Grey Zone",E35>2,"Stable")} -> Stable | F37: {=_xlfn.IFS(F35<1.81,"Distressed",F35<3,"Grey Zone",F35>2,"Stable")} -> Stable | G37: {=_xlfn.IFS(G35<1.81,"Distressed",G35<3,"Grey Zone",G35>2,"Stable")} -> Stable | H37: {=_xlfn.IFS(H35<1.81,"Distressed",H35<3,"Grey Zone",H35>2,"Stable")} -> Stable | I37: {=_xlfn.IFS(I35<1.81,"Distressed",I35<3,"Grey Zone",I35>2,"Stable")} -> Stable
B39: <1.81 - distressed
B40: 1.81-3 = grey zone
B41: >3 = stable

Sheet Beneish M-Score
B3: 1. RAW INPUT VARIABLES
B4: Particulars | C4: FY17 | D4: FY18 | E4: FY19 | F4: FY20 | G4: FY21 | H4: FY22 | I4: FY23 | J4: FY24 | K4: FY25 | L4: FY26
B5: Net Sales | C5: ='Data Sheet'!B17 -> 33162 | D5: ='Data Sheet'!C17 -> 35545 | E5: ='Data Sheet'!D17 -> 39310 | F5: ='Data Sheet'!E17 -> 39783 | G5: ='Data Sheet'!F17 -> 47028 | H5: ='Data Sheet'!G17 -> 52446 | I5: ='Data Sheet'!H17 -> 60580 | J5: ='Data Sheet'!I17 -> 61896 | ... L5: ='Data Sheet'!K17 -> 64468
B6: Trade Receivables | C6: ='Data Sheet'!B67 -> 1085 | D6: ='Data Sheet'!C67 -> 1310 | E6: ='Data Sheet'!D67 -> 1816 | F6: ='Data Sheet'!E67 -> 1149 | G6: ='Data Sheet'!F67 -> 1758 | H6: ='Data Sheet'!G67 -> 2236 | I6: ='Data Sheet'!H67 -> 3079 | J6: ='Data Sheet'!I67 -> 2997 | ... L6: ='Data Sheet'!K67 -> 3379
B7: Gross Profit (Sales − Material Cost) | C7: ='Data Sheet'!B17-SUM('Data Sheet'!B18:B21) -> 16518 | D7: ='Data Sheet'!C17-SUM('Data Sheet'!C18:C21) -> 17947 | E7: ='Data Sheet'!D17-SUM('Data Sheet'!D18:D21) -> 20128 | F7: ='Data Sheet'!E17-SUM('Data Sheet'!E18:E21) -> 20773 | G7: ='Data Sheet'!F17-SUM('Data Sheet'!F18:F21) -> 23275 | H7: ='Data Sheet'!G17-SUM('Data Sheet'!G18:G21) -> 25881 | I7: ='Data Sheet'!H17-SUM('Data Sheet'!H18:H21) -> 27903 | J7: ='Data Sheet'!I17-SUM('Data Sheet'!I18:I21) -> 31232 | ... L7: ='Data Sheet'!K17-SUM('Data Sheet'!K18:K21) -> 31151
B8: Total Assets | C8: ='Data Sheet'!B66 -> 15706 | D8: ='Data Sheet'!C66 -> 17862 | E8: ='Data Sheet'!D66 -> 18629 | F8: ='Data Sheet'!E66 -> 20153 | G8: ='Data Sheet'!F66 -> 68740 | H8: ='Data Sheet'!G66 -> 70506 | I8: ='Data Sheet'!H66 -> 73077 | J8: ='Data Sheet'!I66 -> 78489 | ... L8: ='Data Sheet'!K66 -> 79738
B9: Current Assets (proxy: Other Assets) | C9: ='Data Sheet'!B65 -> 7264 | D9: ='Data Sheet'!C65 -> 10000 | E9: ='Data Sheet'!D65 -> 10792 | F9: ='Data Sheet'!E65 -> 12822 | G9: ='Data Sheet'!F65 -> 13843 | H9: ='Data Sheet'!G65 -> 14199 | I9: ='Data Sheet'!H65 -> 16385 | J9: ='Data Sheet'!I65 -> 19095 | ... L9: ='Data Sheet'!K65 -> 17071
B10: Net PP&E (Net Block + CWIP) | C10: =SUM('Data Sheet'!B62:B63) -> 4648 | D10: =SUM('Data Sheet'!C62:C63) -> 4989 | E10: =SUM('Data Sheet'!D62:D63) -> 5121 | F10: =SUM('Data Sheet'!E62:E63) -> 6076 | G10: =SUM('Data Sheet'!F62:F63) -> 52188 | H10: =SUM('Data Sheet'!G62:G63) -> 52786 | I10: =SUM('Data Sheet'!H62:H63) -> 53810 | J10: =SUM('Data Sheet'!I62:I63) -> 54769 | ... L10: =SUM('Data Sheet'!K62:K63) -> 58308
B11: Securities (Investments) | C11: ='Data Sheet'!B64 -> 3794 | D11: ='Data Sheet'!C64 -> 2873 | E11: ='Data Sheet'!D64 -> 2716 | F11: ='Data Sheet'!E64 -> 1255 | G11: ='Data Sheet'!F64 -> 2709 | H11: ='Data Sheet'!G64 -> 3521 | I11: ='Data Sheet'!H64 -> 2882 | J11: ='Data Sheet'!I64 -> 4625 | ... L11: ='Data Sheet'!K64 -> 4359
B12: Current Liabilities (proxy: Other Liabilities) | C12: ='Data Sheet'!B60 -> 8685 | D12: ='Data Sheet'!C60 -> 10581 | E12: ='Data Sheet'!D60 -> 10663 | F12: ='Data Sheet'!E60 -> 11924 | G12: ='Data Sheet'!F60 -> 21066 | H12: ='Data Sheet'!G60 -> 20402 | I12: ='Data Sheet'!H60 -> 21554 | J12: ='Data Sheet'!I60 -> 25787 | ... L12: ='Data Sheet'!K60 -> 29521
B13: Total Debt (proxy: Borrowings) | C13: ='Data Sheet'!B59 -> 277 | D13: ='Data Sheet'!C59 -> 0 | E13: ='Data Sheet'!D59 -> 99 | F13: ='Data Sheet'!E59 -> 0 | G13: ='Data Sheet'!F59 -> 0 | H13: ='Data Sheet'!G59 -> 1043 | I13: ='Data Sheet'!H59 -> 1219 | J13: ='Data Sheet'!I59 -> 1484 | ... L13: ='Data Sheet'!K59 -> 1478
B14: SG&A Expense (proxy: Employee + Selling/Admin Cost) | C14: =SUM('Data Sheet'!B22:B24) -> 9902 | D14: =SUM('Data Sheet'!C22:C24) -> 10592 | E14: =SUM('Data Sheet'!D22:D24) -> 11224 | F14: =SUM('Data Sheet'!E22:E24) -> 11128 | G14: =SUM('Data Sheet'!F22:F24) -> 12459 | H14: =SUM('Data Sheet'!G22:G24) -> 13068 | I14: =SUM('Data Sheet'!H22:H24) -> 13906 | J14: =SUM('Data Sheet'!I22:I24) -> 16595 | ... L14: =SUM('Data Sheet'!K22:K24) -> 16970
B15: Depreciation | C15: ='Data Sheet'!B26 -> 432 | D15: ='Data Sheet'!C26 -> 520 | E15: ='Data Sheet'!D26 -> 565 | F15: ='Data Sheet'!E26 -> 1002 | G15: ='Data Sheet'!F26 -> 1074 | H15: ='Data Sheet'!G26 -> 1091 | I15: ='Data Sheet'!H26 -> 1137 | J15: ='Data Sheet'!I26 -> 1216 | ... L15: ='Data Sheet'!K26 -> 1333
B16: Net Income | C16: ='Data Sheet'!B30 -> 4476 | D16: ='Data Sheet'!C30 -> 5214 | E16: ='Data Sheet'!D30 -> 6054 | F16: ='Data Sheet'!E30 -> 6748 | G16: ='Data Sheet'!F30 -> 7995 | H16: ='Data Sheet'!G30 -> 8879 | I16: ='Data Sheet'!H30 -> 10120 | J16: ='Data Sheet'!I30 -> 10277 | ... L16: ='Data Sheet'!K30 -> 15040
B17: Cash Flow from Operations | C17: ='Data Sheet'!B82 -> 5185 | D17: ='Data Sheet'!C82 -> 6059 | E17: ='Data Sheet'!D82 -> 5800 | F17: ='Data Sheet'!E82 -> 7623 | G17: ='Data Sheet'!F82 -> 9163 | H17: ='Data Sheet'!G82 -> 9048 | I17: ='Data Sheet'!H82 -> 9991 | J17: ='Data Sheet'!I82 -> 15469 | ... L17: ='Data Sheet'!K82 -> 10999
B19: 2. BENEISH INDEX COMPONENTS (Year-on-Year, FY18 → FY26)
B20: Particulars | C20: FY18 | D20: FY19 | E20: FY20 | F20: FY21 | G20: FY22 | H20: FY23 | I20: FY24 | J20: FY25 | K20: FY26
B21: DSRI — Days' Sales in Receivables Index | C21: =(D6/D5)/(C6/C5) -> 1.1264288 | D21: =(E6/E5)/(D6/D5) -> 1.2534875 | E21: =(F6/F5)/(E6/E5) -> 0.62518665 | F21: =(G6/G5)/(F6/F5) -> 1.2943146 | G21: =(H6/H5)/(G6/G5) -> 1.1405047 | H21: =(I6/I5)/(H6/H5) -> 1.1921228 | I21: =(J6/J5)/(I6/I5) -> 0.95267274 | J21: =(K6/K5)/(J6/J5) -> 1.2860762 | K21: =(L6/L5)/(K6/K5) -> 0.84169188
B22: GMI — Gross Margin Index | C22: =(C7/C5)/(D7/D5) -> 0.98651434 | D22: =(D7/D5)/(E7/E5) -> 0.98608821 | E22: =(E7/E5)/(F7/F5) -> 0.98060903 | F22: =(F7/F5)/(G7/G5) -> 1.055039 | G22: =(G7/G5)/(H7/H5) -> 1.0029159 | H22: =(H7/H5)/(I7/I5) -> 1.0713887 | I22: =(I7/I5)/(J7/J5) -> 0.91281847 | J22: =(J7/J5)/(K7/K5) -> 1.0142373 | K22: =(K7/K5)/(L7/L5) -> 1.0296031
B23: AQI — Asset Quality Index (held at 1.00, see Notes) | C23: =1 -> 1 | D23: =1 -> 1 | E23: =1 -> 1 | F23: =1 -> 1 | G23: =1 -> 1 | H23: =1 -> 1 | I23: =1 -> 1 | J23: =1 -> 1 | K23: =1 -> 1
B24: SGI — Sales Growth Index | C24: =D5/C5 -> 1.0718594 | D24: =E5/D5 -> 1.1059221 | E24: =F5/E5 -> 1.0120326 | F24: =G5/F5 -> 1.182113 | G24: =H5/G5 -> 1.115208 | H24: =I5/H5 -> 1.1550929 | I24: =J5/I5 -> 1.0217233 | J24: =K5/J5 -> 0.99082332 | K24: =L5/K5 -> 1.0512001
B25: DEPI — Depreciation Index | C25: =(C15/(C10+C15))/(D15/(D10+D15)) -> 0.90092671 | D25: =(D15/(D10+D15))/(E15/(E10+E15)) -> 0.94992426 | E25: =(E15/(E10+E15))/(F15/(F10+F15)) -> 0.70191485 | F25: =(F15/(F10+F15))/(G15/(G10+G15)) -> 7.0205373 | G25: =(G15/(G10+G15))/(H15/(H10+H15)) -> 0.99578474 | H25: =(H15/(H10+H15))/(I15/(I10+I15)) -> 0.97859922 | I25: =(I15/(I10+I15))/(J15/(J10+J15)) -> 0.95269654 | J25: =(J15/(J10+J15))/(K15/(K10+K15)) -> 0.98107957 | K25: =(K15/(K10+K15))/(L15/(L10+L15)) -> 0.99054093
B26: SGAI — SG&A Expense Index | C26: =(D14/D5)/(C14/C5) -> 0.99796945 | D26: =(E14/E5)/(D14/D5) -> 0.95817572 | E26: =(F14/F5)/(E14/E5) -> 0.97965909 | F26: =(G14/G5)/(F14/F5) -> 0.94712454 | G26: =(H14/H5)/(G14/G5) -> 0.94052443 | H26: =(I14/I5)/(H14/H5) -> 0.92124724 | I26: =(J14/J5)/(I14/I5) -> 1.167997 | J26: =(K14/K5)/(J14/J5) -> 0.97690692 | K26: =(L14/L5)/(K14/K5) -> 1.0050086
B27: LVGI — Leverage Index | C27: =((D13+D12)/D8)/((C13+C12)/C8) -> 1.0381432 | D27: =((E13+E12)/E8)/((D13+D12)/D8) -> 0.97522947 | E27: =((F13+F12)/F8)/((E13+E12)/E8) -> 1.024186 | F27: =((G13+G12)/G8)/((F13+F12)/F8) -> 0.51795292 | G27: =((H13+H12)/H8)/((G13+G12)/G8) -> 0.99249293 | H27: =((I13+I12)/I8)/((H13+H12)/H8) -> 1.0245651 | I27: =((J13+J12)/J8)/((I13+I12)/I8) -> 1.1149432 | J27: =((K13+K12)/K8)/((J13+J12)/J8) -> 1.0977571 | K27: =((L13+L12)/L8)/((K13+K12)/K8) -> 1.0192572
B28: TATA — Total Accruals to Total Assets | C28: =(D16-D17)/D8 -> -0.047307132 | D28: =(E16-E17)/E8 -> 0.013634656 | E28: =(F16-F17)/F8 -> -0.043417853 | F28: =(G16-G17)/G8 -> -0.016991562 | G28: =(H16-H17)/H8 -> -0.0023969591 | H28: =(I16-I17)/I8 -> 0.0017652613 | I28: =(J16-J17)/J8 -> -0.066149397 | J28: =(K16-K17)/K8 -> -0.015489025 | K28: =(L16-L17)/L8 -> 0.050678472
B30: 3. M-SCORE & CLASSIFICATION
B31: Particulars | C31: FY18 | D31: FY19 | E31: FY20 | F31: FY21 | G31: FY22 | H31: FY23 | I31: FY24 | J31: FY25 | K31: FY26
B32: M-SCORE | C32: =-4.84+0.92*C21+0.528*C22+0.404*C23+0.892*C24+0.115*C25-0.172*C26+4.679*C28-0.327*C27 -> -2.5515745 | D32: =-4.84+0.92*D21+0.528*D22+0.404*D23+0.892*D24+0.115*D25-0.172*D26+4.679*D28-0.327*D27 -> -2.0863228 | E32: =-4.84+0.92*E21+0.528*E22+0.404*E23+0.892*E24+0.115*E25-0.172*E26+4.679*E28-0.327*E27 -> -3.0661758 | F32: =-4.84+0.92*F21+0.528*F22+0.404*F23+0.892*F24+0.115*F25-0.172*F26+4.679*F28-0.327*F27 -> -1.2381429 | G32: =-4.84+0.92*G21+0.528*G22+0.404*G23+0.892*G24+0.115*G25-0.172*G26+4.679*G28-0.327*G27 -> -2.2454461 | H32: =-4.84+0.92*H21+0.528*H22+0.404*H23+0.892*H24+0.115*H25-0.172*H26+4.679*H28-0.327*H27 -> -2.1158997 | I32: =-4.84+0.92*I21+0.528*I22+0.404*I23+0.892*I24+0.115*I25-0.172*I26+4.679*I28-0.327*I27 -> -2.9316305 | J32: =-4.84+0.92*J21+0.528*J22+0.404*J23+0.892*J24+0.115*J25-0.172*J26+4.679*J28-0.327*J27 -> -2.3201218 | K32: =-4.84+0.92*K21+0.528*K22+0.404*K23+0.892*K24+0.115*K25-0.172*K26+4.679*K28-0.327*K27 -> -2.3354644
B33: Classification (M-score > −1.78 = Low Risk) | C33: =IF(C32>-1.78,"Flagged — High Risk","Low Risk / Unlikely") -> Low Risk / Unlikely | D33: =IF(D32>-1.78,"Flagged — High Risk","Low Risk / Unlikely") -> Low Risk / Unlikely | E33: =IF(E32>-1.78,"Flagged — High Risk","Low Risk / Unlikely") -> Low Risk / Unlikely | F33: =IF(F32>-1.78,"Flagged — High Risk","Low Risk / Unlikely") -> Flagged — High Risk | G33: =IF(G32>-1.78,"Flagged — High Risk","Low Risk / Unlikely") -> Low Risk / Unlikely | H33: =IF(H32>-1.78,"Flagged — High Risk","Low Risk / Unlikely") -> Low Risk / Unlikely | I33: =IF(I32>-1.78,"Flagged — High Risk","Low Risk / Unlikely") -> Low Risk / Unlikely | J33: =IF(J32>-1.78,"Flagged — High Risk","Low Risk / Unlikely") -> Low Risk / Unlikely | K33: =IF(K32>-1.78,"Flagged — High Risk","Low Risk / Unlikely") -> Low Risk / Unlikely
B36: * Asset Quality Index (AQI) cannot be computed under its standard definition here because the source balance sheet has no residual 'other non-current/intangible assets' line distinct from PP&E, Investments and Current Assets — CA + PP&E + Securities always equals Total Assets exactly in this dataset, making the formula 0÷0. AQI is therefore held at the neutral value 1.00 in every year; this is a conservative simplification, not a computed result.

Sheet Beta
B2: HUL Weekly Returns | F2: Nifty 50 Weekly Return | I2: Beta Drifting
L3: Beta 1 | M3: =SLOPE(D5:D212,G5:G212) -> 0.44527238
B4: Date | C4: Price | D4: Weekly Return | F4: Price | G4: Weekly Return | I4: Levered Raw Beta | J4: =M4 -> 0.44527238 | L4: Beta 2 | M4: =_xlfn.COVARIANCE.S(D5:D212,G5:G212)/_xlfn.VAR.S(G5:G212) -> 0.44527238
B5: 46243 | C5: 2077.1 | D5: =C5/C6-1 -> -0.0090171756 | F5: 24318.85 | G5: =F5/F6-1 -> -0.010247999 | I5: Raw Beta Weight | J5: 0.75
B6: 46236 | C6: 2096 | D6: =C6/C7-1 -> -0.0025222481 | F6: 24570.65 | G6: =F6/F7-1 -> 0.0076711396
B7: 46229 | C7: 2101.3 | D7: =C7/C8-1 -> -0.02037296 | F7: 24383.6 | G7: =F7/F8-1 -> 0.02592411
B8: 46222 | C8: 2145 | D8: =C8/C9-1 -> 0.00055975371 | F8: 23767.45 | G8: =F8/F9-1 -> -0.02329428 | I8: Market Beta | J8: 1
B9: 46215 | C9: 2143.8 | D9: =C9/C10-1 -> -0.0031619083 | F9: 24334.3 | G9: =F9/F10-1 -> 0.0052629622 | I9: Market Beta weight | J9: 0.25
B10: 46208 | C10: 2150.6 | D10: =C10/C11-1 -> -0.022987461 | F10: 24206.9 | G10: =F10/F11-1 -> -0.002634848
B11: 46201 | C11: 2201.2 | D11: =C11/C12-1 -> 0.012418361 | F11: 24270.85 | G11: =F11/F12-1 -> 0.0089312438 | I11: Adjusted Levered Beta | J11: =(J4*J5)+(J8*J9) -> 0.58395429
B12: 46194 | C12: 2174.2 | D12: =C12/C13-1 -> -0.0092955436 | F12: 24056 | G12: =F12/F13-1 -> 0.0017865249
B13: 46187 | C13: 2194.6 | D13: =C13/C14-1 -> 0.011895979 | F13: 24013.1 | G13: =F13/F14-1 -> 0.01651787
B14: 46180 | C14: 2168.8 | D14: =C14/C15-1 -> 0.022295546 | F14: 23622.9 | G14: =F14/F15-1 -> 0.010964321 | I14: Adjusted beta = it will move towards 1
B15: 46173 | C15: 2121.5 | D15: =C15/C16-1 -> -0.014859531 | F15: 23366.7 | G15: =F15/F16-1 -> -0.0076886327
B16: 46166 | C16: 2153.5 | D16: =C16/C17-1 -> -0.022735524 | F16: 23547.75 | G16: =F16/F17-1 -> -0.0072325069
B17: 46159 | C17: 2203.6 | D17: =C17/C18-1 -> -0.030191004 | F17: 23719.3 | G17: =F17/F18-1 -> 0.0032059551
B18: 46152 | C18: 2272.2 | D18: =C18/C19-1 -> -0.0067753639 | F18: 23643.5 | G18: =F18/F19-1 -> -0.022032044
B19: 46145 | C19: 2287.7 | D19: =C19/C20-1 -> 0.016349016 | F19: 24176.15 | G19: =F19/F20-1 -> 0.0074424264
B20: 46138 | C20: 2250.9 | D20: =C20/C21-1 -> -0.03282774 | F20: 23997.55 | G20: =F20/F21-1 -> 0.0041677215
B21: 46131 | C21: 2327.3 | D21: =C21/C22-1 -> 0.038602285 | F21: 23897.95 | G21: =F21/F22-1 -> -0.018707745
B22: 46124 | C22: 2240.8 | D22: =C22/C23-1 -> 0.039669652 | F22: 24353.55 | G22: =F22/F23-1 -> 0.012596359
B23: 46117 | C23: 2155.3 | D23: =C23/C24-1 -> 0.043577204 | F23: 24050.6 | G23: =F23/F24-1 -> 0.058886722
B24: 46110 | C24: 2065.3 | D24: =C24/C25-1 -> -0.0043868106 | F24: 22713.1 | G24: =F24/F25-1 -> -0.0046670406
B25: 46103 | C25: 2074.4 | D25: =C25/C26-1 -> -0.0039852115 | F25: 22819.6 | G25: =F25/F26-1 -> -0.012758225
B26: 46096 | C26: 2082.7 | D26: =C26/C27-1 -> -0.035787037 | F26: 23114.5 | G26: =F26/F27-1 -> -0.0015809184
... B212: 44794 | C212: 2561.35 | D212: =C212/C213-1 -> -0.023912961 | F212: 17558.9 | G212: =F212/F213-1 -> -0.011236904
B213: 44787 | C213: 2624.1 | D213: - | F213: 17758.45 | G213: -

Sheet Beta comps 
D2: ITC | G2: Nestle | J2: Godrej | M2: Marico | P2: Nifty 50 Weekly Return
C4: Date | D4: Price | E4: Weekly Return | G4: Price | H4: Weekly Return | J4: Price | K4: Weekly Return | M4: Price | N4: Weekly Return | P4: Price | Q4: Weekly Return | T4: Company | U4: Raw Beta
C5: 46243 | D5: 276.85 | E5: =D5/D6-1 -> -0.032331353 | G5: 1509.9 | H5: =G5/G6-1 -> -0.019545455 | J5: 936 | K5: =J5/J6-1 -> -0.10857143 | M5: 862 | N5: =M5/M6-1 -> 0 | P5: 24318.85 | Q5: =P5/P6-1 -> -0.010247999 | T5: =D2 -> ITC | U5: =SLOPE(E5:E213,Q5:Q213) -> 0.54837001
C6: 46236 | D6: 286.1 | E6: =D6/D7-1 -> 0.018149466 | G6: 1540 | H6: =G6/G7-1 -> 0.020137785 | J6: 1050 | K6: =J6/J7-1 -> -0.019058296 | M6: 862 | N6: =M6/M7-1 -> -0.009935106 | P6: 24570.65 | Q6: =P6/P7-1 -> 0.0076711396 | T6: =G2 -> Nestle | U6: =SLOPE(H5:H213,Q5:Q213) -> 0.63043236
C7: 46229 | D7: 281 | E7: =D7/D8-1 -> -0.0086434997 | G7: 1509.6 | H7: =G7/G8-1 -> 0.045791479 | J7: 1070.4 | K7: =J7/J8-1 -> 0.010287872 | M7: 870.65 | N7: =M7/M8-1 -> 0.017589995 | P7: 24383.6 | Q7: =P7/P8-1 -> 0.02592411 | T7: =J2 -> Godrej | U7: =SLOPE(K5:K213,Q5:Q213) -> 0.75183996
C8: 46222 | D8: 283.45 | E8: =D8/D9-1 -> 0.0097969362 | G8: 1443.5 | H8: =G8/G9-1 -> 0.011420964 | J8: 1059.5 | K8: =J8/J9-1 -> -0.011568243 | M8: 855.6 | N8: =M8/M9-1 -> 0.013744076 | P8: 23767.45 | Q8: =P8/P9-1 -> -0.02329428 | T8: =M2 -> Marico | U8: =SLOPE(N5:N213,Q5:Q213) -> 0.42497053
C9: 46215 | D9: 280.7 | E9: =D9/D10-1 -> -0.0037267081 | G9: 1427.2 | H9: =G9/G10-1 -> -0.019241341 | J9: 1071.9 | K9: =J9/J10-1 -> -0.015159868 | M9: 844 | N9: =M9/M10-1 -> -0.0099706745 | P9: 24334.3 | Q9: =P9/P10-1 -> 0.0052629622
C10: 46208 | D10: 281.75 | E10: =D10/D11-1 -> -0.028280738 | G10: 1455.2 | H10: =G10/G11-1 -> -0.0017835094 | J10: 1088.4 | K10: =J10/J11-1 -> 0.0106788 | M10: 852.5 | N10: =M10/M11-1 -> 0.01663586 | P10: 24206.9 | Q10: =P10/P11-1 -> -0.002634848
C11: 46201 | D11: 289.95 | E11: =D11/D12-1 -> -0.00017241379 | G11: 1457.8 | H11: =G11/G12-1 -> 0.040780192 | J11: 1076.9 | K11: =J11/J12-1 -> 0.040885366 | M11: 838.55 | N11: =M11/M12-1 -> 0.015439574 | P11: 24270.85 | Q11: =P11/P12-1 -> 0.0089312438
C12: 46194 | D12: 290 | E12: =D12/D13-1 -> -0.0085470085 | G12: 1400.68 | H12: =G12/G13-1 -> -0.0086278285 | J12: 1034.6 | K12: =J12/J13-1 -> 0.033979612 | M12: 825.8 | N12: =M12/M13-1 -> 0.010709259 | P12: 24056 | Q12: =P12/P13-1 -> 0.0017865249
C13: 46187 | D13: 292.5 | E13: =D13/D14-1 -> 0.025955805 | G13: 1412.87 | H13: =G13/G14-1 -> 0.028424393 | J13: 1000.6 | K13: =J13/J14-1 -> -0.031646182 | M13: 817.05 | N13: =M13/M14-1 -> -0.0024418534 | P13: 24013.1 | Q13: =P13/P14-1 -> 0.01651787 | U13: (Beta will Move towards One)
C14: 46180 | D14: 285.1 | E14: =D14/D15-1 -> 0.015675098 | G14: 1373.82 | H14: =G14/G15-1 -> -0.0089308902 | J14: 1033.3 | K14: =J14/J15-1 -> 0.035370741 | M14: 819.05 | N14: =M14/M15-1 -> 0.010362055 | P14: 23622.9 | Q14: =P14/P15-1 -> 0.010964321 | T14: Beta Drifting
C15: 46173 | D15: 280.7 | E15: =D15/D16-1 -> -0.021610317 | G15: 1386.2 | H15: =G15/G16-1 -> -0.024832923 | J15: 998 | K15: =J15/J16-1 -> -0.030409016 | M15: 810.65 | N15: =M15/M16-1 -> -0.01344773 | P15: 23366.7 | Q15: =P15/P16-1 -> -0.0076886327
C16: 46166 | D16: 286.9 | E16: =D16/D17-1 -> -0.049055353 | G16: 1421.5 | H16: =G16/G17-1 -> -0.0011243061 | J16: 1029.3 | K16: =J16/J17-1 -> 0.0017518248 | M16: 821.7 | N16: =M16/M17-1 -> -0.003335557 | P16: 23547.75 | Q16: =P16/P17-1 -> -0.0072325069 | T16: Company | U16: Levered Raw Beta | V16: Leverage Raw Beta weight | W16: Market Weight | X16: Market Beta | Y16: Adjusted Beta
C17: 46159 | D17: 301.7 | E17: =D17/D18-1 -> -0.025044434 | G17: 1423.1 | H17: =G17/G18-1 -> -0.0051730164 | J17: 1027.5 | K17: =J17/J18-1 -> -0.011258661 | M17: 824.45 | N17: =M17/M18-1 -> -0.019853772 | P17: 23719.3 | Q17: =P17/P18-1 -> 0.0032059551 | T17: =T5 -> ITC | U17: =U5 -> 0.54837001 | V17: 0.75 | W17: 0.25 | X17: 1 | Y17: =(U17*V17)+(X17*W17) -> 0.66127751
C18: 46152 | D18: 309.45 | E18: =D18/D19-1 -> 0.0065051228 | G18: 1430.5 | H18: =G18/G19-1 -> -0.035010793 | J18: 1039.2 | K18: =J18/J19-1 -> -0.0030698388 | M18: 841.15 | N18: =M18/M19-1 -> 0.011848911 | P18: 23643.5 | Q18: =P18/P19-1 -> -0.022032044 | T18: =T6 -> Nestle | U18: =U6 -> 0.63043236 | V18: 0.75 | W18: 0.25 | X18: 1 | Y18: =(U18*V18)+(X18*W18) -> 0.72282427
C19: 46145 | D19: 307.45 | E19: =D19/D20-1 -> -0.023658304 | G19: 1482.4 | H19: =G19/G20-1 -> 0.016317016 | J19: 1042.4 | K19: =J19/J20-1 -> -0.023146847 | M19: 831.3 | N19: =M19/M20-1 -> 0.072645161 | P19: 24176.15 | Q19: =P19/P20-1 -> 0.0074424264 | T19: =T7 -> Godrej | U19: =U7 -> 0.75183996 | V19: 0.75 | W19: 0.25 | X19: 1 | Y19: =(U19*V19)+(X19*W19) -> 0.81387997
C20: 46138 | D20: 314.9 | E20: =D20/D21-1 -> 0.044098143 | G20: 1458.6 | H20: =G20/G21-1 -> 0.02624358 | J20: 1067.1 | K20: =J20/J21-1 -> -0.02091935 | M20: 775 | N20: =M20/M21-1 -> -0.010596196 | P20: 23997.55 | Q20: =P20/P21-1 -> 0.0041677215 | T20: =T8 -> Marico | U20: =U8 -> 0.42497053 | V20: 0.75 | W20: 0.25 | X20: 1 | Y20: =(U20*V20)+(X20*W20) -> 0.5687279
C21: 46131 | D21: 301.6 | E21: =D21/D22-1 -> -0.016949153 | G21: 1421.3 | H21: =G21/G22-1 -> 0.10555383 | J21: 1089.9 | K21: =J21/J22-1 -> -0.017577069 | M21: 783.3 | N21: =M21/M22-1 -> 0.034332497 | P21: 23897.95 | Q21: =P21/P22-1 -> -0.018707745
C22: 46124 | D22: 306.8 | E22: =D22/D23-1 -> 0.0083812654 | G22: 1285.6 | H22: =G22/G23-1 -> 0.029056272 | J22: 1109.4 | K22: =J22/J23-1 -> 0.029032557 | M22: 757.3 | N22: =M22/M23-1 -> -0.0077956109 | P22: 24353.55 | Q22: =P22/P23-1 -> 0.012596359
C23: 46117 | D23: 304.25 | E23: =D23/D24-1 -> 0.038927779 | G23: 1249.3 | H23: =G23/G24-1 -> 0.048686309 | J23: 1078.1 | K23: =J23/J24-1 -> 0.083735424 | M23: 763.25 | N23: =M23/M24-1 -> 0.0024955671 | P23: 24050.6 | Q23: =P23/P24-1 -> 0.058886722
C24: 46110 | D24: 292.85 | E24: =D24/D25-1 -> -0.0062775704 | G24: 1191.3 | H24: =G24/G25-1 -> -0.0015923567 | J24: 994.8 | K24: =J24/J25-1 -> -0.013780113 | M24: 761.35 | N24: =M24/M25-1 -> 0.02545626 | P24: 22713.1 | Q24: =P24/P25-1 -> -0.0046670406
C25: 46103 | D25: 294.7 | E25: =D25/D26-1 -> -0.017502917 | G25: 1193.2 | H25: =G25/G26-1 -> -0.00033512064 | J25: 1008.7 | K25: =J25/J26-1 -> -0.0087460692 | M25: 742.45 | N25: =M25/M26-1 -> -0.0024855569 | P25: 22819.6 | Q25: =P25/P26-1 -> -0.012758225
C26: 46096 | D26: 299.95 | E26: =D26/D27-1 -> -0.0049759496 | G26: 1193.6 | H26: =G26/G27-1 -> -0.0071535518 | J26: 1017.6 | K26: =J26/J27-1 -> -0.01002043 | M26: 744.3 | N26: =M26/M27-1 -> -0.01076555 | P26: 23114.5 | Q26: =P26/P27-1 -> -0.0015809184
C27: 46089 | D27: 301.45 | E27: =D27/D28-1 -> -0.026638683 | G27: 1202.2 | H27: =G27/G28-1 -> -0.040083041 | J27: 1027.9 | K27: =J27/J28-1 -> -0.079437578 | M27: 752.4 | N27: =M27/M28-1 -> -0.041833811 | P27: 23151.1 | Q27: =P27/P28-1 -> -0.053142171
C28: 46082 | D28: 309.7 | E28: =D28/D29-1 -> -0.012436224 | G28: 1252.4 | H28: =G28/G29-1 -> -0.030425021 | J28: 1116.6 | K28: =J28/J29-1 -> -0.082874743 | M28: 785.25 | N28: =M28/M29-1 -> -0.0043111646 | P28: 24450.45 | Q28: =P28/P29-1 -> -0.028921328
C29: 46075 | D29: 313.6 | E29: =D29/D30-1 -> -0.040978593 | G29: 1291.7 | H29: =G29/G30-1 -> -0.0016231257 | J29: 1217.5 | K29: =J29/J30-1 -> 0.0096193714 | M29: 788.65 | N29: =M29/M30-1 -> 0.00057092109 | P29: 25178.65 | Q29: =P29/P30-1 -> -0.01535318
C30: 46068 | D30: 327 | E30: =D30/D31-1 -> 0.042231076 | G30: 1293.8 | H30: =G30/G31-1 -> 0.0087322626 | J30: 1205.9 | K30: =J30/J31-1 -> 0.0087836707 | M30: 788.2 | N30: =M30/M31-1 -> 0.036900612 | P30: 25571.25 | Q30: =P30/P31-1 -> 0.0039319071
C31: 46061 | D31: 313.75 | E31: =D31/D32-1 -> -0.036985881 | G31: 1282.6 | H31: =G31/G32-1 -> -0.015882759 | J31: 1195.4 | K31: =J31/J32-1 -> 0.011507869 | M31: 760.15 | N31: =M31/M32-1 -> 0.0098306211 | P31: 25471.1 | Q31: =P31/P32-1 -> -0.0086636024
C32: 46054 | D32: 325.8 | E32: =D32/D33-1 -> 0.011330126 | G32: 1303.3 | H32: =G32/G33-1 -> -0.021840288 | J32: 1181.8 | K32: =J32/J33-1 -> 0.024001386 | M32: 752.75 | N32: =M32/M33-1 -> 0.031446972 | P32: 25693.7 | Q32: =P32/P33-1 -> 0.014733034
... C212: 44794 | D212: 294.2 | E212: =D212/D213-1 -> 0.0028975626 | G212: 976.41 | H212: =G212/G213-1 -> 0.0044956998 | J212: 897.8 | K212: =J212/J213-1 -> -0.0089413843 | M212: 515.6 | N212: =M212/M213-1 -> -0.00067836031 | P212: 17558.9 | Q212: =P212/P213-1 -> -0.011236904
C213: 44787 | D213: 293.35 | E213: - | G213: 972.04 | H213: - | J213: 905.9 | K213: - | M213: 515.95 | N213: - | P213: 17758.45 | Q213: -

Sheet ERP
B2: Equity Risk Premium (ERP) Calculation — India
B3: All figures follow Damodaran's country-risk methodology. Figures in blue are inputs (sourced externally); figures in black are calculated.
B5: 1. Mature Market Equity Risk Premium
B6: Implied Equity Risk Premium – S&P 500 (Jul 2026) | C6: 0.0442
B7: Less: US Sovereign Default Spread (Aa1 rating) | C7: 0.0022
B8: Mature Market Equity Risk Premium | C8: =C6-C7 -> 0.042
B10: 2. India Country Risk Premium
B11: Total Equity Risk Premium – India (Jul 2026) | C11: 0.0731
B12: Less: Mature Market Equity Risk Premium | C12: =C8 -> 0.042
B13: Implied India Country Risk Premium | C13: =C11-C12 -> 0.0311
B15: 3. Equity Risk Premium for India (used in WACC)
B16: Mature Market Equity Risk Premium | C16: =C8 -> 0.042
B17: Add: India Country Risk Premium | C17: =C13 -> 0.0311
B18: Equity Risk Premium for India | C18: =C16+C17 -> 0.0731
B20: This figure feeds WACC!K22 (Equity Risk Premium) and DCF Valuation!C21.

Sheet WACC
E2: WACC | F2: levered Beta to Unlevered Beta = levered Beta/(1+(1-tax)*D/E)
B3: All figures are in INR unless stated otherwise.
B5: Peer Companies
G6: Debt/ | H6: Debt/ | I6: Levered | J6: Unlevered
B7: Name of the Company | C7: Country | D7: Total debt | E7: Total Equity | F7: Tax Rate 1 | G7: Equity | H7: Capital | I7: Beta 2 | J7: Beta3
B8: Hind. Unilever | C8: India | D8: ='Data Sheet'!K59 -> 1478 | E8: ='Relative Valuation'!F7 -> 493603.97 | F8: 0.3 | G8: =D8/E8 -> 0.0029943033 | H8: =D8/(SUM(D8:E8)) -> 0.0029853642 | I8: =Beta!J11 -> 0.58395429 | J8: =I8/(1+(1-F8)*G8) -> 0.58273287
B9: ITC | C9: India | D9: 2399 | E9: ='Relative Valuation'!F8 -> 352016.3 | F9: 0.3 | G9: =D9/E9 -> 0.0068150253 | H9: =D9/(SUM(D9:E9)) -> 0.0067688951 | I9: ='Beta comps '!Y17 -> 0.66127751 | J9: =I9/(1+(1-F9)*G9) -> 0.65813785
B10: Nestle India | C10: India | D10: 7604 | E10: ='Relative Valuation'!F9 -> 291096.17 | F10: 0.3 | G10: =D10/E10 -> 0.026121952 | H10: =D10/(SUM(D10:E10)) -> 0.025456966 | I10: ='Beta comps '!Y18 -> 0.72282427 | J10: =I10/(1+(1-F10)*G10) -> 0.7098445
B11: Godrej Consumer | C11: India | D11: 4421 | E11: ='Relative Valuation'!F10 -> 109534.03 | F11: 0.3 | G11: =D11/E11 -> 0.040361885 | H11: =D11/(SUM(D11:E11)) -> 0.038796005 | I11: ='Beta comps '!Y19 -> 0.81387997 | J11: =I11/(1+(1-F11)*G11) -> 0.79151699
B12: Marico | C12: India | D12: 557 | E12: ='Relative Valuation'!F11 -> 113045.2 | F12: 0.3 | G12: =D12/E12 -> 0.0049272328 | H12: =D12/(SUM(D12:E12)) -> 0.0049030742 | I12: ='Beta comps '!Y20 -> 0.5687279 | J12: =I12/(1+(1-F12)*G12) -> 0.56677306
E14: Average | F14: =AVERAGE(F8:F12) -> 0.3 | G14: =AVERAGE(G8:G12) -> 0.01624408 | H14: =AVERAGE(H8:H12) -> 0.015782061 | I14: =AVERAGE(I8:I12) -> 0.67013279 | J14: =AVERAGE(J8:J12) -> 0.66180106
E15: Median | F15: =MEDIAN(F8:F12) -> 0.3 | G15: =MEDIAN(G8:G12) -> 0.0068150253 | H15: =MEDIAN(H8:H12) -> 0.0067688951 | I15: =MEDIAN(I8:I12) -> 0.66127751 | J15: =MEDIAN(J8:J12) -> 0.65813785 | K15: Use this unlevered beta (INDUSTRY MED.)
B18: Cost of Debt | G18: Cost of Equity
G19: 10 Y Govt. Bond | K19: 0.068
B20: Pre- Tax Cost of Debt | E20: ='Data Sheet'!K27/'Data Sheet'!K59 -> 0.27740189 | G20: Country Risk | K20: 0.018
B21: Tax Rate | E21: 0.3 | G21: Risk Free Rate | K21: =K19-K20 -> 0.05
B22: Post Tax Cost of Debt | E22: =E20*(1-E21) -> 0.19418133 | G22: Equity Risk Premium | K22: =ERP!C18 -> 0.0731
G23: Levered Beta 4 | K23: =K31 -> 0.66045291
G24: Cost of Equity | K24: =K21+K22*K23 -> 0.098279108
B26: Capital Structure | G26: Levered Beta
D28: Current | E28: Target | G28: Comps Median Unlevered Beta | K28: =J15 -> 0.65813785
B29: Total Debt | C29: =D8 -> 1478 | D29: =C29/$C$31 -> 0.0029853642 | E29: 0.005 | G29: Target Debt / Equity | K29: =E33 -> 0.0050251256
B30: Market Capitalization | C30: =E8 -> 493603.97 | D30: =C30/$C$31 -> 0.99701464 | E30: =E31-E29 -> 0.995 | G30: Tax Rate | K30: =E21 -> 0.3
B31: Total Capital | C31: =SUM(C29:C30) -> 495081.97 | D31: =SUM(D29:D30) -> 1 | E31: =D31 -> 1 | G31: Levered Beta | K31: =K28*(1+(1-K30)*K29) -> 0.66045291
B33: Debt/Equity | D33: =D29/D30 -> 0.0029943033 | E33: =E29/E30 -> 0.0050251256
G34: Weighted Average Cost of Capital
J36: Total Cost | K36: Total Weight
G37: Debt | J37: =E22 -> 0.19418133 | K37: =E29 -> 0.005
G38: Equity | J38: =K24 -> 0.098279108 | K38: =E30 -> 0.995
G39: Weighted Average Cost of Capital | K39: =SUMPRODUCT(J37:J38,K37:K38) -> 0.098758619

Sheet DCF Valuation
B2: Hindustan Unilever Ltd. - Discounted Cash Flow (DCF) Valuation
B3: All figures in Rs. crore unless stated otherwise. Figures in blue are inputs; figures in black are calculated. Base year (FY2026) data is linked to the Profit & Loss and Balance Sheet worksheets.
B5: 1. Assumptions and Drivers
B6: Driver | C6: FY2027E | D6: FY2028E | E6: FY2029E | F6: FY2030E | G6: FY2031E | H6: Basis of Assumption
B7: Revenue Growth % | C7: 0.08 | D7: 0.07 | E7: 0.07 | F7: 0.06 | G7: 0.06 | H7: Tapering from recent momentum of 8 to 10 per cent towards long run FMCG industry growth
B8: Operating Profit Margin (EBIT) % | C8: 0.235 | D8: 0.235 | E8: 0.235 | F8: 0.235 | G8: 0.235 | H8: Five year historical average operating margin of 23.3 to 24.5 per cent, held constant
B9: Effective Tax Rate % | C9: 0.26 | D9: 0.26 | E9: 0.26 | F9: 0.26 | G9: 0.26 | H9: Normalised rate; excludes the one-off rate of 17 per cent in FY2026 arising from the divestment
B10: D&A as % of Revenue | C10: 0.021 | D10: 0.021 | E10: 0.021 | F10: 0.021 | G10: 0.021 | H10: FY2026 actual: 1,333 / 64,468 = 2.07 per cent
B11: Capex as % of Revenue | C11: 0.023 | D11: 0.023 | E11: 0.023 | F11: 0.023 | G11: 0.023 | H11: Marginally above D&A to reflect premiumisation led capacity addition
B12: Net Working Capital as % of Revenue | C12: 0.054 | D12: 0.054 | E12: 0.054 | F12: 0.054 | G12: 0.054 | H12: FY2026 actual: NWC 3,472 / Revenue 64,468 = 5.4 per cent
B13: Terminal Growth Rate (g) | C13: 0.06 | H13: Long run growth assumption linked to nominal GDP growth in India
B15: 2. Capital Structure and Cost of Capital (WACC)
B17: Cost of Equity
B18: 10 Y Govt. Bond | C18: 0.068 | H18: India 10 year G-Sec yield, July 2026
B19: Country Risk | C19: 0.018 | H19: Damodaran's country spread estimate
B20: Risk Free Rate | C20: =C18-C19 -> 0.05
B21: Equity Risk Premium | C21: =WACC!K22 -> 0.0731 | H21: Equity risk premium for India, taken from ERP sheet
B22: Levered Beta 4 | C22: =WACC!K23 -> 0.66045291
B23: Cost of Equity | C23: =C20+C21*C22 -> 0.098279108
B25: Cost of Debt
B27: Pre- Tax Cost of Debt | C27: =WACC!E20 -> 0.27740189 | H27: Interest Payment / Borrowings (FY26)
B28: Tax Rate | C28: 0.3
B29: Post Tax Cost of Debt | C29: =C27*(1-C28) -> 0.19418133
B31: Total Debt | C31: 0.005 | H31: Assuming slight increase in debt
B32: Market Capitalization | C32: =C33-C31 -> 0.995
B33: Total Capital | C33: 1
B35: WACC | C35: =C31*C29+C23*C32 -> 0.098758619
B37: 3. Projected Income Statement
B38: Particulars | C38: FY2027E | D38: FY2028E | E38: FY2029E | F38: FY2030E | G38: FY2031E
B39: Revenue | C39: ='Data Sheet'!K17*(1+'DCF Valuation'!C7) -> 69625.44 | D39: =C39*(1+D7) -> 74499.221 | E39: =D39*(1+E7) -> 79714.166 | F39: =E39*(1+F7) -> 84497.016 | G39: =F39*(1+G7) -> 89566.837
B40: EBIT (Operating Profit) | C40: =C39*C8 -> 16361.978 | D40: =D39*D8 -> 17507.317 | E40: =E39*E8 -> 18732.829 | F40: =F39*F8 -> 19856.799 | G40: =G39*G8 -> 21048.207
B41: Tax on EBIT | C41: =C40*C9 -> 4254.1144 | D41: =D40*D9 -> 4551.9024 | E41: =E40*E9 -> 4870.5356 | F41: =F40*F9 -> 5162.7677 | G41: =G40*G9 -> 5472.5338
B42: NOPAT | C42: =C40-C41 -> 12107.864 | D42: =D40-D41 -> 12955.414 | E42: =E40-E41 -> 13862.294 | F42: =F40-F41 -> 14694.031 | G42: =G40-G41 -> 15575.673
B44: 4. Working Capital and Fixed Asset Schedule
B45: Particulars | C45: FY2027E | D45: FY2028E | E45: FY2029E | F45: FY2030E | G45: FY2031E
B46: Net Working Capital | C46: =C39*C12 -> 3759.7738 | D46: =D39*D12 -> 4022.9579 | E46: =E39*E12 -> 4304.565 | F46: =F39*F12 -> 4562.8389 | G46: =G39*G12 -> 4836.6092
B47: Increase / (Decrease) in NWC | C47: 287.77376 | D47: =D46-C46 -> 263.18416 | E47: =E46-D46 -> 281.60705 | F47: =F46-E46 -> 258.2739 | G47: =G46-F46 -> 273.77033
B48: Capital Expenditure (Capex) | C48: =C39*C11 -> 1601.3851 | D48: =D39*D11 -> 1713.4821 | E48: =E39*E11 -> 1833.4258 | F48: =F39*F11 -> 1943.4314 | G48: =G39*G11 -> 2060.0373
B49: Depreciation and Amortisation (D&A) | C49: =C39*C10 -> 1462.1342 | D49: =D39*D10 -> 1564.4836 | E49: =E39*E10 -> 1673.9975 | F49: =F39*F10 -> 1774.4373 | G49: =G39*G10 -> 1880.9036
B50: Opening Net PP&E | C50: 58308 | D50: =C51 -> 58447.251 | E50: =D51 -> 58596.249 | F50: =E51 -> 58755.678 | G50: =F51 -> 58924.672
B51: Closing Net PP&E | C51: =C50+C48-C49 -> 58447.251 | D51: =D50+D48-D49 -> 58596.249 | E51: =E50+E48-E49 -> 58755.678 | F51: =F50+F48-F49 -> 58924.672 | G51: =G50+G48-G49 -> 59103.805
B53: 5. Free Cash Flow to the Firm (FCFF)
B54: Particulars | C54: FY2027E | D54: FY2028E | E54: FY2029E | F54: FY2030E | G54: FY2031E
B55: NOPAT | C55: =C42 -> 12107.864 | D55: =D42 -> 12955.414 | E55: =E42 -> 13862.294 | F55: =F42 -> 14694.031 | G55: =G42 -> 15575.673
B56: (+) D&A | C56: =C49 -> 1462.1342 | D56: =D49 -> 1564.4836 | E56: =E49 -> 1673.9975 | F56: =F49 -> 1774.4373 | G56: =G49 -> 1880.9036
B57: (-) Capex | C57: =-C48 -> -1601.3851 | D57: =-D48 -> -1713.4821 | E57: =-E48 -> -1833.4258 | F57: =-F48 -> -1943.4314 | G57: =-G48 -> -2060.0373
B58: (-) Increase in NWC | C58: =-C47 -> -287.77376 | D58: =-D47 -> -263.18416 | E58: =-E47 -> -281.60705 | F58: =-F47 -> -258.2739 | G58: =-G47 -> -273.77033
B59: FCFF | C59: =C55+C56+C57+C58 -> 11680.839 | D59: =D55+D56+D57+D58 -> 12543.232 | E59: =E55+E56+E57+E58 -> 13421.258 | F59: =F55+F56+F57+F58 -> 14266.763 | G59: =G55+G56+G57+G58 -> 15122.769
B60: Discount Period (n) | C60: 0.5 | D60: =C60+1 -> 1.5 | E60: =D60+1 -> 2.5 | F60: =E60+1 -> 3.5 | G60: =F60+1 -> 4.5 | H60: Mid year convention
B61: Discount Factor @ WACC | C61: =1/(1+$C$35)^C60 -> 0.95400105 | D61: =1/(1+$C$35)^D60 -> 0.86825353 | E61: =1/(1+$C$35)^E60 -> 0.79021317 | F61: =1/(1+$C$35)^F60 -> 0.71918723 | G61: =1/(1+$C$35)^G60 -> 0.65454525
B62: PV of FCFF | C62: =C59*C61 -> 11143.533 | D62: =D59*D61 -> 10890.705 | E62: =E59*E61 -> 10605.655 | F62: =F59*F61 -> 10260.474 | G62: =G59*G61 -> 9898.5366
B64: 6. Valuation Summary
B66: Sum of PV of Explicit Period FCFF (FY2027E to FY2031E) | C66: =SUM(C62:G62) -> 52798.904
B67: Terminal Value (as at end of FY2031E) | C67: =G59*(1+C13)/(C35-C13) -> 413588.92
B68: PV of Terminal Value | C68: =C67*G61 -> 270712.66
B69: Enterprise Value | C69: =C66+C68 -> 323511.56
B70: Less: Total Debt (FY2026) | C70: =-'Data Sheet'!K59 -> -1478
B71: Add: Cash and Short-Term Investments (FY2026) | C71: ='Data Sheet'!K69 -> 3248
B72: Equity Value | C72: =C69+C70+C71 -> 325281.56
B73: Shares Outstanding (Crore) | C73: ='Data Sheet'!K93 -> 234.96 | H73: Face value of Rs. 1 per share, hence shares in crore equal equity share capital in Rs. crore
B74: Implied Value per Share (Rs.) | C74: =C72/C73 -> 1384.4125
B75: Current Market Price (Rs., 30-Jul-2026) | C75: 2108
B76: Implied Upside / (Downside) vs CMP | C76: =C74/C75-1 -> -0.34325782
B78: Note 1 | C78: The valuation represents a base case and is directly dependent on the stated assumptions for revenue growth, operating margin, WACC and terminal growth. The terminal value accounts for approximately 84 per cent of the enterprise value (Section 6), so the conclusion is particularly sensitive to the terminal growth and WACC assumptions; it should therefore be read alongside the Relative Valuation worksheet rather than in isolation.
B79: 7. Sensitivity Analysis: Implied Share Price (Rs.)
B80: WACC \ Terminal Growth (g)
B81: =C74 -> 1384.4125 | C81: 0.05 | D81: 0.055 | E81: 0.06 | F81: 0.065 | G81: 0.07
B82: =B83-0.005 -> 0.088758619 | C82: {=(SUMPRODUCT($C$59:$G$59,1/(1+$B82)^$C$60:$G$60)+($G$59*(1+C$81)/($B82-C$81))/(1+$B82)^$G$60+$C$70+$C$71)/$C$73} -> 1426.5689 | D82: {=(SUMPRODUCT($C$59:$G$59,1/(1+$B82)^$C$60:$G$60)+($G$59*(1+D$81)/($B82-D$81))/(1+$B82)^$G$60+$C$70+$C$71)/$C$73} -> 1609.208 | E82: {=(SUMPRODUCT($C$59:$G$59,1/(1+$B82)^$C$60:$G$60)+($G$59*(1+E$81)/($B82-E$81))/(1+$B82)^$G$60+$C$70+$C$71)/$C$73} -> 1855.3547 | F82: {=(SUMPRODUCT($C$59:$G$59,1/(1+$B82)^$C$60:$G$60)+($G$59*(1+F$81)/($B82-F$81))/(1+$B82)^$G$60+$C$70+$C$71)/$C$73} -> 2205.1046 | G82: {=(SUMPRODUCT($C$59:$G$59,1/(1+$B82)^$C$60:$G$60)+($G$59*(1+G$81)/($B82-G$81))/(1+$B82)^$G$60+$C$70+$C$71)/$C$73} -> 2741.302
B83: =B84-0.005 -> 0.093758619 | C83: {=(SUMPRODUCT($C$59:$G$59,1/(1+$B83)^$C$60:$G$60)+($G$59*(1+C$81)/($B83-C$81))/(1+$B83)^$G$60+$C$70+$C$71)/$C$73} -> 1266.6176 | D83: {=(SUMPRODUCT($C$59:$G$59,1/(1+$B83)^$C$60:$G$60)+($G$59*(1+D$81)/($B83-D$81))/(1+$B83)^$G$60+$C$70+$C$71)/$C$73} -> 1405.2773 | E83: {=(SUMPRODUCT($C$59:$G$59,1/(1+$B83)^$C$60:$G$60)+($G$59*(1+E$81)/($B83-E$81))/(1+$B83)^$G$60+$C$70+$C$71)/$C$73} -> 1585.0109 | F83: {=(SUMPRODUCT($C$59:$G$59,1/(1+$B83)^$C$60:$G$60)+($G$59*(1+F$81)/($B83-F$81))/(1+$B83)^$G$60+$C$70+$C$71)/$C$73} -> 1827.2417 | G83: {=(SUMPRODUCT($C$59:$G$59,1/(1+$B83)^$C$60:$G$60)+($G$59*(1+G$81)/($B83-G$81))/(1+$B83)^$G$60+$C$70+$C$71)/$C$73} -> 2171.4276
B84: =C35 -> 0.098758619 | C84: {=(SUMPRODUCT($C$59:$G$59,1/(1+$B84)^$C$60:$G$60)+($G$59*(1+C$81)/($B84-C$81))/(1+$B84)^$G$60+$C$70+$C$71)/$C$73} -> 1139.4725 | D84: {=(SUMPRODUCT($C$59:$G$59,1/(1+$B84)^$C$60:$G$60)+($G$59*(1+D$81)/($B84-D$81))/(1+$B84)^$G$60+$C$70+$C$71)/$C$73} -> 1247.9487 | E84: {=(SUMPRODUCT($C$59:$G$59,1/(1+$B84)^$C$60:$G$60)+($G$59*(1+E$81)/($B84-E$81))/(1+$B84)^$G$60+$C$70+$C$71)/$C$73} -> 1384.4125 | F84: {=(SUMPRODUCT($C$59:$G$59,1/(1+$B84)^$C$60:$G$60)+($G$59*(1+F$81)/($B84-F$81))/(1+$B84)^$G$60+$C$70+$C$71)/$C$73} -> 1561.2997 | G84: {=(SUMPRODUCT($C$59:$G$59,1/(1+$B84)^$C$60:$G$60)+($G$59*(1+G$81)/($B84-G$81))/(1+$B84)^$G$60+$C$70+$C$71)/$C$73} -> 1799.6944
B85: =B84+0.005 -> 0.10375862 | C85: {=(SUMPRODUCT($C$59:$G$59,1/(1+$B85)^$C$60:$G$60)+($G$59*(1+C$81)/($B85-C$81))/(1+$B85)^$G$60+$C$70+$C$71)/$C$73} -> 1035.9799 | D85: {=(SUMPRODUCT($C$59:$G$59,1/(1+$B85)^$C$60:$G$60)+($G$59*(1+D$81)/($B85-D$81))/(1+$B85)^$G$60+$C$70+$C$71)/$C$73} -> 1122.8856 | E85: {=(SUMPRODUCT($C$59:$G$59,1/(1+$B85)^$C$60:$G$60)+($G$59*(1+E$81)/($B85-E$81))/(1+$B85)^$G$60+$C$70+$C$71)/$C$73} -> 1229.6516 | F85: {=(SUMPRODUCT($C$59:$G$59,1/(1+$B85)^$C$60:$G$60)+($G$59*(1+F$81)/($B85-F$81))/(1+$B85)^$G$60+$C$70+$C$71)/$C$73} -> 1363.964 | G85: {=(SUMPRODUCT($C$59:$G$59,1/(1+$B85)^$C$60:$G$60)+($G$59*(1+G$81)/($B85-G$81))/(1+$B85)^$G$60+$C$70+$C$71)/$C$73} -> 1538.0625
B86: =B85+0.005 -> 0.10875862 | C86: {=(SUMPRODUCT($C$59:$G$59,1/(1+$B86)^$C$60:$G$60)+($G$59*(1+C$81)/($B86-C$81))/(1+$B86)^$G$60+$C$70+$C$71)/$C$73} -> 950.10144 | D86: {=(SUMPRODUCT($C$59:$G$59,1/(1+$B86)^$C$60:$G$60)+($G$59*(1+D$81)/($B86-D$81))/(1+$B86)^$G$60+$C$70+$C$71)/$C$73} -> 1021.0851 | E86: {=(SUMPRODUCT($C$59:$G$59,1/(1+$B86)^$C$60:$G$60)+($G$59*(1+E$81)/($B86-E$81))/(1+$B86)^$G$60+$C$70+$C$71)/$C$73} -> 1106.6269 | F86: {=(SUMPRODUCT($C$59:$G$59,1/(1+$B86)^$C$60:$G$60)+($G$59*(1+F$81)/($B86-F$81))/(1+$B86)^$G$60+$C$70+$C$71)/$C$73} -> 1211.7172 | G86: {=(SUMPRODUCT($C$59:$G$59,1/(1+$B86)^$C$60:$G$60)+($G$59*(1+G$81)/($B86-G$81))/(1+$B86)^$G$60+$C$70+$C$71)/$C$73} -> 1343.9216
B88: Note | C88: Each cell re-discounts the base case FCFF stream from Section 5 together with the terminal value, using the WACC shown in the row and the terminal growth rate shown in the column. The underlying cash flow projections remain unchanged. The base case (current WACC, g 6.0 per cent) is shaded.

Sheet Data for Relative Valuation
B3: S.No. | C3: Name | D3: CMP Rs. | E3: Mar Cap Rs.Cr. | F3: P/E | G3: NP 12M Rs.Cr. | H3: No. Eq. Shares Cr. | I3: Cash End Rs.Cr. | J3: EBIDT Ann Rs.Cr. | K3: Sales Rs.Cr. | L3: PAT 12M Rs.Cr. | M3: Debt Rs.Cr. | N3: Eq Cap Rs.Cr. | O3: EBIT
B4: 1 | C4: Hind. Unilever | D4: 2100.8 | E4: 493567.01 | F4: 44.76 | G4: 14971 | H4: 234.96 | I4: 3248 | J4: 15790 | K4: 66052 | L4: 11027.55 | M4: 1478 | N4: 235 | O4: 14457
B5: 2 | C5: ITC | D5: 280.95 | E5: 351768.6 | F5: 16.84 | G5: 21018.15 | H5: 1252.95 | I5: 3008.79 | J5: 30108.95 | K5: 78868.4 | L5: 20895.43 | M5: 2399.06 | N5: 1252.95 | O5: 28398.42
B6: 3 | C6: Nestle India | D6: 1509.6 | E6: 291136.62 | F6: 77.54 | G6: 3860.49 | H6: 192.83 | I6: 1340.87 | J6: 5342.42 | K6: 24436.62 | L6: 3754.89 | M6: 444.16 | N6: 192.83 | O6: 4643.19
B7: 4 | C7: Godrej Consumer | D7: 1070.4 | E7: 109524.34 | F7: 55.26 | G7: 1861.47 | H7: 102.33 | I7: 1005.41 | J7: 3368.97 | K7: 15177.9 | L7: 1981.93 | M7: 4420.52 | N7: 102.32 | O7: 3101.44
B8: 5 | C8: Marico | D8: 870.65 | E8: 112783.97 | F8: 64.36 | G8: 1813 | H8: 129.84 | I8: 493 | J8: 2524 | K8: 13611 | L8: 1752.37 | M8: 557 | N8: 130 | O8: 2322
B11: Nestle India | C11: 1509.6 | D11: 291136.62 | E11: 77.54 | F11: 3860.49 | G11: 192.83 | H11: 1340.87 | I11: 5342.42 | J11: 24436.62 | K11: 3754.89 | L11: 444.16 | M11: 192.83 | N11: 4643.19

Sheet Relative Valuation
B2: Comparable Company Valuation
D4: Market Data | J4: Financials | S4: Valuation
B5: Company | C5: Ticker | D5: Share Price | E5: Share Outstanding | F5: Equity Value | G5: Net Debt | H5: Enterprise Value | J5: Revenue | L5: EBITDA | N5: EBIT | P5: Net Income | S5: EV/Revenue | U5: EV/EBITDA | W5: EV/ EBIT | Y5: P/E
J6: 2026A | K6: 2027F | L6: 2026A | M6: 2027F | N6: 2026A | O6: 2027F | P6: 2026A | Q6: 2027F | S6: 2026A | T6: 2027F | U6: 2026A | V6: 2027F | W6: 2026A | X6: 2027F | Y6: 2026A | Z6: 2027F
B7: Hind. Unilever | D7: ='Data for Relative Valuation'!D4 -> 2100.8 | E7: ='Data for Relative Valuation'!H4 -> 234.96 | F7: =D7*E7 -> 493603.97 | G7: ='Data for Relative Valuation'!M4-'Data for Relative Valuation'!I4 -> -1770 | H7: =SUM(F7,G7) -> 491833.97 | J7: ='Data for Relative Valuation'!K4 -> 66052 | K7: 69625.44 | L7: ='Data for Relative Valuation'!J4 -> 15790 | M7: 17824.11 | N7: ='Data for Relative Valuation'!O4 -> 14457 | O7: 16361.98 | P7: ='Data for Relative Valuation'!L4 -> 11027.55 | Q7: 12107.86 | S7: =$H7/J7 -> 7.4461631 | T7: =$H7/K7 -> 7.063998 | U7: =$H7/L7 -> 31.148446 | V7: =$H7/M7 -> 27.593746 | W7: =$H7/N7 -> 34.020472 | X7: =$H7/O7 -> 30.059563 | Y7: =$F7/P7 -> 44.760982 | Z7: =$F7/Q7 -> 40.767235
B8: ITC | D8: ='Data for Relative Valuation'!D5 -> 280.95 | E8: ='Data for Relative Valuation'!H5 -> 1252.95 | F8: =D8*E8 -> 352016.3 | G8: ='Data for Relative Valuation'!M5-'Data for Relative Valuation'!I5 -> -609.73 | H8: =SUM(F8,G8) -> 351406.57 | J8: ='Data for Relative Valuation'!K5 -> 78868.4 | K8: 80761.5 | L8: ='Data for Relative Valuation'!J5 -> 30108.95 | M8: 26947.5 | N8: ='Data for Relative Valuation'!O5 -> 28398.42 | O8: 25416.6 | P8: ='Data for Relative Valuation'!L5 -> 20895.43 | Q8: 18701.4 | S8: =$H8/J8 -> 4.4556067 | T8: =$H8/K8 -> 4.3511645 | U8: =$H8/L8 -> 11.671167 | V8: =$H8/M8 -> 13.040415 | W8: =$H8/N8 -> 12.374159 | X8: =$H8/O8 -> 13.825869 | Y8: =$F8/P8 -> 16.846569 | Z8: =$F8/Q8 -> 18.822992
B9: Nestle India | D9: ='Data for Relative Valuation'!D6 -> 1509.6 | E9: ='Data for Relative Valuation'!H6 -> 192.83 | F9: =D9*E9 -> 291096.17 | G9: ='Data for Relative Valuation'!M6-'Data for Relative Valuation'!I6 -> -896.71 | H9: =SUM(F9,G9) -> 290199.46 | J9: ='Data for Relative Valuation'!K6 -> 24436.62 | K9: 27857.8 | L9: ='Data for Relative Valuation'!J6 -> 5342.42 | M9: 6304.1 | N9: ='Data for Relative Valuation'!O6 -> 4643.19 | O9: 5478.9 | P9: ='Data for Relative Valuation'!L6 -> 3754.89 | Q9: 4528.4 | S9: =$H9/J9 -> 11.875597 | T9: =$H9/K9 -> 10.417171 | U9: =$H9/L9 -> 54.319851 | V9: =$H9/M9 -> 46.033448 | W9: =$H9/N9 -> 62.500018 | X9: =$H9/O9 -> 52.966737 | Y9: =$F9/P9 -> 77.524553 | Z9: =$F9/Q9 -> 64.282344
B10: Godrej Consumer | D10: ='Data for Relative Valuation'!D7 -> 1070.4 | E10: ='Data for Relative Valuation'!H7 -> 102.33 | F10: =D10*E10 -> 109534.03 | G10: ='Data for Relative Valuation'!M7-'Data for Relative Valuation'!I7 -> 3415.11 | H10: =SUM(F10,G10) -> 112949.14 | J10: ='Data for Relative Valuation'!K7 -> 15177.9 | K10: 17909.9 | L10: ='Data for Relative Valuation'!J7 -> 3368.97 | M10: 3840.6 | N10: ='Data for Relative Valuation'!O7 -> 3101.44 | O10: 3535.6 | P10: ='Data for Relative Valuation'!L7 -> 1981.93 | Q10: 2209.8 | S10: =$H10/J10 -> 7.4416844 | T10: =$H10/K10 -> 6.30652 | U10: =$H10/L10 -> 33.526313 | V10: =$H10/M10 -> 29.409244 | W10: =$H10/N10 -> 36.41829 | X10: =$H10/O10 -> 31.946244 | Y10: =$F10/P10 -> 55.266347 | Z10: =$F10/Q10 -> 49.567396
B11: Marico | D11: ='Data for Relative Valuation'!D8 -> 870.65 | E11: ='Data for Relative Valuation'!H8 -> 129.84 | F11: =D11*E11 -> 113045.2 | G11: ='Data for Relative Valuation'!M8-'Data for Relative Valuation'!I8 -> 64 | H11: =SUM(F11,G11) -> 113109.2 | J11: ='Data for Relative Valuation'!K8 -> 13611 | K11: 15000 | L11: ='Data for Relative Valuation'!J8 -> 2524 | M11: 2978.3 | N11: ='Data for Relative Valuation'!O8 -> 2322 | O11: 2740 | P11: ='Data for Relative Valuation'!L8 -> 1752.37 | Q11: 2137.9 | S11: =$H11/J11 -> 8.3101312 | T11: =$H11/K11 -> 7.5406131 | U11: =$H11/L11 -> 44.813469 | V11: =$H11/M11 -> 37.977771 | W11: =$H11/N11 -> 48.711971 | X11: =$H11/O11 -> 41.280728 | Y11: =$F11/P11 -> 64.50989 | Z11: =$F11/Q11 -> 52.876746
B13: High | S13: =MAX(S8:S11) -> 11.875597 | T13: =MAX(T8:T11) -> 10.417171 | U13: =MAX(U8:U11) -> 54.319851 | V13: =MAX(V8:V11) -> 46.033448 | W13: =MAX(W8:W11) -> 62.500018 | X13: =MAX(X8:X11) -> 52.966737 | Y13: =MAX(Y8:Y11) -> 77.524553 | Z13: =MAX(Z8:Z11) -> 64.282344
B14: 75th Percentile | S14: =_xlfn.QUARTILE.INC(S8:S11,3) -> 9.2014977 | T14: =_xlfn.QUARTILE.INC(T8:T11,3) -> 8.2597525 | U14: =_xlfn.QUARTILE.INC(U8:U11,3) -> 47.190065 | V14: =_xlfn.QUARTILE.INC(V8:V11,3) -> 39.99169 | W14: =_xlfn.QUARTILE.INC(W8:W11,3) -> 52.158983 | X14: =_xlfn.QUARTILE.INC(X8:X11,3) -> 44.202231 | Y14: =_xlfn.QUARTILE.INC(Y8:Y11,3) -> 67.763556 | Z14: =_xlfn.QUARTILE.INC(Z8:Z11,3) -> 55.728146
B15: Average | S15: =AVERAGE(S8:S11) -> 8.0207549 | T15: =AVERAGE(T8:T11) -> 7.1538671 | U15: =AVERAGE(U8:U11) -> 36.0827 | V15: =AVERAGE(V8:V11) -> 31.615219 | W15: =AVERAGE(W8:W11) -> 40.00111 | X15: =AVERAGE(X8:X11) -> 35.004895 | Y15: =AVERAGE(Y8:Y11) -> 53.53684 | Z15: =AVERAGE(Z8:Z11) -> 46.38737
B16: Median | S16: =MEDIAN(S8:S11) -> 7.8759078 | T16: =MEDIAN(T8:T11) -> 6.9235665 | U16: =MEDIAN(U8:U11) -> 39.169891 | V16: =MEDIAN(V8:V11) -> 33.693508 | W16: =MEDIAN(W8:W11) -> 42.56513 | X16: =MEDIAN(X8:X11) -> 36.613486 | Y16: =MEDIAN(Y8:Y11) -> 59.888119 | Z16: =MEDIAN(Z8:Z11) -> 51.222071
B17: 25th Percentile | S17: =_xlfn.QUARTILE.INC(S8:S11,1) -> 6.695165 | T17: =_xlfn.QUARTILE.INC(T8:T11,1) -> 5.8176811 | U17: =_xlfn.QUARTILE.INC(U8:U11,1) -> 28.062526 | V17: =_xlfn.QUARTILE.INC(V8:V11,1) -> 25.317037 | W17: =_xlfn.QUARTILE.INC(W8:W11,1) -> 30.407257 | X17: =_xlfn.QUARTILE.INC(X8:X11,1) -> 27.416151 | Y17: =_xlfn.QUARTILE.INC(Y8:Y11,1) -> 45.661403 | Z17: =_xlfn.QUARTILE.INC(Z8:Z11,1) -> 41.881295
B18: Low | S18: =MIN(S8:S11) -> 4.4556067 | T18: =MIN(T8:T11) -> 4.3511645 | U18: =MIN(U8:U11) -> 11.671167 | V18: =MIN(V8:V11) -> 13.040415 | W18: =MIN(W8:W11) -> 12.374159 | X18: =MIN(X8:X11) -> 13.825869 | Y18: =MIN(Y8:Y11) -> 16.846569 | Z18: =MIN(Z8:Z11) -> 18.822992
B20: Titan Company Comparable Valuation | S20: =S5 -> EV/Revenue | U20: =U5 -> EV/EBITDA | W20: EV/ EBIT | Y20: =Y5 -> P/E
S21: 2026A | T21: 2027F | U21: 2026A | V21: 2027F | W21: 2026A | X21: 2027F | Y21: 2026A | Z21: 2027F
B22: Implied Enterprise Value | S22: =J7*S16 -> 520219.46 | T22: =K7*T16 -> 482056.37 | U22: =U16*L7 -> 618492.58 | V22: =V16*M7 -> 600556.78 | W22: =W16*N7 -> 615364.09 | X22: =X16*O7 -> 599069.13 | Y22: =Y24+Y23 -> 658649.22 | Z22: =Z24+Z23 -> 618419.67
B23: Net Debt | S23: =$G$7 -> -1770 | T23: =$G$7 -> -1770 | U23: =$G$7 -> -1770 | V23: =$G$7 -> -1770 | W23: =$G$7 -> -1770 | X23: =$G$7 -> -1770 | Y23: =$G$7 -> -1770 | Z23: =$G$7 -> -1770
B24: Implied Value of Equity | S24: =S22-S23 -> 521989.46 | T24: =T22-T23 -> 483826.37 | U24: =U22-U23 -> 620262.58 | V24: =V22-V23 -> 602326.78 | W24: =W22-W23 -> 617134.09 | X24: =X22-X23 -> 600839.13 | Y24: =Y16*P7 -> 660419.22 | Z24: =Z16*Q7 -> 620189.67
B25: No. of Shares | S25: =$E$7 -> 234.96 | T25: =$E$7 -> 234.96 | U25: =$E$7 -> 234.96 | V25: =$E$7 -> 234.96 | W25: =$E$7 -> 234.96 | X25: =$E$7 -> 234.96 | Y25: =$E$7 -> 234.96 | Z25: =$E$7 -> 234.96
B26: Implied Value per Share | S26: =S24/S25 -> 2221.6099 | T26: =T24/T25 -> 2059.1861 | U26: =U24/U25 -> 2639.8646 | V26: =V24/V25 -> 2563.529 | W26: =W24/W25 -> 2626.5496 | X26: =X24/X25 -> 2557.1975 | Y26: =Y24/Y25 -> 2810.773 | Z26: =Z24/Z25 -> 2639.5543
B27: Verdict | S27: {=_xlfn.IFS(S26>$D$7, "Undervalued",S26<$D$7,"Overvalued",S26=$D$7,"Fairly Valued")} -> Undervalued | T27: {=_xlfn.IFS(T26>$D$7, "Undervalued",T26<$D$7,"Overvalued",T26=$D$7,"Fairly Valued")} -> Overvalued | U27: {=_xlfn.IFS(U26>$D$7, "Undervalued",U26<$D$7,"Overvalued",U26=$D$7,"Fairly Valued")} -> Undervalued | V27: {=_xlfn.IFS(V26>$D$7, "Undervalued",V26<$D$7,"Overvalued",V26=$D$7,"Fairly Valued")} -> Undervalued | W27: {=_xlfn.IFS(W26>$D$7, "Undervalued",W26<$D$7,"Overvalued",W26=$D$7,"Fairly Valued")} -> Undervalued | X27: {=_xlfn.IFS(X26>$D$7, "Undervalued",X26<$D$7,"Overvalued",X26=$D$7,"Fairly Valued")} -> Undervalued | Y27: {=_xlfn.IFS(Y26>$D$7, "Undervalued",Y26<$D$7,"Overvalued",Y26=$D$7,"Fairly Valued")} -> Undervalued | Z27: {=_xlfn.IFS(Z26>$D$7, "Undervalued",Z26<$D$7,"Overvalued",Z26=$D$7,"Fairly Valued")} -> Undervalued
